Workbook

Sheet SEGMENT PULSE
A1: SEGMENT PULSE - Market Allocation Drivers | E1: Normal Demand Expected | H1: COMPETITIVE POSITIONING
A3: HIGH SEGMENT ANALYSIS | H3: Entity | I3: Price | J3: Attractiveness
A4: Zone | B4: My Market Share | C4: Est. Demand | D4: Awareness Gap | E4: Price Gap | F4: Attractiveness | G4: Allocation Flag | H4: My Product | I4: 53 | J4: 45.909363
A5: Center | B5: 19.407453 | C5: 6831.4236 | D5: -26.064972 | E5: 0.24561404 | F5: 65.870527 | G5: OK | H5: Competitors | I5: 55 | J5: 0
A6: West | B6: 34.88334 | C6: 8372.0015 | D6: 18.115448 | E6: -0.37984496 | F6: 55.693342 | G6: OK
A7: North | B7: 34.901804 | C7: 6840.7535 | D7: 22.591987 | E7: -0.046511628 | F7: 58.071712 | G7: OK
A8: East | B8: 0 | C8: 0 | D8: 0 | E8: 0 | F8: 0 | G8: NO PRESENCE: Zone Not Active
A9: South | B9: 0 | C9: 0 | D9: 0 | E9: 0 | F9: 0 | G9: NO PRESENCE: Zone Not Active
A12: LOW SEGMENT ANALYSIS
A13: Zone | B13: My Market Share | C13: Est. Demand | D13: Awareness Gap | E13: Price Gap | F13: Attractiveness | G13: Allocation Flag
A14: Center | B14: 17.054727 | C14: 12756.936 | D14: 0.53825856 | E14: 0.71604938 | F14: 89.511119 | G14: RISK: Losing Volume to Price
A15: West | B15: 11.641514 | C15: 5937.1721 | D15: -10.247892 | E15: 0.14666667 | F15: 65.26902 | G15: RISK: Losing Volume to Price
A16: North | B16: 12.859557 | C16: 6481.2166 | D16: 9.2327139 | E16: 0.0084033613 | F16: 89.031774 | G16: OK
A17: East | B17: 0 | C17: 0 | D17: 0 | E17: 0 | F17: 0 | G17: NO PRESENCE: Zone Not Active
A18: South | B18: 0 | C18: 0 | D18: 0 | E18: 0 | F18: 0 | G18: NO PRESENCE: Zone Not Active
H24: HIGH vs LOW SEGMENT GAP
H26: Metric | I26: High Segment | J26: Low Segment
H27: Awareness | I27: 39.075562 | J27: 39.075562
H28: Price Competitiveness | I28: 99.516059 | J28: 99.516059
H29: Attractiveness | I29: 45.909363 | J29: 45.909363

Sheet INNOVATION LAB
A1: INNOVATION LAB - Feature Selection
A2: Note: Innovations increase Attractiveness. Required for High Segment Allocation.
A4: Feature Name | B4: Decision (1=Yes) | C4: Est. Cost ($) | D4: Cost Details
A5: STAINLESS MATERIAL | B5: 0 | C5: 15000 | D5: $15,000 + $0.15/unit
A6: RECYCLABLE MATERIALS | B6: 0 | C6: 30000 | D6: $30,000 + $0.15/unit
A7: ENERGY EFFICIENCY | B7: 0 | C7: 30000 | D7: $30,000 + $0.15/unit
A8: LIGHTER AND MORE COMPACT | B8: 0 | C8: 30000 | D8: $30,000 + $0.30/unit
A9: IMPACT RESISTANCE | B9: 0 | C9: 30000 | D9: $30,000 + $0.30/unit
A10: NOISE REDUCTION | B10: 0 | C10: 45000 | D10: $45,000 + $0.30/unit
A11: IMPROVED BATTERY CAPACITY | B11: 0 | C11: 45000 | D11: $45,000 + $0.45/unit
A12: SELF-CLEANING | B12: 0 | C12: 45000 | D12: $45,000 + $0.45/unit
A13: SPEED SETTINGS | B13: 0 | C13: 45000 | D13: $45,000 + $0.45/unit
A14: DIGITAL CONTROLS | B14: 0 | C14: 45000 | D14: $45,000 + $0.45/unit
A15: VOICE ASSISTANCE INTEGRATION | B15: 0 | C15: 45000 | D15: $45,000 + $0.75/unit
A16: AUTOMATION AND PROGRAMMABILITY | B16: 0 | C16: 45000 | D16: $45,000 + $0.75/unit
... A18: MAPPING TECHNOLOGY | B18: 0 | C18: 100000 | D18: $100,000 + $1.00/unit
A20: TOTAL INNOVATION COST | C20: =SUMPRODUCT(B5:B18,C5:C18) -> 0

Sheet STRATEGY COCKPIT
A1: UNIT ECONOMICS CHEAT SHEET
A2: TV Cost/Spot | B2: Radio Cost/Spot | C2: Hiring Fee | D2: Salary/Person
A3: 3000 | B3: 300 | C3: 1100 | D3: 1500
A5: HOW TO USE: Adjust Yellow cells. Check Profit Projection. Go to UPLOAD_READY tabs to copy decisions.
A7: SECTION A: GLOBAL ALLOCATIONS
A9: TV Spots (Qty) | B9: 10 | C9: =B9*3000 -> 30000
A10: Brand Focus (0-100) | B10: 50 | C10: 0=Awareness focus, 100=Attributes focus
A13: SECTION B: ZONAL ALLOCATIONS
A15: Zone | B15: Last Sales | C15: Stockout? | D15: Target Demand | E15: Radio Spots (Qty) | F15: Headcount | G15: Price | H15: Avg Comp Price | I15: Payment | J15: A/R Discount% | K15: Est. Revenue | L15: Mkt Cost | M15: Contribution
A16: Center | B16: 2358 | C16: OK | D16: 2358 | E16: 10 | F16: 5 | G16: 103 | H16: 83 | J16: =IF(I16="A",0.13,IF(I16="B",0.075,IF(I16="C",0.025,0))) -> 0 | K16: =D16*G16*(1-J16) -> 242874 | L16: =(C9/5) + (E16*300) + (F16*1500) + (MAX(0, F16-5)*1100) -> 16500 | M16: =K16-L16 -> 226374
A17: West | B17: 2075 | C17: OK | D17: 2075 | E17: 8 | F17: 4 | G17: 76 | H17: 77 | J17: =IF(I17="A",0.13,IF(I17="B",0.075,IF(I17="C",0.025,0))) -> 0 | K17: =D17*G17*(1-J17) -> 157700 | L17: =(C9/5) + (E17*300) + (F17*1500) + (MAX(0, F17-5)*1100) -> 14400 | M17: =K17-L17 -> 143300
A18: North | B18: 8437 | C18: OK | D18: 8437 | E18: 6 | F18: 3 | G18: 86 | H18: 115 | J18: =IF(I18="A",0.13,IF(I18="B",0.075,IF(I18="C",0.025,0))) -> 0 | K18: =D18*G18*(1-J18) -> 725582 | L18: =(C9/5) + (E18*300) + (F18*1500) + (MAX(0, F18-5)*1100) -> 12300 | M18: =K18-L18 -> 713282
A19: East | B19: 0 | C19: OK | D19: 0 | E19: 7 | F19: 4 | G19: 0 | H19: 0 | J19: =IF(I19="A",0.13,IF(I19="B",0.075,IF(I19="C",0.025,0))) -> 0 | K19: =D19*G19*(1-J19) -> 0 | L19: =(C9/5) + (E19*300) + (F19*1500) + (MAX(0, F19-5)*1100) -> 14100 | M19: =K19-L19 -> -14100
A20: South | B20: 0 | C20: OK | D20: 0 | E20: 9 | F20: 5 | G20: 0 | H20: 0 | J20: =IF(I20="A",0.13,IF(I20="B",0.075,IF(I20="C",0.025,0))) -> 0 | K20: =D20*G20*(1-J20) -> 0 | L20: =(C9/5) + (E20*300) + (F20*1500) + (MAX(0, F20-5)*1100) -> 16200 | M20: =K20-L20 -> -16200
F30: ='INNOVATION LAB'!B5 -> 0

Sheet UPLOAD READY MARKETING
A1: MARKETING DECISIONS - ExSim Upload Format
A2: Copy these values to ExSim Marketing upload
A4: Marketing Campaigns | G4: Demand | J4: Pricing Strategy | N4: Channels
A5: Brand | B5: Zone | C5: Channel | D5: Amount | E5: Brand Focus | G5: Zone | H5: Demand | J5: Zone | K5: Brand | L5: Price | N5: Zone | O5: Payment | P5: Salespeople
A6: A | B6: All | C6: TV | D6: ='STRATEGY COCKPIT'!C9 -> 30000 | E6: ='STRATEGY COCKPIT'!B10 -> 50 | G6: Center | H6: ='STRATEGY COCKPIT'!D16 -> 2358 | J6: Center | K6: A | L6: ='STRATEGY COCKPIT'!G16 -> 103 | N6: Center | O6: ='STRATEGY COCKPIT'!I16 -> 0 | P6: ='STRATEGY COCKPIT'!F16 -> 5
A7: A | B7: Center | C7: Radio | D7: ='STRATEGY COCKPIT'!E16*'STRATEGY COCKPIT'!$B$3 -> 3000 | E7: ='STRATEGY COCKPIT'!B10 -> 50 | G7: West | H7: ='STRATEGY COCKPIT'!D17 -> 2075 | J7: West | K7: A | L7: ='STRATEGY COCKPIT'!G17 -> 76 | N7: West | O7: ='STRATEGY COCKPIT'!I17 -> 0 | P7: ='STRATEGY COCKPIT'!F17 -> 4
A8: A | B8: West | C8: Radio | D8: ='STRATEGY COCKPIT'!E17*'STRATEGY COCKPIT'!$B$3 -> 2400 | E8: ='STRATEGY COCKPIT'!B10 -> 50 | G8: North | H8: ='STRATEGY COCKPIT'!D18 -> 8437 | J8: North | K8: A | L8: ='STRATEGY COCKPIT'!G18 -> 86 | N8: North | O8: ='STRATEGY COCKPIT'!I18 -> 0 | P8: ='STRATEGY COCKPIT'!F18 -> 3
A9: A | B9: North | C9: Radio | D9: ='STRATEGY COCKPIT'!E18*'STRATEGY COCKPIT'!$B$3 -> 1800 | E9: ='STRATEGY COCKPIT'!B10 -> 50 | G9: East | H9: ='STRATEGY COCKPIT'!D19 -> 0 | J9: East | K9: A | L9: ='STRATEGY COCKPIT'!G19 -> 0 | N9: East | O9: ='STRATEGY COCKPIT'!I19 -> 0 | P9: ='STRATEGY COCKPIT'!F19 -> 4
A10: A | B10: East | C10: Radio | D10: ='STRATEGY COCKPIT'!E19*'STRATEGY COCKPIT'!$B$3 -> 2100 | E10: ='STRATEGY COCKPIT'!B10 -> 50 | G10: South | H10: ='STRATEGY COCKPIT'!D20 -> 0 | J10: South | K10: A | L10: ='STRATEGY COCKPIT'!G20 -> 0 | N10: South | O10: ='STRATEGY COCKPIT'!I20 -> 0 | P10: ='STRATEGY COCKPIT'!F20 -> 5
A11: A | B11: South | C11: Radio | D11: ='STRATEGY COCKPIT'!E20*'STRATEGY COCKPIT'!$B$3 -> 2700 | E11: ='STRATEGY COCKPIT'!B10 -> 50

Sheet UPLOAD READY INNOVATION
A1: INNOVATION DECISIONS - ExSim Upload Format
A2: Copy these values to ExSim Innovation upload
A4: Brand | B4: Improvement | C4: Value
A5: A | B5: STAINLESS MATERIAL | C5: ='INNOVATION LAB'!B5 -> 0
A6: A | B6: RECYCLABLE MATERIALS | C6: =[1]INNOVATION_LAB!B6 -> #REF!
A7: A | B7: ENERGY EFFICIENCY | C7: =[1]INNOVATION_LAB!B7 -> #REF!
A8: A | B8: LIGHTER AND MORE COMPACT | C8: =[1]INNOVATION_LAB!B8 -> #REF!
A9: A | B9: IMPACT RESISTANCE | C9: =[1]INNOVATION_LAB!B9 -> #REF!
A10: A | B10: NOISE REDUCTION | C10: =[1]INNOVATION_LAB!B10 -> #REF!
A11: A | B11: IMPROVED BATTERY CAPACITY | C11: =[1]INNOVATION_LAB!B11 -> #REF!
A12: A | B12: SELF-CLEANING | C12: =[1]INNOVATION_LAB!B12 -> #REF!
A13: A | B13: SPEED SETTINGS | C13: =[1]INNOVATION_LAB!B13 -> #REF!
A14: A | B14: DIGITAL CONTROLS | C14: =[1]INNOVATION_LAB!B14 -> #REF!
A15: A | B15: VOICE ASSISTANCE INTEGRATION | C15: =[1]INNOVATION_LAB!B15 -> #REF!
A16: A | B16: AUTOMATION AND PROGRAMMABILITY | C16: =[1]INNOVATION_LAB!B16 -> #REF!
A17: A | B17: MULTIFUNCTIONAL ACCESSORIES | C17: =[1]INNOVATION_LAB!B17 -> #REF!
A18: A | B18: MAPPING TECHNOLOGY | C18: =[1]INNOVATION_LAB!B18 -> #REF!

Sheet CROSS REFERENCE
A1: CROSS-REFERENCE SUMMARY - Upstream Support
A2: Key metrics from Production and Finance.
A4: Production (Capacity)
A5: Production Plan (Total Units) | B5: 0
A6: Avg Capacity Utilization | B6: 85.0%
A9: Finance (Budget)
A10: Budget Status | B10: Check Finance Dashboard
A11: Liquidity Status | B11: 🟡 Excess Cash
