Workbook

Sheet DEMAND
B1: Companies: | C1: 4 | L1: Period | M1: Region | N1: Per Company | O1: Total Market | P1: Market Share | Q1: Demand Projection | S1: Row Labels | T1: Sum of Total Market
L2: 1 | M2: Center | N2: 4100 | O2: =+N2*4 -> 16400 | P2: 0.25 | Q2: =+O2*P2 -> 4100 | S2: 1 | T2: 26400
B3: Seasonality | L3: 1 | M3: West | N3: 1800 | O3: =+N3*4 -> 7200 | P3: 0.25 | Q3: =+O3*P3 -> 1800 | S3: 2 | T3: 26800
B4: 1 | C4: 0.29 | L4: 1 | M4: North | N4: 700 | O4: =+N4*4 -> 2800 | P4: 0.25 | Q4: =+O4*P4 -> 700 | S4: 3 | T4: 47600
B5: 2 | C5: 0.28 | L5: 1 | M5: East | N5: 0 | O5: =+N5*4 -> 0 | P5: =+O5*4 -> 0 | Q5: =+O5*P5 -> 0 | S5: 4 | T5: 46000
B6: 3 | C6: 0.43 | L6: 1 | M6: South | N6: 0 | O6: =+N6*4 -> 0 | P6: =+O6*4 -> 0 | Q6: =+O6*P6 -> 0 | S6: 5 | T6: 42800
L7: 2 | M7: Center | N7: 3600 | O7: =+N7*4 -> 14400 | P7: 0.25 | Q7: =+O7*P7 -> 3600 | S7: 6 | T7: 69312
B8: Table I. 1 Target populations* per company by region and segment (in # of households) | L8: 2 | M8: West | N8: 1900 | O8: =+N8*4 -> 7600 | P8: 0.25 | Q8: =+O8*P8 -> 1900 | S8: 7 | T8: 64800
B9: Segment\Region | D9: Center | E9: West | F9: North | G9: East | H9: South | I9: Total | L9: 2 | M9: North | N9: 1200 | O9: =+N9*4 -> 4800 | P9: 0.25 | Q9: =+O9*P9 -> 1200 | S9: 8 | T9: 61600
B10: High | D10: 35200 | E10: 24000 | F10: 19600 | G10: 10000 | H10: 9600 | I10: =+SUM(D10:H10) -> 98400 | L10: 2 | M10: East | N10: 0 | O10: =+N10*4 -> 0 | P10: =+O10*4 -> 0 | Q10: =+O10*P10 -> 0 | S10: 9 | T10: 101200
B11: Low | D11: 74800 | E11: 51000 | F11: 50400 | G11: 40000 | H11: 20400 | I11: =+SUM(D11:H11) -> 236600 | L11: 2 | M11: South | N11: 0 | O11: =+N11*4 -> 0 | P11: =+O11*4 -> 0 | Q11: =+O11*P11 -> 0 | S11: 10 | T11: 78400
D12: =+SUM(D10:D11) -> 110000 | E12: =+SUM(E10:E11) -> 75000 | F12: =+SUM(F10:F11) -> 70000 | G12: =+SUM(G10:G11) -> 50000 | H12: =+SUM(H10:H11) -> 30000 | I12: =+SUM(D12:H12) -> 335000 | L12: 3 | M12: Center | N12: 6600 | O12: =+N12*4 -> 26400 | P12: 0.25 | Q12: =+O12*P12 -> 6600 | S12: 11 | T12: 74400
L13: 3 | M13: West | N13: 2700 | O13: =+N13*4 -> 10800 | P13: 0.25 | Q13: =+O13*P13 -> 2700 | S13: 12 | T13: 122800
B14: Total Demand | D14: Center | E14: West | F14: North | G14: East | H14: South | I14: Total | L14: 3 | M14: North | N14: 2600 | O14: =+N14*4 -> 10400 | P14: 0.25 | Q14: =+O14*P14 -> 2600 | S14: Grand Total | T14: 762112
B15: Year 1 | D15: =+SUM(D32:D34) -> 14300 | E15: =+SUM(E32:E34) -> 6400 | F15: =+SUM(F32:F34) -> 4500 | G15: =+SUM(G32:G34) -> 0 | H15: =+SUM(H32:H34) -> 0 | I15: =+SUM(I32:I34) -> 25200 | L15: 3 | M15: East | N15: 0 | O15: =+N15*4 -> 0 | P15: =+O15*4 -> 0 | Q15: =+O15*P15 -> 0
B16: Year 2 | D16: =+SUM(D35:D37) -> 20000 | E16: =+SUM(E35:E37) -> 9728 | F16: =+SUM(F35:F37) -> 9800 | G16: =+SUM(G35:G37) -> 0 | H16: =+SUM(H35:H37) -> 0 | I16: =+SUM(I35:I37) -> 39528 | L16: 3 | M16: South | N16: 0 | O16: =+N16*4 -> 0 | P16: =+O16*4 -> 0 | Q16: =+O16*P16 -> 0
B17: Year 3 | D17: 24000 | E17: 13132.8 | F17: 14700 | G17: 4100 | H17: 3000 | I17: =+SUM(I38:I40) -> 58932.8 | L17: 4 | M17: Center | N17: 6000 | O17: =+N17*4 -> 24000 | P17: 0.25 | Q17: =+O17*P17 -> 6000
B18: Year 4 | D18: 26400 | E18: 16416 | F18: 17640 | G18: 8200 | H18: 5400 | I18: =+SUM(I41:I43) -> 74056 | L18: 4 | M18: West | N18: 2800 | O18: =+N18*4 -> 11200 | P18: 0.25 | Q18: =+O18*P18 -> 2800
B19: Growth | L19: 4 | M19: North | N19: 2700 | O19: =+N19*4 -> 10800 | P19: 0.25 | Q19: =+O19*P19 -> 2700
B20: Year 2 | D20: =IFERROR(+D16/D15-1,0) -> 0.3986014 | E20: =IFERROR(+E16/E15-1,0) -> 0.52 | F20: =IFERROR(+F16/F15-1,0) -> 1.1777778 | G20: =IFERROR(+G16/G15-1,0) -> 0 | H20: =IFERROR(+H16/H15-1,0) -> 0 | I20: =IFERROR(+I16/I15-1,0) -> 0.56857143 | L20: 4 | M20: East | N20: 0 | O20: =+N20*4 -> 0 | P20: =+O20*4 -> 0 | Q20: =+O20*P20 -> 0
B21: Year 3 | D21: =IFERROR(+D17/D16-1,0) -> 0.2 | E21: =IFERROR(+E17/E16-1,0) -> 0.35 | F21: =IFERROR(+F17/F16-1,0) -> 0.5 | G21: =IFERROR(+G17/G16-1,0) -> 0 | H21: =IFERROR(+H17/H16-1,0) -> 0 | I21: =IFERROR(+I17/I16-1,0) -> 0.49091277 | L21: 4 | M21: South | N21: 0 | O21: =+N21*4 -> 0 | P21: =+O21*4 -> 0 | Q21: =+O21*P21 -> 0
B22: Year 4 | D22: =IFERROR(+D18/D17-1,0) -> 0.1 | E22: =IFERROR(+E18/E17-1,0) -> 0.25 | F22: =IFERROR(+F18/F17-1,0) -> 0.2 | G22: =IFERROR(+G18/G17-1,0) -> 1 | H22: =IFERROR(+H18/H17-1,0) -> 0.8 | I22: =IFERROR(+I18/I17-1,0) -> 0.25661771 | L22: 5 | M22: Center | N22: 5100 | O22: =+N22*4 -> 20400 | P22: 0.25 | Q22: =+O22*P22 -> 5100
L23: 5 | M23: West | N23: 2900 | O23: =+N23*4 -> 11600 | P23: 0.25 | Q23: =+O23*P23 -> 2900
L24: 5 | M24: North | N24: 2700 | O24: =+N24*4 -> 10800 | P24: 0.25 | Q24: =+O24*P24 -> 2700
B25: Penetration | D25: Center | E25: West | F25: North | G25: East | H25: South | I25: Total | L25: 5 | M25: East | N25: 0 | O25: =+N25*4 -> 0 | P25: =+O25*4 -> 0 | Q25: =+O25*P25 -> 0
B26: Year 1 | D26: =IFERROR(+D15/D$12,0) -> 0.13 | E26: =IFERROR(+E15/E$12,0) -> 0.085333333 | F26: =IFERROR(+F15/F$12,0) -> 0.064285714 | G26: =IFERROR(+G15/G$12,0) -> 0 | H26: =IFERROR(+H15/H$12,0) -> 0 | I26: =IFERROR(+I15/I$12,0) -> 0.075223881 | L26: 5 | M26: South | N26: 0 | O26: =+N26*4 -> 0 | P26: =+O26*4 -> 0 | Q26: =+O26*P26 -> 0
B27: Year 2 | D27: =IFERROR(+D16/D$12,0) -> 0.18181818 | E27: =IFERROR(+E16/E$12,0) -> 0.12970667 | F27: =IFERROR(+F16/F$12,0) -> 0.14 | G27: =IFERROR(+G16/G$12,0) -> 0 | H27: =IFERROR(+H16/H$12,0) -> 0 | I27: =IFERROR(+I16/I$12,0) -> 0.11799403 | L27: 6 | M27: Center | N27: 8900 | O27: =+N27*4 -> 35600 | P27: 0.25 | Q27: =+O27*P27 -> 8900
B28: Year 3 | D28: =IFERROR(+D17/D$12,0) -> 0.21818182 | E28: =IFERROR(+E17/E$12,0) -> 0.175104 | F28: =IFERROR(+F17/F$12,0) -> 0.21 | G28: =IFERROR(+G17/G$12,0) -> 0.082 | H28: =IFERROR(+H17/H$12,0) -> 0.1 | I28: =IFERROR(+I17/I$12,0) -> 0.17591881 | L28: 6 | M28: West | N28: 4028 | O28: =+N28*4 -> 16112 | P28: 0.25 | Q28: =+O28*P28 -> 4028
B29: Year 4 | D29: =IFERROR(+D18/D$12,0) -> 0.24 | E29: =IFERROR(+E18/E$12,0) -> 0.21888 | F29: =IFERROR(+F18/F$12,0) -> 0.252 | G29: =IFERROR(+G18/G$12,0) -> 0.164 | H29: =IFERROR(+H18/H$12,0) -> 0.18 | I29: =IFERROR(+I18/I$12,0) -> 0.22106269 | L29: 6 | M29: North | N29: 4400 | O29: =+N29*4 -> 17600 | P29: 0.25 | Q29: =+O29*P29 -> 4400
L30: 6 | M30: East | N30: 0 | O30: =+N30*4 -> 0 | P30: =+O30*4 -> 0 | Q30: =+O30*P30 -> 0
B31: Demand by period | C31: Period | D31: Center | E31: West | F31: North | G31: East | H31: South | I31: Total | L31: 6 | M31: South | N31: 0 | O31: =+N31*4 -> 0 | P31: =+O31*4 -> 0 | Q31: =+O31*P31 -> 0
B32: Year 1 | C32: 1 | D32: 4100 | E32: 1800 | F32: 700 | I32: =+SUM(D32:H32) -> 6600 | L32: 7 | M32: Center | N32: 6960 | O32: =+N32*4 -> 27840 | Q32: =+O32*P32 -> 0
B33: Year 1 | C33: 2 | D33: 3600 | E33: 1900 | F33: 1200 | I33: =+SUM(D33:H33) -> 6700 | L33: 7 | M33: West | N33: 3808.512 | O33: =+N33*4 -> 15234.048 | Q33: =+O33*P33 -> 0
B34: Year 1 | C34: 3 | D34: 6600 | E34: 2700 | F34: 2600 | I34: =+SUM(D34:H34) -> 11900 | L34: 7 | M34: North | N34: 4263 | O34: =+N34*4 -> 17052 | Q34: =+O34*P34 -> 0
B35: Year 2 | C35: 4 | D35: 6000 | E35: 2800 | F35: 2700 | I35: =+SUM(D35:H35) -> 11500 | L35: 7 | M35: East | N35: 1189 | O35: =+N35*4 -> 4756 | Q35: =+O35*P35 -> 0
B36: Year 2 | C36: 5 | D36: 5100 | E36: 2900 | F36: 2700 | I36: =+SUM(D36:H36) -> 10700 | L36: 7 | M36: South | N36: 870 | O36: =+N36*4 -> 3480 | Q36: =+O36*P36 -> 0
B37: Year 2 | C37: 6 | D37: 8900 | E37: 4028 | F37: 4400 | I37: =+SUM(D37:H37) -> 17328 | L37: 8 | M37: Center | N37: 6720 | O37: =+N37*4 -> 26880 | Q37: =+O37*P37 -> 0
B38: Year 3 | C38: 7 | D38: =+D$17*$C4 -> 6960 | E38: =+E$17*$C4 -> 3808.512 | F38: =+F$17*$C4 -> 4263 | G38: =+G$17*$C4 -> 1189 | H38: =+H$17*$C4 -> 870 | I38: =+SUM(D38:H38) -> 17090.512 | L38: 8 | M38: West | N38: 3677.184 | O38: =+N38*4 -> 14708.736 | Q38: =+O38*P38 -> 0
B39: Year 3 | C39: 8 | D39: =+D$17*$C5 -> 6720 | E39: =+E$17*$C5 -> 3677.184 | F39: =+F$17*$C5 -> 4116 | G39: =+G$17*$C5 -> 1148 | H39: =+H$17*$C5 -> 840 | I39: =+SUM(D39:H39) -> 16501.184 | L39: 8 | M39: North | N39: 4116 | O39: =+N39*4 -> 16464 | Q39: =+O39*P39 -> 0
B40: Year 3 | C40: 9 | D40: =+D$17*$C6 -> 10320 | E40: =+E$17*$C6 -> 5647.104 | F40: =+F$17*$C6 -> 6321 | G40: =+G$17*$C6 -> 1763 | H40: =+H$17*$C6 -> 1290 | I40: =+SUM(D40:H40) -> 25341.104 | L40: 8 | M40: East | N40: 1148 | O40: =+N40*4 -> 4592 | Q40: =+O40*P40 -> 0
B41: Year 4 | C41: 10 | D41: =+D$18*$C4 -> 7656 | E41: =+E$18*$C4 -> 4760.64 | F41: =+F$18*$C4 -> 5115.6 | G41: =+G$18*$C4 -> 2378 | H41: =+H$18*$C4 -> 1566 | I41: =+SUM(D41:H41) -> 21476.24 | L41: 8 | M41: South | N41: 840 | O41: =+N41*4 -> 3360 | Q41: =+O41*P41 -> 0
B42: Year 4 | C42: 11 | D42: =+D$18*$C5 -> 7392 | E42: =+E$18*$C5 -> 4596.48 | F42: =+F$18*$C5 -> 4939.2 | G42: =+G$18*$C5 -> 2296 | H42: =+H$18*$C5 -> 1512 | I42: =+SUM(D42:H42) -> 20735.68 | L42: 9 | M42: Center | N42: 10320 | O42: =+N42*4 -> 41280 | Q42: =+O42*P42 -> 0
B43: Year 4 | C43: 12 | D43: =+D$18*$C6 -> 11352 | E43: =+E$18*$C6 -> 7058.88 | F43: =+F$18*$C6 -> 7585.2 | G43: =+G$18*$C6 -> 3526 | H43: =+H$18*$C6 -> 2322 | I43: =+SUM(D43:H43) -> 31844.08 | L43: 9 | M43: West | N43: 5647.104 | O43: =+N43*4 -> 22588.416 | Q43: =+O43*P43 -> 0
L44: 9 | M44: North | N44: 6321 | O44: =+N44*4 -> 25284 | Q44: =+O44*P44 -> 0
L45: 9 | M45: East | N45: 1763 | O45: =+N45*4 -> 7052 | Q45: =+O45*P45 -> 0
L46: 9 | M46: South | N46: 1290 | O46: =+N46*4 -> 5160 | Q46: =+O46*P46 -> 0
L47: 10 | M47: Center | N47: 7656 | O47: =+N47*4 -> 30624 | Q47: =+O47*P47 -> 0
L48: 10 | M48: West | N48: 4760.64 | O48: =+N48*4 -> 19042.56 | Q48: =+O48*P48 -> 0
L49: 10 | M49: North | N49: 5115.6 | O49: =+N49*4 -> 20462.4 | Q49: =+O49*P49 -> 0
L50: 10 | M50: East | N50: 2378 | O50: =+N50*4 -> 9512 | Q50: =+O50*P50 -> 0
L51: 10 | M51: South | N51: 1566 | O51: =+N51*4 -> 6264 | Q51: =+O51*P51 -> 0
L52: 11 | M52: Center | N52: 7392 | O52: =+N52*4 -> 29568 | Q52: =+O52*P52 -> 0
L53: 11 | M53: West | N53: 4596.48 | O53: =+N53*4 -> 18385.92 | Q53: =+O53*P53 -> 0
L54: 11 | M54: North | N54: 4939.2 | O54: =+N54*4 -> 19756.8 | Q54: =+O54*P54 -> 0
L55: 11 | M55: East | N55: 2296 | O55: =+N55*4 -> 9184 | Q55: =+O55*P55 -> 0
... L61: 12 | M61: South | N61: 2322 | O61: =+N61*4 -> 9288 | Q61: =+O61*P61 -> 0

Sheet INPUTS_MASTER
A1: Period | B1: Company | C1: Region | D1: Run Type | E1: Price | F1: TV Spots | G1: TV Spend | H1: Radio Spots | I1: Radio Spend | J1: Total Ad Spend | K1: Feature Focus % | L1: Salespeople | M1: Payment Term | N1: Projected demand
A2: 6 | B2: C1 | C2: Center | D2: Real | E2: 68 | F2: 35 | G2: =3000*F2/COUNTIF($A:$A,A2) -> 35000 | H2: 210 | I2: =+H2*300 -> 63000 | J2: =+G2+I2 -> 98000 | K2: 50 | L2: 17 | M2: B
A3: 6 | B3: C1 | C3: West | D3: Real | E3: 68 | F3: 35 | G3: =3000*F3/COUNTIF($A:$A,A3) -> 35000 | H3: 102 | I3: =+H3*300 -> 30600 | J3: =+G3+I3 -> 65600 | K3: 50 | L3: 13 | M3: B
A4: 6 | B4: C1 | C4: North | D4: Real | E4: 91 | F4: 35 | G4: =3000*F4/COUNTIF($A:$A,A4) -> 35000 | H4: 82 | I4: =+H4*300 -> 24600 | J4: =+G4+I4 -> 59600 | K4: 50 | L4: 14 | M4: B
A5: 7 | B5: C1 | C5: Center | D5: MarketTest | E5: 69 | F5: 35 | G5: =3000*F5/COUNTIF($A:$A,A5) -> 21000 | H5: 210 | I5: =+H5*300 -> 63000 | J5: =+G5+I5 -> 84000 | K5: 50 | L5: 17 | M5: B
A6: 7 | B6: C1 | C6: West | D6: MarketTest | E6: 69 | F6: 35 | G6: =3000*F6/COUNTIF($A:$A,A6) -> 21000 | H6: 102 | I6: =+H6*300 -> 30600 | J6: =+G6+I6 -> 51600 | K6: 50 | L6: 13 | M6: B
A7: 7 | B7: C1 | C7: North | D7: MarketTest | E7: 92 | F7: 35 | G7: =3000*F7/COUNTIF($A:$A,A7) -> 21000 | H7: 82 | I7: =+H7*300 -> 24600 | J7: =+G7+I7 -> 45600 | K7: 50 | L7: 14 | M7: B
A8: 7 | B8: C1 | C8: East | D8: MarketTest | E8: 65 | F8: 35 | G8: =3000*F8/COUNTIF($A:$A,A8) -> 21000 | H8: 40 | I8: =+H8*300 -> 12000 | J8: =+G8+I8 -> 33000 | K8: 50 | L8: 7 | M8: A
A9: 7 | B9: C1 | C9: South | D9: MarketTest | E9: 65 | F9: 35 | G9: =3000*F9/COUNTIF($A:$A,A9) -> 21000 | H9: 40 | I9: =+H9*300 -> 12000 | J9: =+G9+I9 -> 33000 | K9: 50 | L9: 7 | M9: A

Sheet INNOVATION
A1: ID | B1: NAME AND DESCRIPTION | C1: COST INI | D1: COST COGS | E1: Innovation | F1: CLASSIFICATION | G1: High | H1: Low | I1: Rationale | J1: PERIOD | N1: Improvements | O1: A1 - Maison Sigma - A | P1: A2 - Odisseum - A | Q1: A3 - AirFlow Six - A | R1: A4 - Electron - A
A2: 1 | B2: Stainless material – makes the appliance attractive and durable | C2: 15000 | D2: 0.15 | E2: Stainless material | F2: Performance | G2: 5 | H2: 3 | I2: High values premium aesthetics; Low values durability | J2: 7 | L2: High segment → values sophistication, performance, advanced features, technology | N2: STAINLESS MATERIAL | O2: ​ | P2: ✔ | Q2: ​ | R2: ✔
A3: 2 | B3: Recyclable materials – environmentally friendly, recyclable | C3: 30000 | D3: 0.15 | E3: Recyclable materials | F3: Eco-friendliness | G3: 6 | H3: 2 | I3: High values sustainability; Low less concerned | J3: 0 | L3: Low segment → values convenience, efficiency, operating cost, ease of use | N3: RECYCLABLE MATERIALS | O3: ​ | P3: ✔ | Q3: ​ | R3: ​
A4: 3 | B4: Energy efficiency – uses less electric power | C4: 30000 | D4: 0.15 | E4: Energy efficiency | F4: Efficiency | G4: 4 | H4: 6 | I4: High moderate interest; Low values cost savings | J4: 0 | N4: ENERGY EFFICIENCY | O4: ✔ | P4: ✔ | Q4: ​ | R4: ✔
A5: 4 | B5: Lighter and more compact – easier installation | C5: 30000 | D5: 0.3 | E5: Lighter/compact | F5: Convenience | G5: 5 | H5: 4 | I5: High values space (urban); Low values convenience | J5: 0 | L5: High segment → TV | N5: LIGHTER AND MORE COMPACT | O5: ✔ | P5: ​ | Q5: ​ | R5: ✔
A6: 5 | B6: Impact-resistance – more resistant frame | C6: 30000 | D6: 0.3 | E6: Impact resistance | F6: Performance | G6: 4 | H6: 6 | I6: High moderate; Low values practical durability | J6: 0 | L6: Low segment → Radio | N6: IMPACT RESISTANCE | O6: ​ | P6: ✔ | Q6: ​ | R6: ​
A7: 6 | B7: Noise reduction – less noisy operation | C7: 45000 | D7: 0.3 | E7: Noise reduction | F7: Convenience | G7: 6 | H7: 3 | I7: High values quiet premium experience; Low less priority | J7: 0 | N7: NOISE REDUCTION | O7: ​ | P7: ✔ | Q7: ​ | R7: ​
A8: 7 | B8: Improved battery capacity – longer performance per charge | C8: 45000 | D8: 0.45 | E8: Improved battery | F8: Performance | G8: 6 | H8: 5 | I8: Both value performance, High slightly more | J8: 0 | N8: IMPROVED BATTERY CAPACITY | O8: ✔ | P8: ✔ | Q8: ​ | R8: ​
A9: 8 | B9: Self-cleaning – automatic container cleansing | C9: 45000 | D9: 0.45 | E9: Self-cleaning | F9: Convenience | G9: 7 | H9: 2 | I9: High values luxury convenience; Low sees as unnecessary | J9: 0 | N9: SELF-CLEANING | O9: ✔ | P9: ​ | Q9: ​ | R9: ​
A10: 9 | B10: Speed settings – three operating speeds | C10: 45000 | D10: 0.45 | E10: Speed settings | F10: Extra features | G10: 5 | H10: 2 | I10: High values customization; Low prefers simple | J10: 0 | N10: SPEED SETTINGS | O10: ​ | P10: ✔ | Q10: ​ | R10: ​
A11: 10 | B11: Digital controls – luminous digital display | C11: 45000 | D11: 0.45 | E11: Digital controls | F11: Extra features | G11: 8 | H11: 1 | I11: High loves tech interface; Low intimidated | J11: 0 | N11: DIGITAL CONTROLS | O11: ✔ | P11: ✔ | Q11: ​ | R11: ​
A12: 11 | B12: Voice assistance integration – Siri/Alexa control | C12: 45000 | D12: 0.75 | E12: Voice assistance | F12: Extra features | G12: 8 | H12: 1 | I12: High early adopters; Low unnecessary complexity | J12: 0 | N12: VOICE ASSISTANCE INTEGRATION | O12: ​ | P12: ​ | Q12: ​ | R12: ​
A13: 12 | B13: Automation and programmability – automatic start/end | C13: 45000 | D13: 0.75 | E13: Automation/programmability | F13: Extra features | G13: 7 | H13: 2 | I13: High values smart features; Low prefers manual control | J13: 0 | N13: AUTOMATION AND PROGRAMMABILITY | O13: ✔ | P13: ✔ | Q13: ​ | R13: ​
A14: 13 | B14: Multifunctional accessories – compatibility with accessories | C14: 100000 | D14: 1 | E14: Multifunctional accessories | F14: Extra features | G14: 5 | H14: 3 | I14: High values versatility; Low basic use sufficient | J14: 0 | N14: MULTIFUNCTIONAL ACCESSORIES | O14: ​ | P14: ​ | Q14: ​ | R14: ​
A15: 14 | B15: Mapping technology – efficient navigation and obstacle avoidance | C15: 100000 | D15: 1 | E15: Mapping technology | F15: Efficiency | G15: 8 | H15: 1 | I15: High smart home integration; Low overkill | J15: 0 | N15: MAPPING TECHNOLOGY | O15: ​ | P15: ​ | Q15: ​ | R15: ​

Sheet MARKET_DATA
A1: Period | B1: Company | C1: Region | D1: Segment | E1: Run Type | F1: Market Share Region % | G1: Market Share Segment % | H1: Price | I1: Awareness % | J1: Attractiveness % | K1: Salesforce Effectiveness %
A2: 6 | B2: A1 | C2: Center | D2: High | E2: Real | F2: 25 | G2: 25 | H2: 68 | I2: 42.39 | J2: 20 | K2: 94.44
A3: 6 | B3: A2 | C3: Center | D3: High | E3: Real | F3: 25 | G3: 25 | H3: 68 | I3: 42.39 | J3: 20 | K3: 94.44
A4: 6 | B4: A3 | C4: Center | D4: High | E4: Real | F4: 25 | G4: 25 | H4: 68 | I4: 42.39 | J4: 20 | K4: 94.44
A5: 6 | B5: A4 | C5: Center | D5: High | E5: Real | F5: 25 | G5: 25 | H5: 68 | I5: 42.39 | J5: 20 | K5: 94.44
A6: 6 | B6: A1 | C6: Center | D6: Low | E6: Real | F6: 25 | G6: 25 | H6: 68 | I6: 28.72 | J6: 20 | K6: 94.44
A7: 6 | B7: A2 | C7: Center | D7: Low | E7: Real | F7: 25 | G7: 25 | H7: 68 | I7: 28.72 | J7: 20 | K7: 94.44
A8: 6 | B8: A3 | C8: Center | D8: Low | E8: Real | F8: 25 | G8: 25 | H8: 68 | I8: 28.72 | J8: 20 | K8: 94.44
A9: 6 | B9: A4 | C9: Center | D9: Low | E9: Real | F9: 25 | G9: 25 | H9: 68 | I9: 28.72 | J9: 20 | K9: 94.44
A10: 6 | B10: A1 | C10: West | D10: High | E10: Real | F10: 25 | G10: 25 | H10: 68 | I10: 34.58 | J10: 20 | K10: 81.55
A11: 6 | B11: A2 | C11: West | D11: High | E11: Real | F11: 25 | G11: 25 | H11: 68 | I11: 34.58 | J11: 20 | K11: 81.55
A12: 6 | B12: A3 | C12: West | D12: High | E12: Real | F12: 25 | G12: 25 | H12: 68 | I12: 34.58 | J12: 20 | K12: 81.55
A13: 6 | B13: A4 | C13: West | D13: High | E13: Real | F13: 25 | G13: 25 | H13: 68 | I13: 34.58 | J13: 20 | K13: 81.55
... A40: 6 | B40: A3 | C40: South | D40: Low | E40: Real | F40: 0 | G40: 0 | H40: 0 | I40: 0 | J40: 0 | K40: 0
A41: 6 | B41: A4 | C41: South | D41: Low | E41: Real | F41: 0 | G41: 0 | H41: 0 | I41: 0 | J41: 0 | K41: 0 | L41: Period | M41: Company | N41: Region | O41: Segment | P41: Run Type | Q41: Market Share Region % | R41: Market Share Segment % | S41: Price | T41: Awareness % | U41: Attractiveness % | V41: Salesforce Effectiveness %
A42: 7 | B42: A1 | C42: Center | D42: High | E42: SIM1 | F42: 38.2 | G42: 33.1 | H42: 78.00 | I42: 60.71 | J42: 76.51 | K42: 94.44 | L42: 7 | M42: A1 | N42: Center | O42: High | P42: Real | Q42: 38.2 | R42: 33.1 | S42: 78 | T42: 60.71 | U42: 76.51 | V42: 94.44
A43: 7 | B43: A2 | C43: Center | D43: High | E43: SIM1 | F43: 7.9 | G43: 24.3 | H43: 102.00 | I43: 72.62 | J43: 84.14 | K43: 94.44 | L43: 7 | M43: A2 | N43: Center | O43: High | P43: Real | Q43: 7.9 | R43: 24.3 | S43: 102 | T43: 72.62 | U43: 84.14 | V43: 94.44
A44: 7 | B44: A3 | C44: Center | D44: High | E44: SIM1 | F44: 37.8 | G44: 22.0 | H44: 54.00 | I44: 61.02 | J44: 20.00 | K44: 94.44 | L44: 7 | M44: A3 | N44: Center | O44: High | P44: Real | Q44: 37.8 | R44: 22 | S44: 54 | T44: 61.02 | U44: 20 | V44: 94.44
A45: 7 | B45: A4 | C45: Center | D45: High | E45: SIM1 | F45: 16.1 | G45: 20.7 | H45: 90.00 | I45: 67.56 | J45: 39.85 | K45: 94.44 | L45: 7 | M45: A4 | N45: Center | O45: High | P45: Real | Q45: 16.1 | R45: 20.7 | S45: 90 | T45: 67.56 | U45: 39.85 | V45: 94.44
A46: 7 | B46: A1 | C46: Center | D46: Low | E46: SIM1 | G46: 40.7 | I46: 40.99 | J46: 82.42 | L46: 7 | M46: A1 | N46: Center | O46: Low | P46: Real | Q46: 38.2 | R46: 40.7 | S46: 78 | T46: 40.99 | U46: 82.42 | V46: 94.44
A47: 7 | B47: A2 | C47: Center | D47: Low | E47: SIM1 | G47: 0.2 | I47: 61.69 | J47: 96.32 | L47: 7 | M47: A2 | N47: Center | O47: Low | P47: Real | Q47: 7.9 | R47: 0.2 | S47: 102 | T47: 61.69 | U47: 96.32 | V47: 94.44
A48: 7 | B48: A3 | C48: Center | D48: Low | E48: SIM1 | G48: 45.2 | I48: 45.93 | J48: 20.00 | L48: 7 | M48: A3 | N48: Center | O48: Low | P48: Real | Q48: 37.8 | R48: 45.2 | S48: 54 | T48: 45.93 | U48: 20 | V48: 94.44
A49: 7 | B49: A4 | C49: Center | D49: Low | E49: SIM1 | G49: 13.9 | I49: 48.83 | J49: 53.10 | L49: 7 | M49: A4 | N49: Center | O49: Low | P49: Real | Q49: 16.1 | R49: 13.9 | S49: 90 | T49: 48.83 | U49: 53.1 | V49: 94.44
A50: 7 | B50: A1 | C50: West | D50: High | E50: SIM1 | F50: 44.8 | G50: 34.3 | H50: 78.00 | I50: 53.67 | J50: 76.51 | K50: 81.55 | L50: 7 | M50: A1 | N50: West | O50: High | P50: Real | Q50: 44.8 | R50: 34.3 | S50: 78 | T50: 53.67 | U50: 76.51 | V50: 81.55
A51: 7 | B51: A2 | C51: West | D51: High | E51: SIM1 | F51: 8.1 | G51: 24.8 | H51: 102.00 | I51: 64.50 | J51: 84.14 | K51: 81.55 | L51: 7 | M51: A2 | N51: West | O51: High | P51: Real | Q51: 8.1 | R51: 24.8 | S51: 102 | T51: 64.5 | U51: 84.14 | V51: 81.55
A52: 7 | B52: A3 | C52: West | D52: High | E52: SIM1 | F52: 28.0 | G52: 19.5 | H52: 82.00 | I52: 53.54 | J52: 20.00 | K52: 81.55 | L52: 7 | M52: A3 | N52: West | O52: High | P52: Real | Q52: 28 | R52: 19.5 | S52: 82 | T52: 53.54 | U52: 20 | V52: 81.55
A53: 7 | B53: A4 | C53: West | D53: High | E53: SIM1 | F53: 19.0 | G53: 21.4 | H53: 90.00 | I53: 60.03 | J53: 39.85 | K53: 81.55 | L53: 7 | M53: A4 | N53: West | O53: High | P53: Real | Q53: 19 | R53: 21.4 | S53: 90 | T53: 60.03 | U53: 39.85 | V53: 81.55
A54: 7 | B54: A1 | C54: West | D54: Low | E54: SIM1 | G54: 49.8 | I54: 33.05 | J54: 82.42 | L54: 7 | M54: A1 | N54: West | O54: Low | P54: Real | Q54: 44.8 | R54: 49.8 | S54: 78 | T54: 33.05 | U54: 82.42 | V54: 81.55
A55: 7 | B55: A2 | C55: West | D55: Low | E55: SIM1 | G55: 0.3 | I55: 49.41 | J55: 96.32 | L55: 7 | M55: A2 | N55: West | O55: Low | P55: Real | Q55: 8.1 | R55: 0.3 | S55: 102 | T55: 49.41 | U55: 96.32 | V55: 81.55
A56: 7 | B56: A3 | C56: West | D56: Low | E56: SIM1 | G56: 32.1 | I56: 37.97 | J56: 20.00 | L56: 7 | M56: A3 | N56: West | O56: Low | P56: Real | Q56: 28 | R56: 32.1 | S56: 82 | T56: 37.97 | U56: 20 | V56: 81.55
A57: 7 | B57: A4 | C57: West | D57: Low | E57: SIM1 | G57: 17.9 | I57: 39.10 | J57: 53.10 | L57: 7 | M57: A4 | N57: West | O57: Low | P57: Real | Q57: 19 | R57: 17.9 | S57: 90 | T57: 39.1 | U57: 53.1 | V57: 81.55
A58: 7 | B58: A1 | C58: North | D58: High | E58: SIM1 | F58: 40.2 | G58: 36.4 | H58: 105.00 | I58: 48.17 | J58: 76.51 | K58: 95.32 | L58: 7 | M58: A1 | N58: North | O58: High | P58: Real | Q58: 40.2 | R58: 36.4 | S58: 105 | T58: 48.17 | U58: 76.51 | V58: 95.32
A59: 7 | B59: A2 | C59: North | D59: High | E59: SIM1 | F59: 6.3 | G59: 18.3 | H59: 137.00 | I59: 58.59 | J59: 84.14 | K59: 95.32 | L59: 7 | M59: A2 | N59: North | O59: High | P59: Real | Q59: 6.3 | R59: 18.3 | S59: 137 | T59: 58.59 | U59: 84.14 | V59: 95.32
A60: 7 | B60: A3 | C60: North | D60: High | E60: SIM1 | F60: 36.7 | G60: 23.4 | H60: 91.00 | I60: 48.24 | J60: 20.00 | K60: 95.32 | L60: 7 | M60: A3 | N60: North | O60: High | P60: Real | Q60: 36.7 | R60: 23.4 | S60: 91 | T60: 48.24 | U60: 20 | V60: 95.32
A61: 7 | B61: A4 | C61: North | D61: High | E61: SIM1 | F61: 16.8 | G61: 21.9 | H61: 120.00 | I61: 53.49 | J61: 39.85 | K61: 95.32 | L61: 7 | M61: A4 | N61: North | O61: High | P61: Real | Q61: 16.8 | R61: 21.9 | S61: 120 | T61: 53.49 | U61: 39.85 | V61: 95.32
A62: 7 | B62: A1 | C62: North | D62: Low | E62: SIM1 | G62: 42.2 | I62: 32.54 | J62: 82.42 | L62: 7 | M62: A1 | N62: North | O62: Low | P62: Real | Q62: 40.2 | R62: 42.2 | S62: 105 | T62: 32.54 | U62: 82.42 | V62: 95.32
A63: 7 | B63: A2 | C63: North | D63: Low | E63: SIM1 | G63: 0.1 | I63: 46.83 | J63: 96.32 | L63: 7 | M63: A2 | N63: North | O63: Low | P63: Real | Q63: 6.3 | R63: 0.1 | S63: 137 | T63: 46.83 | U63: 96.32 | V63: 95.32
A64: 7 | B64: A3 | C64: North | D64: Low | E64: SIM1 | G64: 43.7 | I64: 36.87 | J64: 20.00 | L64: 7 | M64: A3 | N64: North | O64: Low | P64: Real | Q64: 36.7 | R64: 43.7 | S64: 91 | T64: 36.87 | U64: 20 | V64: 95.32
A65: 7 | B65: A4 | C65: North | D65: Low | E65: SIM1 | G65: 14.1 | I65: 38.67 | J65: 53.10 | L65: 7 | M65: A4 | N65: North | O65: Low | P65: Real | Q65: 16.8 | R65: 14.1 | S65: 120 | T65: 38.67 | U65: 53.1 | V65: 95.32
A66: 7 | B66: A1 | C66: East | D66: High | E66: SIM1 | F66: 18.0 | G66: 28.2 | H66: 105.00 | I66: 31.68 | J66: 91.10 | K66: 63.21 | L66: 7 | M66: A1 | N66: East | O66: High | P66: Real | Q66: 18 | R66: 28.2 | S66: 105 | T66: 31.68 | U66: 91.1 | V66: 63.21
A67: 7 | B67: A2 | C67: East | D67: High | E67: SIM1 | F67: 30.1 | G67: 40.5 | H67: 114.00 | I67: 43.37 | J67: 93.54 | K67: 87.01 | L67: 7 | M67: A2 | N67: East | O67: High | P67: Real | Q67: 30.1 | R67: 40.5 | S67: 114 | T67: 43.37 | U67: 93.54 | V67: 87.01
A68: 7 | B68: A3 | C68: East | D68: High | E68: SIM1 | F68: 24.2 | G68: 13.2 | H68: 20.00 | I68: 33.63 | J68: 20.00 | K68: 96.82 | L68: 7 | M68: A3 | N68: East | O68: High | P68: Real | Q68: 24.2 | R68: 13.2 | S68: 20 | T68: 33.63 | U68: 20 | V68: 96.82
A69: 7 | B69: A4 | C69: East | D69: High | E69: SIM1 | F69: 27.7 | G69: 18.2 | H69: 75.00 | I69: 43.00 | J69: 42.22 | K69: 0.00 | L69: 7 | M69: A4 | N69: East | O69: High | P69: Real | Q69: 27.7 | R69: 18.2 | S69: 75 | T69: 43 | U69: 42.22 | V69: 0
A70: 7 | B70: A1 | C70: East | D70: Low | E70: SIM1 | G70: 14.6 | I70: 16.65 | J70: 87.16 | L70: 7 | M70: A1 | N70: East | O70: Low | P70: Real | Q70: 18 | R70: 14.6 | S70: 105 | T70: 16.65 | U70: 87.16 | V70: 63.21
A71: 7 | B71: A2 | C71: East | D71: Low | E71: SIM1 | G71: 26.6 | I71: 28.46 | J71: 100.00 | L71: 7 | M71: A2 | N71: East | O71: Low | P71: Real | Q71: 30.1 | R71: 26.6 | S71: 114 | T71: 28.46 | U71: 100 | V71: 87.01
A72: 7 | B72: A3 | C72: East | D72: Low | E72: SIM1 | G72: 27.9 | I72: 21.02 | J72: 20.00 | L72: 7 | M72: A3 | N72: East | O72: Low | P72: Real | Q72: 24.2 | R72: 27.9 | S72: 20 | T72: 21.02 | U72: 20 | V72: 96.82
A73: 7 | B73: A4 | C73: East | D73: Low | E73: SIM1 | G73: 30.8 | I73: 30.12 | J73: 58.77 | L73: 7 | M73: A4 | N73: East | O73: Low | P73: Real | Q73: 27.7 | R73: 30.8 | S73: 75 | T73: 30.12 | U73: 58.77 | V73: 0
A74: 7 | B74: A1 | C74: South | D74: High | E74: SIM1 | F74: 20.8 | G74: 28.1 | H74: 105.00 | I74: 31.67 | J74: 91.10 | K74: 63.21 | L74: 7 | M74: A1 | N74: South | O74: High | P74: Real | Q74: 20.8 | R74: 28.1 | S74: 105 | T74: 31.67 | U74: 91.1 | V74: 63.21
A75: 7 | B75: A2 | C75: South | D75: High | E75: SIM1 | F75: 31.9 | G75: 39.8 | H75: 102.00 | I75: 42.71 | J75: 93.54 | K75: 87.01 | L75: 7 | M75: A2 | N75: South | O75: High | P75: Real | Q75: 31.9 | R75: 39.8 | S75: 102 | T75: 42.71 | U75: 93.54 | V75: 87.01
A76: 7 | B76: A3 | C76: South | D76: High | E76: SIM1 | F76: 20.0 | G76: 13.2 | H76: 20.00 | I76: 33.63 | J76: 20.00 | K76: 96.82 | L76: 7 | M76: A3 | N76: South | O76: High | P76: Real | Q76: 20 | R76: 13.2 | S76: 20 | T76: 33.63 | U76: 20 | V76: 96.82
A77: 7 | B77: A4 | C77: South | D77: High | E77: SIM1 | F77: 27.3 | G77: 19.0 | H77: 75.00 | I77: 47.41 | J77: 42.22 | K77: 0.00 | L77: 7 | M77: A4 | N77: South | O77: High | P77: Real | Q77: 27.3 | R77: 19 | S77: 75 | T77: 47.41 | U77: 42.22 | V77: 0
A78: 7 | B78: A1 | C78: South | D78: Low | E78: SIM1 | G78: 13.9 | I78: 16.65 | J78: 87.16 | L78: 7 | M78: A1 | N78: South | O78: Low | P78: Real | Q78: 20.8 | R78: 13.9 | S78: 105 | T78: 16.65 | U78: 87.16 | V78: 63.21
A79: 7 | B79: A2 | C79: South | D79: Low | E79: SIM1 | G79: 24.2 | I79: 26.83 | J79: 100.00 | L79: 7 | M79: A2 | N79: South | O79: Low | P79: Real | Q79: 31.9 | R79: 24.2 | S79: 102 | T79: 26.83 | U79: 100 | V79: 87.01
A80: 7 | B80: A3 | C80: South | D80: Low | E80: SIM1 | G80: 26.5 | I80: 21.02 | J80: 20.00 | L80: 7 | M80: A3 | N80: South | O80: Low | P80: Real | Q80: 20 | R80: 26.5 | S80: 20 | T80: 21.02 | U80: 20 | V80: 96.82
A81: 7 | B81: A4 | C81: South | D81: Low | E81: SIM1 | G81: 35.4 | I81: 40.89 | J81: 58.77 | L81: 7 | M81: A4 | N81: South | O81: Low | P81: Real | Q81: 27.3 | R81: 35.4 | S81: 75 | T81: 40.89 | U81: 58.77 | V81: 0

Sheet AWARENESS
A1: β | B1: 0.7
A2: γ_market | B2: 0.4
A3: α | B3: 0.4
A4: Decay Rate | B4: 0.1
A6: Period | B6: Company | C6: Region | D6: Segment | E6: Awareness (t-1) | F6: Avg Market Awareness (t-1) | G6: TV Spots Global | H6: Radio Spots Region | I6: Feature Focus % | J6: MediaFit TV | K6: MediaFit Radio | L6: Awareness-Focused GRPs | M6: Diminishing Returns | N6: Market Saturation | O6: Ad Impact | P6: Decay | Q6: Awareness (t)
A7: 7 | B7: C1 | C7: Center | D7: High | E7: {=IFERROR( _xlfn.XLOOKUP(1, (MARKET_DATA!$A:$A=$A7-1)* (MARKET_DATA!$B:$B=$B7)* (MARKET_DATA!$C:$C=$C7)* (MARKET_DATA!$D:$D=$D7), MARKET_DATA!$I:$I), 0)} -> 0 | F7: =AVERAGEIFS(MARKET_DATA!I:I, MARKET_DATA!$A:$A,$A7-1, MARKET_DATA!$C:$C,$C7, MARKET_DATA!$D:$D,$D7) -> 42.39 | G7: {=_xlfn.XLOOKUP(1, (INPUTS_MASTER!$A:$A=$A7)* (INPUTS_MASTER!$B:$B=$B7), INPUTS_MASTER!$F:$F )} -> 35 | H7: {=_xlfn.XLOOKUP(1, (INPUTS_MASTER!$A:$A=$A7)* (INPUTS_MASTER!$B:$B=$B7)* (INPUTS_MASTER!$C:$C=$C7), INPUTS_MASTER!$H:$H )} -> 210 | I7: {=_xlfn.XLOOKUP(1, (INPUTS_MASTER!$A:$A=$A7)* (INPUTS_MASTER!$B:$B=$B7)* (INPUTS_MASTER!$C:$C=$C7), INPUTS_MASTER!$K:$K )} -> 50 | J7: =+IF($D7="High",1, 0.3) -> 1 | K7: =+IF($D7="Low",1, 0.3) -> 0.3 | L7: =+(G7*J7 + H7*K7) * (100 - I7) / 100 -> 49 | M7: =+(1-E7/100)^$B$1 -> 1 | N7: =+(1-F7/100)^$B$2 -> 0.80204577 | O7: =+$B$3*L7*M7*N7 -> 15.720097 | P7: =+E7*$B$4 -> 0 | Q7: =+MIN(100, MAX(0, E7-P7+O7)) -> 15.720097
A8: 7 | B8: C1 | C8: Center | D8: Low | E8: {=IFERROR( _xlfn.XLOOKUP(1, (MARKET_DATA!$A:$A=$A8-1)* (MARKET_DATA!$B:$B=$B8)* (MARKET_DATA!$C:$C=$C8)* (MARKET_DATA!$D:$D=$D8), MARKET_DATA!$I:$I), 0)} -> 0 | F8: =AVERAGEIFS(MARKET_DATA!I:I, MARKET_DATA!$A:$A,$A8-1, MARKET_DATA!$C:$C,$C8, MARKET_DATA!$D:$D,$D8) -> 28.72 | G8: {=_xlfn.XLOOKUP(1, (INPUTS_MASTER!$A:$A=$A8)* (INPUTS_MASTER!$B:$B=$B8), INPUTS_MASTER!$F:$F )} -> 35 | H8: {=_xlfn.XLOOKUP(1, (INPUTS_MASTER!$A:$A=$A8)* (INPUTS_MASTER!$B:$B=$B8)* (INPUTS_MASTER!$C:$C=$C8), INPUTS_MASTER!$H:$H )} -> 210 | I8: {=_xlfn.XLOOKUP(1, (INPUTS_MASTER!$A:$A=$A8)* (INPUTS_MASTER!$B:$B=$B8)* (INPUTS_MASTER!$C:$C=$C8), INPUTS_MASTER!$K:$K )} -> 50 | J8: =+IF($D8="High",1, 0.3) -> 0.3 | K8: =+IF($D8="Low",1, 0.3) -> 1 | L8: =+(G8*J8 + H8*K8) * (100 - I8) / 100 -> 110.25 | M8: =+(1-E8/100)^$B$1 -> 1 | N8: =+(1-F8/100)^$B$2 -> 0.87334749 | O8: =+$B$3*L8*M8*N8 -> 38.514624 | P8: =+E8*$B$4 -> 0 | Q8: =+MIN(100, MAX(0, E8-P8+O8)) -> 38.514624
A9: 7 | B9: C1 | C9: West | D9: High | E9: {=IFERROR( _xlfn.XLOOKUP(1, (MARKET_DATA!$A:$A=$A9-1)* (MARKET_DATA!$B:$B=$B9)* (MARKET_DATA!$C:$C=$C9)* (MARKET_DATA!$D:$D=$D9), MARKET_DATA!$I:$I), 0)} -> 0 | F9: =AVERAGEIFS(MARKET_DATA!I:I, MARKET_DATA!$A:$A,$A9-1, MARKET_DATA!$C:$C,$C9, MARKET_DATA!$D:$D,$D9) -> 34.58 | G9: {=_xlfn.XLOOKUP(1, (INPUTS_MASTER!$A:$A=$A9)* (INPUTS_MASTER!$B:$B=$B9), INPUTS_MASTER!$F:$F )} -> 35 | H9: {=_xlfn.XLOOKUP(1, (INPUTS_MASTER!$A:$A=$A9)* (INPUTS_MASTER!$B:$B=$B9)* (INPUTS_MASTER!$C:$C=$C9), INPUTS_MASTER!$H:$H )} -> 102 | I9: {=_xlfn.XLOOKUP(1, (INPUTS_MASTER!$A:$A=$A9)* (INPUTS_MASTER!$B:$B=$B9)* (INPUTS_MASTER!$C:$C=$C9), INPUTS_MASTER!$K:$K )} -> 50 | J9: =+IF($D9="High",1, 0.3) -> 1 | K9: =+IF($D9="Low",1, 0.3) -> 0.3 | L9: =+(G9*J9 + H9*K9) * (100 - I9) / 100 -> 32.8 | M9: =+(1-E9/100)^$B$1 -> 1 | N9: =+(1-F9/100)^$B$2 -> 0.84388684 | O9: =+$B$3*L9*M9*N9 -> 11.071795 | P9: =+E9*$B$4 -> 0 | Q9: =+MIN(100, MAX(0, E9-P9+O9)) -> 11.071795
A10: 7 | B10: C1 | C10: West | D10: Low | E10: {=IFERROR( _xlfn.XLOOKUP(1, (MARKET_DATA!$A:$A=$A10-1)* (MARKET_DATA!$B:$B=$B10)* (MARKET_DATA!$C:$C=$C10)* (MARKET_DATA!$D:$D=$D10), MARKET_DATA!$I:$I), 0)} -> 0 | F10: =AVERAGEIFS(MARKET_DATA!I:I, MARKET_DATA!$A:$A,$A10-1, MARKET_DATA!$C:$C,$C10, MARKET_DATA!$D:$D,$D10) -> 22.16 | G10: {=_xlfn.XLOOKUP(1, (INPUTS_MASTER!$A:$A=$A10)* (INPUTS_MASTER!$B:$B=$B10), INPUTS_MASTER!$F:$F )} -> 35 | H10: {=_xlfn.XLOOKUP(1, (INPUTS_MASTER!$A:$A=$A10)* (INPUTS_MASTER!$B:$B=$B10)* (INPUTS_MASTER!$C:$C=$C10), INPUTS_MASTER!$H:$H )} -> 102 | I10: {=_xlfn.XLOOKUP(1, (INPUTS_MASTER!$A:$A=$A10)* (INPUTS_MASTER!$B:$B=$B10)* (INPUTS_MASTER!$C:$C=$C10), INPUTS_MASTER!$K:$K )} -> 50 | J10: =+IF($D10="High",1, 0.3) -> 0.3 | K10: =+IF($D10="Low",1, 0.3) -> 1 | L10: =+(G10*J10 + H10*K10) * (100 - I10) / 100 -> 56.25 | M10: =+(1-E10/100)^$B$1 -> 1 | N10: =+(1-F10/100)^$B$2 -> 0.90465113 | O10: =+$B$3*L10*M10*N10 -> 20.35465 | P10: =+E10*$B$4 -> 0 | Q10: =+MIN(100, MAX(0, E10-P10+O10)) -> 20.35465
A11: 7 | B11: C1 | C11: North | D11: High | E11: {=IFERROR( _xlfn.XLOOKUP(1, (MARKET_DATA!$A:$A=$A11-1)* (MARKET_DATA!$B:$B=$B11)* (MARKET_DATA!$C:$C=$C11)* (MARKET_DATA!$D:$D=$D11), MARKET_DATA!$I:$I), 0)} -> 0 | F11: =AVERAGEIFS(MARKET_DATA!I:I, MARKET_DATA!$A:$A,$A11-1, MARKET_DATA!$C:$C,$C11, MARKET_DATA!$D:$D,$D11) -> 26.84 | G11: {=_xlfn.XLOOKUP(1, (INPUTS_MASTER!$A:$A=$A11)* (INPUTS_MASTER!$B:$B=$B11), INPUTS_MASTER!$F:$F )} -> 35 | H11: {=_xlfn.XLOOKUP(1, (INPUTS_MASTER!$A:$A=$A11)* (INPUTS_MASTER!$B:$B=$B11)* (INPUTS_MASTER!$C:$C=$C11), INPUTS_MASTER!$H:$H )} -> 82 | I11: {=_xlfn.XLOOKUP(1, (INPUTS_MASTER!$A:$A=$A11)* (INPUTS_MASTER!$B:$B=$B11)* (INPUTS_MASTER!$C:$C=$C11), INPUTS_MASTER!$K:$K )} -> 50 | J11: =+IF($D11="High",1, 0.3) -> 1 | K11: =+IF($D11="Low",1, 0.3) -> 0.3 | L11: =+(G11*J11 + H11*K11) * (100 - I11) / 100 -> 29.8 | M11: =+(1-E11/100)^$B$1 -> 1 | N11: =+(1-F11/100)^$B$2 -> 0.88248936 | O11: =+$B$3*L11*M11*N11 -> 10.519273 | P11: =+E11*$B$4 -> 0 | Q11: =+MIN(100, MAX(0, E11-P11+O11)) -> 10.519273
A12: 7 | B12: C1 | C12: North | D12: Low | E12: {=IFERROR( _xlfn.XLOOKUP(1, (MARKET_DATA!$A:$A=$A12-1)* (MARKET_DATA!$B:$B=$B12)* (MARKET_DATA!$C:$C=$C12)* (MARKET_DATA!$D:$D=$D12), MARKET_DATA!$I:$I), 0)} -> 0 | F12: =AVERAGEIFS(MARKET_DATA!I:I, MARKET_DATA!$A:$A,$A12-1, MARKET_DATA!$C:$C,$C12, MARKET_DATA!$D:$D,$D12) -> 23.1 | G12: {=_xlfn.XLOOKUP(1, (INPUTS_MASTER!$A:$A=$A12)* (INPUTS_MASTER!$B:$B=$B12), INPUTS_MASTER!$F:$F )} -> 35 | H12: {=_xlfn.XLOOKUP(1, (INPUTS_MASTER!$A:$A=$A12)* (INPUTS_MASTER!$B:$B=$B12)* (INPUTS_MASTER!$C:$C=$C12), INPUTS_MASTER!$H:$H )} -> 82 | I12: {=_xlfn.XLOOKUP(1, (INPUTS_MASTER!$A:$A=$A12)* (INPUTS_MASTER!$B:$B=$B12)* (INPUTS_MASTER!$C:$C=$C12), INPUTS_MASTER!$K:$K )} -> 50 | J12: =+IF($D12="High",1, 0.3) -> 0.3 | K12: =+IF($D12="Low",1, 0.3) -> 1 | L12: =+(G12*J12 + H12*K12) * (100 - I12) / 100 -> 46.25 | M12: =+(1-E12/100)^$B$1 -> 1 | N12: =+(1-F12/100)^$B$2 -> 0.90026535 | O12: =+$B$3*L12*M12*N12 -> 16.654909 | P12: =+E12*$B$4 -> 0 | Q12: =+MIN(100, MAX(0, E12-P12+O12)) -> 16.654909
A13: 7 | B13: C1 | C13: East | D13: High | E13: {=IFERROR( _xlfn.XLOOKUP(1, (MARKET_DATA!$A:$A=$A13-1)* (MARKET_DATA!$B:$B=$B13)* (MARKET_DATA!$C:$C=$C13)* (MARKET_DATA!$D:$D=$D13), MARKET_DATA!$I:$I), 0)} -> 0 | F13: =AVERAGEIFS(MARKET_DATA!I:I, MARKET_DATA!$A:$A,$A13-1, MARKET_DATA!$C:$C,$C13, MARKET_DATA!$D:$D,$D13) -> 0 | G13: {=_xlfn.XLOOKUP(1, (INPUTS_MASTER!$A:$A=$A13)* (INPUTS_MASTER!$B:$B=$B13), INPUTS_MASTER!$F:$F )} -> 35 | H13: {=_xlfn.XLOOKUP(1, (INPUTS_MASTER!$A:$A=$A13)* (INPUTS_MASTER!$B:$B=$B13)* (INPUTS_MASTER!$C:$C=$C13), INPUTS_MASTER!$H:$H )} -> 40 | I13: {=_xlfn.XLOOKUP(1, (INPUTS_MASTER!$A:$A=$A13)* (INPUTS_MASTER!$B:$B=$B13)* (INPUTS_MASTER!$C:$C=$C13), INPUTS_MASTER!$K:$K )} -> 50 | J13: =+IF($D13="High",1, 0.3) -> 1 | K13: =+IF($D13="Low",1, 0.3) -> 0.3 | L13: =+(G13*J13 + H13*K13) * (100 - I13) / 100 -> 23.5 | M13: =+(1-E13/100)^$B$1 -> 1 | N13: =+(1-F13/100)^$B$2 -> 1 | O13: =+$B$3*L13*M13*N13 -> 9.4 | P13: =+E13*$B$4 -> 0 | Q13: =+MIN(100, MAX(0, E13-P13+O13)) -> 9.4
A14: 7 | B14: C1 | C14: East | D14: Low | E14: {=IFERROR( _xlfn.XLOOKUP(1, (MARKET_DATA!$A:$A=$A14-1)* (MARKET_DATA!$B:$B=$B14)* (MARKET_DATA!$C:$C=$C14)* (MARKET_DATA!$D:$D=$D14), MARKET_DATA!$I:$I), 0)} -> 0 | F14: =AVERAGEIFS(MARKET_DATA!I:I, MARKET_DATA!$A:$A,$A14-1, MARKET_DATA!$C:$C,$C14, MARKET_DATA!$D:$D,$D14) -> 0 | G14: {=_xlfn.XLOOKUP(1, (INPUTS_MASTER!$A:$A=$A14)* (INPUTS_MASTER!$B:$B=$B14), INPUTS_MASTER!$F:$F )} -> 35 | H14: {=_xlfn.XLOOKUP(1, (INPUTS_MASTER!$A:$A=$A14)* (INPUTS_MASTER!$B:$B=$B14)* (INPUTS_MASTER!$C:$C=$C14), INPUTS_MASTER!$H:$H )} -> 40 | I14: {=_xlfn.XLOOKUP(1, (INPUTS_MASTER!$A:$A=$A14)* (INPUTS_MASTER!$B:$B=$B14)* (INPUTS_MASTER!$C:$C=$C14), INPUTS_MASTER!$K:$K )} -> 50 | J14: =+IF($D14="High",1, 0.3) -> 0.3 | K14: =+IF($D14="Low",1, 0.3) -> 1 | L14: =+(G14*J14 + H14*K14) * (100 - I14) / 100 -> 25.25 | M14: =+(1-E14/100)^$B$1 -> 1 | N14: =+(1-F14/100)^$B$2 -> 1 | O14: =+$B$3*L14*M14*N14 -> 10.1 | P14: =+E14*$B$4 -> 0 | Q14: =+MIN(100, MAX(0, E14-P14+O14)) -> 10.1
A15: 7 | B15: C1 | C15: South | D15: High | E15: {=IFERROR( _xlfn.XLOOKUP(1, (MARKET_DATA!$A:$A=$A15-1)* (MARKET_DATA!$B:$B=$B15)* (MARKET_DATA!$C:$C=$C15)* (MARKET_DATA!$D:$D=$D15), MARKET_DATA!$I:$I), 0)} -> 0 | F15: =AVERAGEIFS(MARKET_DATA!I:I, MARKET_DATA!$A:$A,$A15-1, MARKET_DATA!$C:$C,$C15, MARKET_DATA!$D:$D,$D15) -> 0 | G15: {=_xlfn.XLOOKUP(1, (INPUTS_MASTER!$A:$A=$A15)* (INPUTS_MASTER!$B:$B=$B15), INPUTS_MASTER!$F:$F )} -> 35 | H15: {=_xlfn.XLOOKUP(1, (INPUTS_MASTER!$A:$A=$A15)* (INPUTS_MASTER!$B:$B=$B15)* (INPUTS_MASTER!$C:$C=$C15), INPUTS_MASTER!$H:$H )} -> 40 | I15: {=_xlfn.XLOOKUP(1, (INPUTS_MASTER!$A:$A=$A15)* (INPUTS_MASTER!$B:$B=$B15)* (INPUTS_MASTER!$C:$C=$C15), INPUTS_MASTER!$K:$K )} -> 50 | J15: =+IF($D15="High",1, 0.3) -> 1 | K15: =+IF($D15="Low",1, 0.3) -> 0.3 | L15: =+(G15*J15 + H15*K15) * (100 - I15) / 100 -> 23.5 | M15: =+(1-E15/100)^$B$1 -> 1 | N15: =+(1-F15/100)^$B$2 -> 1 | O15: =+$B$3*L15*M15*N15 -> 9.4 | P15: =+E15*$B$4 -> 0 | Q15: =+MIN(100, MAX(0, E15-P15+O15)) -> 9.4
A16: 7 | B16: C1 | C16: South | D16: Low | E16: {=IFERROR( _xlfn.XLOOKUP(1, (MARKET_DATA!$A:$A=$A16-1)* (MARKET_DATA!$B:$B=$B16)* (MARKET_DATA!$C:$C=$C16)* (MARKET_DATA!$D:$D=$D16), MARKET_DATA!$I:$I), 0)} -> 0 | F16: =AVERAGEIFS(MARKET_DATA!I:I, MARKET_DATA!$A:$A,$A16-1, MARKET_DATA!$C:$C,$C16, MARKET_DATA!$D:$D,$D16) -> 0 | G16: {=_xlfn.XLOOKUP(1, (INPUTS_MASTER!$A:$A=$A16)* (INPUTS_MASTER!$B:$B=$B16), INPUTS_MASTER!$F:$F )} -> 35 | H16: {=_xlfn.XLOOKUP(1, (INPUTS_MASTER!$A:$A=$A16)* (INPUTS_MASTER!$B:$B=$B16)* (INPUTS_MASTER!$C:$C=$C16), INPUTS_MASTER!$H:$H )} -> 40 | I16: {=_xlfn.XLOOKUP(1, (INPUTS_MASTER!$A:$A=$A16)* (INPUTS_MASTER!$B:$B=$B16)* (INPUTS_MASTER!$C:$C=$C16), INPUTS_MASTER!$K:$K )} -> 50 | J16: =+IF($D16="High",1, 0.3) -> 0.3 | K16: =+IF($D16="Low",1, 0.3) -> 1 | L16: =+(G16*J16 + H16*K16) * (100 - I16) / 100 -> 25.25 | M16: =+(1-E16/100)^$B$1 -> 1 | N16: =+(1-F16/100)^$B$2 -> 1 | O16: =+$B$3*L16*M16*N16 -> 10.1 | P16: =+E16*$B$4 -> 0 | Q16: =+MIN(100, MAX(0, E16-P16+O16)) -> 10.1
A17: 8 | B17: C1 | C17: Center | D17: High
A18: 8 | B18: C1 | C18: Center | D18: Low
A19: 8 | B19: C1 | C19: West | D19: High
A20: 8 | B20: C1 | C20: West | D20: Low
A21: 8 | B21: C1 | C21: North | D21: High
A22: 8 | B22: C1 | C22: North | D22: Low
A23: 8 | B23: C1 | C23: East | D23: High
A24: 8 | B24: C1 | C24: East | D24: Low
A25: 8 | B25: C1 | C25: South | D25: High
A26: 8 | B26: C1 | C26: South | D26: Low
A27: 9 | B27: C1 | C27: Center | D27: High
A28: 9 | B28: C1 | C28: Center | D28: Low
... A66: 12 | B66: C1 | C66: South | D66: Low

Sheet ATTRACTIVENESS
A3: Decay | B3: 0.05
A4: γ | B4: 0.05
A5: High Segment Premium | B5: 1.2
A8: Period | B8: Company | C8: Region | D8: Segment | E8: Attractiveness (t-1) | F8: Awareness (t-1) | G8: Base Points | H8: TV Spots Global | I8: Radio Spots Region | J8: Feature Focus % | K8: MediaFit TV | L8: MediaFit Radio | M8: Decayed Attractiveness (t-1) | N8: Starting Attractiveness | O8: Feature-Focused GRPs | P8: Communication Boost | Q8: Segment Multiplier | R8: Attractiveness (t)
A9: 7 | B9: C1 | C9: Center | D9: High | E9: {=IFERROR( _xlfn.XLOOKUP(1, (MARKET_DATA!$A:$A=$A9-1)* (MARKET_DATA!$B:$B=$B9)* (MARKET_DATA!$C:$C=$C9)* (MARKET_DATA!$D:$D=$D9), MARKET_DATA!$J:$J), 0)} -> 0 | F9: {=IFERROR( _xlfn.XLOOKUP(1, (MARKET_DATA!$A:$A=$A9-1)* (MARKET_DATA!$B:$B=$B9)* (MARKET_DATA!$C:$C=$C9)* (MARKET_DATA!$D:$D=$D9), MARKET_DATA!$I:$I), 0)} -> 0 | G9: =20+SUMIFS( INDEX(INNOVATION!$G:$H,,MATCH($D9,{"High";"Low"},0)), INNOVATION!$J:$J, ">="&$A9) -> 25 | H9: {=_xlfn.XLOOKUP(1, (INPUTS_MASTER!$A:$A=$A9)* (INPUTS_MASTER!$B:$B=$B9), INPUTS_MASTER!$F:$F )} -> 35 | I9: {=_xlfn.XLOOKUP(1, (INPUTS_MASTER!$A:$A=$A9)* (INPUTS_MASTER!$B:$B=$B9)* (INPUTS_MASTER!$C:$C=$C9), INPUTS_MASTER!$H:$H )} -> 210 | J9: {=_xlfn.XLOOKUP(1, (INPUTS_MASTER!$A:$A=$A9)* (INPUTS_MASTER!$B:$B=$B9)* (INPUTS_MASTER!$C:$C=$C9), INPUTS_MASTER!$K:$K )} -> 50 | K9: =+IF($D9="High",1, 0.3) -> 1 | L9: =+IF($D9="Low",1, 0.3) -> 0.3 | M9: =+E9 * (1 - $B$3) -> 0 | N9: =+MAX(G9, M9) -> 25 | O9: =+(H9*K9 + I9*L9) * J9/100 -> 49 | P9: =+$B$4 * O9 * (1 - N9/100) * (F9/100) -> 0 | Q9: =+IF(D9="High",$B$5, 1) -> 1.2 | R9: =+MIN(100, (N9 + P9) * Q9) -> 30
A10: 7 | B10: C1 | C10: Center | D10: Low | E10: {=IFERROR( _xlfn.XLOOKUP(1, (MARKET_DATA!$A:$A=$A10-1)* (MARKET_DATA!$B:$B=$B10)* (MARKET_DATA!$C:$C=$C10)* (MARKET_DATA!$D:$D=$D10), MARKET_DATA!$J:$J), 0)} -> 0 | F10: {=IFERROR( _xlfn.XLOOKUP(1, (MARKET_DATA!$A:$A=$A10-1)* (MARKET_DATA!$B:$B=$B10)* (MARKET_DATA!$C:$C=$C10)* (MARKET_DATA!$D:$D=$D10), MARKET_DATA!$I:$I), 0)} -> 0 | G10: =20+SUMIFS( INDEX(INNOVATION!$G:$H,,MATCH($D10,{"High";"Low"},0)), INNOVATION!$J:$J, ">="&$A10) -> 23 | H10: {=_xlfn.XLOOKUP(1, (INPUTS_MASTER!$A:$A=$A10)* (INPUTS_MASTER!$B:$B=$B10), INPUTS_MASTER!$F:$F )} -> 35 | I10: {=_xlfn.XLOOKUP(1, (INPUTS_MASTER!$A:$A=$A10)* (INPUTS_MASTER!$B:$B=$B10)* (INPUTS_MASTER!$C:$C=$C10), INPUTS_MASTER!$H:$H )} -> 210 | J10: {=_xlfn.XLOOKUP(1, (INPUTS_MASTER!$A:$A=$A10)* (INPUTS_MASTER!$B:$B=$B10)* (INPUTS_MASTER!$C:$C=$C10), INPUTS_MASTER!$K:$K )} -> 50 | K10: =+IF($D10="High",1, 0.3) -> 0.3 | L10: =+IF($D10="Low",1, 0.3) -> 1 | M10: =+E10 * (1 - $B$3) -> 0 | N10: =+MAX(G10, M10) -> 23 | O10: =+(H10*K10 + I10*L10) * J10/100 -> 110.25 | P10: =+$B$4 * O10 * (1 - N10/100) * (F10/100) -> 0 | Q10: =+IF(D10="High",$B$5, 1) -> 1 | R10: =+MIN(100, (N10 + P10) * Q10) -> 23
A11: 7 | B11: C1 | C11: West | D11: High | E11: {=IFERROR( _xlfn.XLOOKUP(1, (MARKET_DATA!$A:$A=$A11-1)* (MARKET_DATA!$B:$B=$B11)* (MARKET_DATA!$C:$C=$C11)* (MARKET_DATA!$D:$D=$D11), MARKET_DATA!$J:$J), 0)} -> 0 | F11: {=IFERROR( _xlfn.XLOOKUP(1, (MARKET_DATA!$A:$A=$A11-1)* (MARKET_DATA!$B:$B=$B11)* (MARKET_DATA!$C:$C=$C11)* (MARKET_DATA!$D:$D=$D11), MARKET_DATA!$I:$I), 0)} -> 0 | G11: =20+SUMIFS( INDEX(INNOVATION!$G:$H,,MATCH($D11,{"High";"Low"},0)), INNOVATION!$J:$J, ">="&$A11) -> 25 | H11: {=_xlfn.XLOOKUP(1, (INPUTS_MASTER!$A:$A=$A11)* (INPUTS_MASTER!$B:$B=$B11), INPUTS_MASTER!$F:$F )} -> 35 | I11: {=_xlfn.XLOOKUP(1, (INPUTS_MASTER!$A:$A=$A11)* (INPUTS_MASTER!$B:$B=$B11)* (INPUTS_MASTER!$C:$C=$C11), INPUTS_MASTER!$H:$H )} -> 102 | J11: {=_xlfn.XLOOKUP(1, (INPUTS_MASTER!$A:$A=$A11)* (INPUTS_MASTER!$B:$B=$B11)* (INPUTS_MASTER!$C:$C=$C11), INPUTS_MASTER!$K:$K )} -> 50 | K11: =+IF($D11="High",1, 0.3) -> 1 | L11: =+IF($D11="Low",1, 0.3) -> 0.3 | M11: =+E11 * (1 - $B$3) -> 0 | N11: =+MAX(G11, M11) -> 25 | O11: =+(H11*K11 + I11*L11) * J11/100 -> 32.8 | P11: =+$B$4 * O11 * (1 - N11/100) * (F11/100) -> 0 | Q11: =+IF(D11="High",$B$5, 1) -> 1.2 | R11: =+MIN(100, (N11 + P11) * Q11) -> 30
A12: 7 | B12: C1 | C12: West | D12: Low | E12: {=IFERROR( _xlfn.XLOOKUP(1, (MARKET_DATA!$A:$A=$A12-1)* (MARKET_DATA!$B:$B=$B12)* (MARKET_DATA!$C:$C=$C12)* (MARKET_DATA!$D:$D=$D12), MARKET_DATA!$J:$J), 0)} -> 0 | F12: {=IFERROR( _xlfn.XLOOKUP(1, (MARKET_DATA!$A:$A=$A12-1)* (MARKET_DATA!$B:$B=$B12)* (MARKET_DATA!$C:$C=$C12)* (MARKET_DATA!$D:$D=$D12), MARKET_DATA!$I:$I), 0)} -> 0 | G12: =20+SUMIFS( INDEX(INNOVATION!$G:$H,,MATCH($D12,{"High";"Low"},0)), INNOVATION!$J:$J, ">="&$A12) -> 23 | H12: {=_xlfn.XLOOKUP(1, (INPUTS_MASTER!$A:$A=$A12)* (INPUTS_MASTER!$B:$B=$B12), INPUTS_MASTER!$F:$F )} -> 35 | I12: {=_xlfn.XLOOKUP(1, (INPUTS_MASTER!$A:$A=$A12)* (INPUTS_MASTER!$B:$B=$B12)* (INPUTS_MASTER!$C:$C=$C12), INPUTS_MASTER!$H:$H )} -> 102 | J12: {=_xlfn.XLOOKUP(1, (INPUTS_MASTER!$A:$A=$A12)* (INPUTS_MASTER!$B:$B=$B12)* (INPUTS_MASTER!$C:$C=$C12), INPUTS_MASTER!$K:$K )} -> 50 | K12: =+IF($D12="High",1, 0.3) -> 0.3 | L12: =+IF($D12="Low",1, 0.3) -> 1 | M12: =+E12 * (1 - $B$3) -> 0 | N12: =+MAX(G12, M12) -> 23 | O12: =+(H12*K12 + I12*L12) * J12/100 -> 56.25 | P12: =+$B$4 * O12 * (1 - N12/100) * (F12/100) -> 0 | Q12: =+IF(D12="High",$B$5, 1) -> 1 | R12: =+MIN(100, (N12 + P12) * Q12) -> 23
A13: 7 | B13: C1 | C13: North | D13: High | E13: {=IFERROR( _xlfn.XLOOKUP(1, (MARKET_DATA!$A:$A=$A13-1)* (MARKET_DATA!$B:$B=$B13)* (MARKET_DATA!$C:$C=$C13)* (MARKET_DATA!$D:$D=$D13), MARKET_DATA!$J:$J), 0)} -> 0 | F13: {=IFERROR( _xlfn.XLOOKUP(1, (MARKET_DATA!$A:$A=$A13-1)* (MARKET_DATA!$B:$B=$B13)* (MARKET_DATA!$C:$C=$C13)* (MARKET_DATA!$D:$D=$D13), MARKET_DATA!$I:$I), 0)} -> 0 | G13: =20+SUMIFS( INDEX(INNOVATION!$G:$H,,MATCH($D13,{"High";"Low"},0)), INNOVATION!$J:$J, ">="&$A13) -> 25 | H13: {=_xlfn.XLOOKUP(1, (INPUTS_MASTER!$A:$A=$A13)* (INPUTS_MASTER!$B:$B=$B13), INPUTS_MASTER!$F:$F )} -> 35 | I13: {=_xlfn.XLOOKUP(1, (INPUTS_MASTER!$A:$A=$A13)* (INPUTS_MASTER!$B:$B=$B13)* (INPUTS_MASTER!$C:$C=$C13), INPUTS_MASTER!$H:$H )} -> 82 | J13: {=_xlfn.XLOOKUP(1, (INPUTS_MASTER!$A:$A=$A13)* (INPUTS_MASTER!$B:$B=$B13)* (INPUTS_MASTER!$C:$C=$C13), INPUTS_MASTER!$K:$K )} -> 50 | K13: =+IF($D13="High",1, 0.3) -> 1 | L13: =+IF($D13="Low",1, 0.3) -> 0.3 | M13: =+E13 * (1 - $B$3) -> 0 | N13: =+MAX(G13, M13) -> 25 | O13: =+(H13*K13 + I13*L13) * J13/100 -> 29.8 | P13: =+$B$4 * O13 * (1 - N13/100) * (F13/100) -> 0 | Q13: =+IF(D13="High",$B$5, 1) -> 1.2 | R13: =+MIN(100, (N13 + P13) * Q13) -> 30
A14: 7 | B14: C1 | C14: North | D14: Low | E14: {=IFERROR( _xlfn.XLOOKUP(1, (MARKET_DATA!$A:$A=$A14-1)* (MARKET_DATA!$B:$B=$B14)* (MARKET_DATA!$C:$C=$C14)* (MARKET_DATA!$D:$D=$D14), MARKET_DATA!$J:$J), 0)} -> 0 | F14: {=IFERROR( _xlfn.XLOOKUP(1, (MARKET_DATA!$A:$A=$A14-1)* (MARKET_DATA!$B:$B=$B14)* (MARKET_DATA!$C:$C=$C14)* (MARKET_DATA!$D:$D=$D14), MARKET_DATA!$I:$I), 0)} -> 0 | G14: =20+SUMIFS( INDEX(INNOVATION!$G:$H,,MATCH($D14,{"High";"Low"},0)), INNOVATION!$J:$J, ">="&$A14) -> 23 | H14: {=_xlfn.XLOOKUP(1, (INPUTS_MASTER!$A:$A=$A14)* (INPUTS_MASTER!$B:$B=$B14), INPUTS_MASTER!$F:$F )} -> 35 | I14: {=_xlfn.XLOOKUP(1, (INPUTS_MASTER!$A:$A=$A14)* (INPUTS_MASTER!$B:$B=$B14)* (INPUTS_MASTER!$C:$C=$C14), INPUTS_MASTER!$H:$H )} -> 82 | J14: {=_xlfn.XLOOKUP(1, (INPUTS_MASTER!$A:$A=$A14)* (INPUTS_MASTER!$B:$B=$B14)* (INPUTS_MASTER!$C:$C=$C14), INPUTS_MASTER!$K:$K )} -> 50 | K14: =+IF($D14="High",1, 0.3) -> 0.3 | L14: =+IF($D14="Low",1, 0.3) -> 1 | M14: =+E14 * (1 - $B$3) -> 0 | N14: =+MAX(G14, M14) -> 23 | O14: =+(H14*K14 + I14*L14) * J14/100 -> 46.25 | P14: =+$B$4 * O14 * (1 - N14/100) * (F14/100) -> 0 | Q14: =+IF(D14="High",$B$5, 1) -> 1 | R14: =+MIN(100, (N14 + P14) * Q14) -> 23
A15: 7 | B15: C1 | C15: East | D15: High | E15: {=IFERROR( _xlfn.XLOOKUP(1, (MARKET_DATA!$A:$A=$A15-1)* (MARKET_DATA!$B:$B=$B15)* (MARKET_DATA!$C:$C=$C15)* (MARKET_DATA!$D:$D=$D15), MARKET_DATA!$J:$J), 0)} -> 0 | F15: {=IFERROR( _xlfn.XLOOKUP(1, (MARKET_DATA!$A:$A=$A15-1)* (MARKET_DATA!$B:$B=$B15)* (MARKET_DATA!$C:$C=$C15)* (MARKET_DATA!$D:$D=$D15), MARKET_DATA!$I:$I), 0)} -> 0 | G15: =20+SUMIFS( INDEX(INNOVATION!$G:$H,,MATCH($D15,{"High";"Low"},0)), INNOVATION!$J:$J, ">="&$A15) -> 25 | H15: {=_xlfn.XLOOKUP(1, (INPUTS_MASTER!$A:$A=$A15)* (INPUTS_MASTER!$B:$B=$B15), INPUTS_MASTER!$F:$F )} -> 35 | I15: {=_xlfn.XLOOKUP(1, (INPUTS_MASTER!$A:$A=$A15)* (INPUTS_MASTER!$B:$B=$B15)* (INPUTS_MASTER!$C:$C=$C15), INPUTS_MASTER!$H:$H )} -> 40 | J15: {=_xlfn.XLOOKUP(1, (INPUTS_MASTER!$A:$A=$A15)* (INPUTS_MASTER!$B:$B=$B15)* (INPUTS_MASTER!$C:$C=$C15), INPUTS_MASTER!$K:$K )} -> 50 | K15: =+IF($D15="High",1, 0.3) -> 1 | L15: =+IF($D15="Low",1, 0.3) -> 0.3 | M15: =+E15 * (1 - $B$3) -> 0 | N15: =+MAX(G15, M15) -> 25 | O15: =+(H15*K15 + I15*L15) * J15/100 -> 23.5 | P15: =+$B$4 * O15 * (1 - N15/100) * (F15/100) -> 0 | Q15: =+IF(D15="High",$B$5, 1) -> 1.2 | R15: =+MIN(100, (N15 + P15) * Q15) -> 30
A16: 7 | B16: C1 | C16: East | D16: Low | E16: {=IFERROR( _xlfn.XLOOKUP(1, (MARKET_DATA!$A:$A=$A16-1)* (MARKET_DATA!$B:$B=$B16)* (MARKET_DATA!$C:$C=$C16)* (MARKET_DATA!$D:$D=$D16), MARKET_DATA!$J:$J), 0)} -> 0 | F16: {=IFERROR( _xlfn.XLOOKUP(1, (MARKET_DATA!$A:$A=$A16-1)* (MARKET_DATA!$B:$B=$B16)* (MARKET_DATA!$C:$C=$C16)* (MARKET_DATA!$D:$D=$D16), MARKET_DATA!$I:$I), 0)} -> 0 | G16: =20+SUMIFS( INDEX(INNOVATION!$G:$H,,MATCH($D16,{"High";"Low"},0)), INNOVATION!$J:$J, ">="&$A16) -> 23 | H16: {=_xlfn.XLOOKUP(1, (INPUTS_MASTER!$A:$A=$A16)* (INPUTS_MASTER!$B:$B=$B16), INPUTS_MASTER!$F:$F )} -> 35 | I16: {=_xlfn.XLOOKUP(1, (INPUTS_MASTER!$A:$A=$A16)* (INPUTS_MASTER!$B:$B=$B16)* (INPUTS_MASTER!$C:$C=$C16), INPUTS_MASTER!$H:$H )} -> 40 | J16: {=_xlfn.XLOOKUP(1, (INPUTS_MASTER!$A:$A=$A16)* (INPUTS_MASTER!$B:$B=$B16)* (INPUTS_MASTER!$C:$C=$C16), INPUTS_MASTER!$K:$K )} -> 50 | K16: =+IF($D16="High",1, 0.3) -> 0.3 | L16: =+IF($D16="Low",1, 0.3) -> 1 | M16: =+E16 * (1 - $B$3) -> 0 | N16: =+MAX(G16, M16) -> 23 | O16: =+(H16*K16 + I16*L16) * J16/100 -> 25.25 | P16: =+$B$4 * O16 * (1 - N16/100) * (F16/100) -> 0 | Q16: =+IF(D16="High",$B$5, 1) -> 1 | R16: =+MIN(100, (N16 + P16) * Q16) -> 23
A17: 7 | B17: C1 | C17: South | D17: High | E17: {=IFERROR( _xlfn.XLOOKUP(1, (MARKET_DATA!$A:$A=$A17-1)* (MARKET_DATA!$B:$B=$B17)* (MARKET_DATA!$C:$C=$C17)* (MARKET_DATA!$D:$D=$D17), MARKET_DATA!$J:$J), 0)} -> 0 | F17: {=IFERROR( _xlfn.XLOOKUP(1, (MARKET_DATA!$A:$A=$A17-1)* (MARKET_DATA!$B:$B=$B17)* (MARKET_DATA!$C:$C=$C17)* (MARKET_DATA!$D:$D=$D17), MARKET_DATA!$I:$I), 0)} -> 0 | G17: =20+SUMIFS( INDEX(INNOVATION!$G:$H,,MATCH($D17,{"High";"Low"},0)), INNOVATION!$J:$J, ">="&$A17) -> 25 | H17: {=_xlfn.XLOOKUP(1, (INPUTS_MASTER!$A:$A=$A17)* (INPUTS_MASTER!$B:$B=$B17), INPUTS_MASTER!$F:$F )} -> 35 | I17: {=_xlfn.XLOOKUP(1, (INPUTS_MASTER!$A:$A=$A17)* (INPUTS_MASTER!$B:$B=$B17)* (INPUTS_MASTER!$C:$C=$C17), INPUTS_MASTER!$H:$H )} -> 40 | J17: {=_xlfn.XLOOKUP(1, (INPUTS_MASTER!$A:$A=$A17)* (INPUTS_MASTER!$B:$B=$B17)* (INPUTS_MASTER!$C:$C=$C17), INPUTS_MASTER!$K:$K )} -> 50 | K17: =+IF($D17="High",1, 0.3) -> 1 | L17: =+IF($D17="Low",1, 0.3) -> 0.3 | M17: =+E17 * (1 - $B$3) -> 0 | N17: =+MAX(G17, M17) -> 25 | O17: =+(H17*K17 + I17*L17) * J17/100 -> 23.5 | P17: =+$B$4 * O17 * (1 - N17/100) * (F17/100) -> 0 | Q17: =+IF(D17="High",$B$5, 1) -> 1.2 | R17: =+MIN(100, (N17 + P17) * Q17) -> 30
A18: 7 | B18: C1 | C18: South | D18: Low | E18: {=IFERROR( _xlfn.XLOOKUP(1, (MARKET_DATA!$A:$A=$A18-1)* (MARKET_DATA!$B:$B=$B18)* (MARKET_DATA!$C:$C=$C18)* (MARKET_DATA!$D:$D=$D18), MARKET_DATA!$J:$J), 0)} -> 0 | F18: {=IFERROR( _xlfn.XLOOKUP(1, (MARKET_DATA!$A:$A=$A18-1)* (MARKET_DATA!$B:$B=$B18)* (MARKET_DATA!$C:$C=$C18)* (MARKET_DATA!$D:$D=$D18), MARKET_DATA!$I:$I), 0)} -> 0 | G18: =20+SUMIFS( INDEX(INNOVATION!$G:$H,,MATCH($D18,{"High";"Low"},0)), INNOVATION!$J:$J, ">="&$A18) -> 23 | H18: {=_xlfn.XLOOKUP(1, (INPUTS_MASTER!$A:$A=$A18)* (INPUTS_MASTER!$B:$B=$B18), INPUTS_MASTER!$F:$F )} -> 35 | I18: {=_xlfn.XLOOKUP(1, (INPUTS_MASTER!$A:$A=$A18)* (INPUTS_MASTER!$B:$B=$B18)* (INPUTS_MASTER!$C:$C=$C18), INPUTS_MASTER!$H:$H )} -> 40 | J18: {=_xlfn.XLOOKUP(1, (INPUTS_MASTER!$A:$A=$A18)* (INPUTS_MASTER!$B:$B=$B18)* (INPUTS_MASTER!$C:$C=$C18), INPUTS_MASTER!$K:$K )} -> 50 | K18: =+IF($D18="High",1, 0.3) -> 0.3 | L18: =+IF($D18="Low",1, 0.3) -> 1 | M18: =+E18 * (1 - $B$3) -> 0 | N18: =+MAX(G18, M18) -> 23 | O18: =+(H18*K18 + I18*L18) * J18/100 -> 25.25 | P18: =+$B$4 * O18 * (1 - N18/100) * (F18/100) -> 0 | Q18: =+IF(D18="High",$B$5, 1) -> 1 | R18: =+MIN(100, (N18 + P18) * Q18) -> 23
A19: 8 | B19: C1 | C19: Center | D19: High
A20: 8 | B20: C1 | C20: Center | D20: Low
A21: 8 | B21: C1 | C21: West | D21: High
A22: 8 | B22: C1 | C22: West | D22: Low
A23: 8 | B23: C1 | C23: North | D23: High
A24: 8 | B24: C1 | C24: North | D24: Low
A25: 8 | B25: C1 | C25: East | D25: High
A26: 8 | B26: C1 | C26: East | D26: Low
A27: 8 | B27: C1 | C27: South | D27: High
A28: 8 | B28: C1 | C28: South | D28: Low
A29: 9 | B29: C1 | C29: Center | D29: High
A30: 9 | B30: C1 | C30: Center | D30: Low
... A68: 12 | B68: C1 | C68: South | D68: Low

Sheet AVAILABILITY
A1: decay | B1: 0.1
A2: months threshold | B2: 2
A3: salesforce quits | B3: 0.2
A4: base effectiveness | B4: 23
A5: diminishing returns exponent | B5: 0.5
A6: adjustment speed | B6: 0.7
A8: Period | B8: Company | C8: Region | D8: Availability (t-1) | E8: Lost Sales Months (t-1) | F8: Salespeople (t) | G8: Morale Factor | H8: Resignation Impact | I8: Effective Salespeople | J8: Availability (t)
A9: 7 | B9: C1 | C9: Center | D9: {=IFERROR( _xlfn.XLOOKUP(1, (MARKET_DATA!$A:$A=$A9-1)* (MARKET_DATA!$B:$B=$B9)* (MARKET_DATA!$C:$C=$C9), MARKET_DATA!$K:$K), 0)} -> 0 | E9: 0 | F9: {=_xlfn.XLOOKUP(1, (INPUTS_MASTER!$A:$A=$A9)* (INPUTS_MASTER!$B:$B=$B9)* (INPUTS_MASTER!$C:$C=$C9), INPUTS_MASTER!$L:$L)} -> 17 | G9: =((1-$B$1)^E9) -> 1 | H9: =IF(E9>=$B$2, 1-$B$3, 1) -> 1 | I9: =F9*G9*H9 -> 17 | J9: =MIN(100, D9 + ($B$4*(I9^$B$5) - D9)*$B$6) -> 66.382001
A10: 7 | B10: C1 | C10: West | D10: {=IFERROR( _xlfn.XLOOKUP(1, (MARKET_DATA!$A:$A=$A10-1)* (MARKET_DATA!$B:$B=$B10)* (MARKET_DATA!$C:$C=$C10), MARKET_DATA!$K:$K), 0)} -> 0 | E10: 0 | F10: {=_xlfn.XLOOKUP(1, (INPUTS_MASTER!$A:$A=$A10)* (INPUTS_MASTER!$B:$B=$B10)* (INPUTS_MASTER!$C:$C=$C10), INPUTS_MASTER!$L:$L)} -> 13 | G10: =((1-$B$1)^E10) -> 1 | H10: =IF(E10>=$B$2, 1-$B$3, 1) -> 1 | I10: =F10*G10*H10 -> 13 | J10: =MIN(100, D10 + ($B$4*(I10^$B$5) - D10)*$B$6) -> 58.049376
A11: 7 | B11: C1 | C11: North | D11: {=IFERROR( _xlfn.XLOOKUP(1, (MARKET_DATA!$A:$A=$A11-1)* (MARKET_DATA!$B:$B=$B11)* (MARKET_DATA!$C:$C=$C11), MARKET_DATA!$K:$K), 0)} -> 0 | E11: 0 | F11: {=_xlfn.XLOOKUP(1, (INPUTS_MASTER!$A:$A=$A11)* (INPUTS_MASTER!$B:$B=$B11)* (INPUTS_MASTER!$C:$C=$C11), INPUTS_MASTER!$L:$L)} -> 14 | G11: =((1-$B$1)^E11) -> 1 | H11: =IF(E11>=$B$2, 1-$B$3, 1) -> 1 | I11: =F11*G11*H11 -> 14 | J11: =MIN(100, D11 + ($B$4*(I11^$B$5) - D11)*$B$6) -> 60.240684
A12: 7 | B12: C1 | C12: East | D12: {=IFERROR( _xlfn.XLOOKUP(1, (MARKET_DATA!$A:$A=$A12-1)* (MARKET_DATA!$B:$B=$B12)* (MARKET_DATA!$C:$C=$C12), MARKET_DATA!$K:$K), 0)} -> 0 | E12: 0 | F12: {=_xlfn.XLOOKUP(1, (INPUTS_MASTER!$A:$A=$A12)* (INPUTS_MASTER!$B:$B=$B12)* (INPUTS_MASTER!$C:$C=$C12), INPUTS_MASTER!$L:$L)} -> 7 | G12: =((1-$B$1)^E12) -> 1 | H12: =IF(E12>=$B$2, 1-$B$3, 1) -> 1 | I12: =F12*G12*H12 -> 7 | J12: =MIN(100, D12 + ($B$4*(I12^$B$5) - D12)*$B$6) -> 42.596596
A13: 7 | B13: C1 | C13: South | D13: {=IFERROR( _xlfn.XLOOKUP(1, (MARKET_DATA!$A:$A=$A13-1)* (MARKET_DATA!$B:$B=$B13)* (MARKET_DATA!$C:$C=$C13), MARKET_DATA!$K:$K), 0)} -> 0 | E13: 0 | F13: {=_xlfn.XLOOKUP(1, (INPUTS_MASTER!$A:$A=$A13)* (INPUTS_MASTER!$B:$B=$B13)* (INPUTS_MASTER!$C:$C=$C13), INPUTS_MASTER!$L:$L)} -> 7 | G13: =((1-$B$1)^E13) -> 1 | H13: =IF(E13>=$B$2, 1-$B$3, 1) -> 1 | I13: =F13*G13*H13 -> 7 | J13: =MIN(100, D13 + ($B$4*(I13^$B$5) - D13)*$B$6) -> 42.596596
A14: 8 | B14: C1 | C14: Center | D14: {=IFERROR( _xlfn.XLOOKUP(1, (MARKET_DATA!$A:$A=$A14-1)* (MARKET_DATA!$B:$B=$B14)* (MARKET_DATA!$C:$C=$C14), MARKET_DATA!$K:$K), 0)} -> 0 | F14: {=_xlfn.XLOOKUP(1, (INPUTS_MASTER!$A:$A=$A14)* (INPUTS_MASTER!$B:$B=$B14)* (INPUTS_MASTER!$C:$C=$C14), INPUTS_MASTER!$L:$L)} -> #N/A
A15: 8 | B15: C1 | C15: West | D15: {=IFERROR( _xlfn.XLOOKUP(1, (MARKET_DATA!$A:$A=$A15-1)* (MARKET_DATA!$B:$B=$B15)* (MARKET_DATA!$C:$C=$C15), MARKET_DATA!$K:$K), 0)} -> 0 | F15: {=_xlfn.XLOOKUP(1, (INPUTS_MASTER!$A:$A=$A15)* (INPUTS_MASTER!$B:$B=$B15)* (INPUTS_MASTER!$C:$C=$C15), INPUTS_MASTER!$L:$L)} -> #N/A
A16: 8 | B16: C1 | C16: North | D16: {=IFERROR( _xlfn.XLOOKUP(1, (MARKET_DATA!$A:$A=$A16-1)* (MARKET_DATA!$B:$B=$B16)* (MARKET_DATA!$C:$C=$C16), MARKET_DATA!$K:$K), 0)} -> 0 | F16: {=_xlfn.XLOOKUP(1, (INPUTS_MASTER!$A:$A=$A16)* (INPUTS_MASTER!$B:$B=$B16)* (INPUTS_MASTER!$C:$C=$C16), INPUTS_MASTER!$L:$L)} -> #N/A
A17: 8 | B17: C1 | C17: East | D17: {=IFERROR( _xlfn.XLOOKUP(1, (MARKET_DATA!$A:$A=$A17-1)* (MARKET_DATA!$B:$B=$B17)* (MARKET_DATA!$C:$C=$C17), MARKET_DATA!$K:$K), 0)} -> 0 | F17: {=_xlfn.XLOOKUP(1, (INPUTS_MASTER!$A:$A=$A17)* (INPUTS_MASTER!$B:$B=$B17)* (INPUTS_MASTER!$C:$C=$C17), INPUTS_MASTER!$L:$L)} -> #N/A
A18: 8 | B18: C1 | C18: South | D18: {=IFERROR( _xlfn.XLOOKUP(1, (MARKET_DATA!$A:$A=$A18-1)* (MARKET_DATA!$B:$B=$B18)* (MARKET_DATA!$C:$C=$C18), MARKET_DATA!$K:$K), 0)} -> 0 | F18: {=_xlfn.XLOOKUP(1, (INPUTS_MASTER!$A:$A=$A18)* (INPUTS_MASTER!$B:$B=$B18)* (INPUTS_MASTER!$C:$C=$C18), INPUTS_MASTER!$L:$L)} -> #N/A
A19: 9 | B19: C1 | C19: Center | D19: {=IFERROR( _xlfn.XLOOKUP(1, (MARKET_DATA!$A:$A=$A19-1)* (MARKET_DATA!$B:$B=$B19)* (MARKET_DATA!$C:$C=$C19), MARKET_DATA!$K:$K), 0)} -> 0 | F19: {=_xlfn.XLOOKUP(1, (INPUTS_MASTER!$A:$A=$A19)* (INPUTS_MASTER!$B:$B=$B19)* (INPUTS_MASTER!$C:$C=$C19), INPUTS_MASTER!$L:$L)} -> #N/A
A20: 9 | B20: C1 | C20: West | D20: {=IFERROR( _xlfn.XLOOKUP(1, (MARKET_DATA!$A:$A=$A20-1)* (MARKET_DATA!$B:$B=$B20)* (MARKET_DATA!$C:$C=$C20), MARKET_DATA!$K:$K), 0)} -> 0 | F20: {=_xlfn.XLOOKUP(1, (INPUTS_MASTER!$A:$A=$A20)* (INPUTS_MASTER!$B:$B=$B20)* (INPUTS_MASTER!$C:$C=$C20), INPUTS_MASTER!$L:$L)} -> #N/A
A21: 9 | B21: C1 | C21: North | D21: {=IFERROR( _xlfn.XLOOKUP(1, (MARKET_DATA!$A:$A=$A21-1)* (MARKET_DATA!$B:$B=$B21)* (MARKET_DATA!$C:$C=$C21), MARKET_DATA!$K:$K), 0)} -> 0 | F21: {=_xlfn.XLOOKUP(1, (INPUTS_MASTER!$A:$A=$A21)* (INPUTS_MASTER!$B:$B=$B21)* (INPUTS_MASTER!$C:$C=$C21), INPUTS_MASTER!$L:$L)} -> #N/A
A22: 9 | B22: C1 | C22: East | D22: {=IFERROR( _xlfn.XLOOKUP(1, (MARKET_DATA!$A:$A=$A22-1)* (MARKET_DATA!$B:$B=$B22)* (MARKET_DATA!$C:$C=$C22), MARKET_DATA!$K:$K), 0)} -> 0 | F22: {=_xlfn.XLOOKUP(1, (INPUTS_MASTER!$A:$A=$A22)* (INPUTS_MASTER!$B:$B=$B22)* (INPUTS_MASTER!$C:$C=$C22), INPUTS_MASTER!$L:$L)} -> #N/A
A23: 9 | B23: C1 | C23: South | D23: {=IFERROR( _xlfn.XLOOKUP(1, (MARKET_DATA!$A:$A=$A23-1)* (MARKET_DATA!$B:$B=$B23)* (MARKET_DATA!$C:$C=$C23), MARKET_DATA!$K:$K), 0)} -> 0 | F23: {=_xlfn.XLOOKUP(1, (INPUTS_MASTER!$A:$A=$A23)* (INPUTS_MASTER!$B:$B=$B23)* (INPUTS_MASTER!$C:$C=$C23), INPUTS_MASTER!$L:$L)} -> #N/A
A24: 10 | B24: C1 | C24: Center | D24: {=IFERROR( _xlfn.XLOOKUP(1, (MARKET_DATA!$A:$A=$A24-1)* (MARKET_DATA!$B:$B=$B24)* (MARKET_DATA!$C:$C=$C24), MARKET_DATA!$K:$K), 0)} -> 0 | F24: {=_xlfn.XLOOKUP(1, (INPUTS_MASTER!$A:$A=$A24)* (INPUTS_MASTER!$B:$B=$B24)* (INPUTS_MASTER!$C:$C=$C24), INPUTS_MASTER!$L:$L)} -> #N/A
A25: 10 | B25: C1 | C25: West | D25: {=IFERROR( _xlfn.XLOOKUP(1, (MARKET_DATA!$A:$A=$A25-1)* (MARKET_DATA!$B:$B=$B25)* (MARKET_DATA!$C:$C=$C25), MARKET_DATA!$K:$K), 0)} -> 0 | F25: {=_xlfn.XLOOKUP(1, (INPUTS_MASTER!$A:$A=$A25)* (INPUTS_MASTER!$B:$B=$B25)* (INPUTS_MASTER!$C:$C=$C25), INPUTS_MASTER!$L:$L)} -> #N/A
... A38: 12 | B38: C1 | C38: South | D38: {=IFERROR( _xlfn.XLOOKUP(1, (MARKET_DATA!$A:$A=$A38-1)* (MARKET_DATA!$B:$B=$B38)* (MARKET_DATA!$C:$C=$C38), MARKET_DATA!$K:$K), 0)} -> 0 | F38: {=_xlfn.XLOOKUP(1, (INPUTS_MASTER!$A:$A=$A38)* (INPUTS_MASTER!$B:$B=$B38)* (INPUTS_MASTER!$C:$C=$C38), INPUTS_MASTER!$L:$L)} -> #N/A

Sheet PRICE_P
A1: Price Sensitivity - Low segment | B1: 2
A2: Price Sensitivity - High segment | B2: 1
A3: Price Score min | B3: 50
A4: Price Score max | B4: 110
A6: Period | B6: Company | C6: Region | D6: Segment | E6: Price (t-1) | F6: Avg Market Price (t-1) | G6: Price Ratio | H6: Price Sensitivity | I6: Raw Price Score | J6: Price Score (t)
A7: 7 | B7: C1 | C7: Center | D7: High | E7: {=IFERROR(_xlfn.XLOOKUP(1, (INPUTS_MASTER!$A:$A=$A7-1)* (INPUTS_MASTER!$B:$B=$B7)* (INPUTS_MASTER!$C:$C=$C7), INPUTS_MASTER!$E:$E),0)} -> 68 | F7: =AVERAGEIFS(MARKET_DATA!H:H, MARKET_DATA!$A:$A,$A7-1, MARKET_DATA!$C:$C,$C7) -> 68 | G7: =IFERROR(+F7/E7,0) -> 1 | H7: =+IF(D7="High", $B$2, $B$1) -> 1 | I7: =100 * (G7^H7) -> 100 | J7: =+MIN($B$4,MAX($B$3, I7)) -> 100
A8: 7 | B8: C1 | C8: West | D8: High | E8: {=IFERROR(_xlfn.XLOOKUP(1, (INPUTS_MASTER!$A:$A=$A8-1)* (INPUTS_MASTER!$B:$B=$B8)* (INPUTS_MASTER!$C:$C=$C8), INPUTS_MASTER!$E:$E),0)} -> 68 | F8: =AVERAGEIFS(MARKET_DATA!H:H, MARKET_DATA!$A:$A,$A8-1, MARKET_DATA!$C:$C,$C8) -> 68 | G8: =IFERROR(+F8/E8,0) -> 1 | H8: =+IF(D8="High", $B$2, $B$1) -> 1 | I8: =100 * (G8^H8) -> 100 | J8: =+MIN($B$4,MAX($B$3, I8)) -> 100
A9: 7 | B9: C1 | C9: North | D9: High | E9: {=IFERROR(_xlfn.XLOOKUP(1, (INPUTS_MASTER!$A:$A=$A9-1)* (INPUTS_MASTER!$B:$B=$B9)* (INPUTS_MASTER!$C:$C=$C9), INPUTS_MASTER!$E:$E),0)} -> 91 | F9: =AVERAGEIFS(MARKET_DATA!H:H, MARKET_DATA!$A:$A,$A9-1, MARKET_DATA!$C:$C,$C9) -> 91 | G9: =IFERROR(+F9/E9,0) -> 1 | H9: =+IF(D9="High", $B$2, $B$1) -> 1 | I9: =100 * (G9^H9) -> 100 | J9: =+MIN($B$4,MAX($B$3, I9)) -> 100
A10: 7 | B10: C1 | C10: East | D10: High | E10: {=IFERROR(_xlfn.XLOOKUP(1, (INPUTS_MASTER!$A:$A=$A10-1)* (INPUTS_MASTER!$B:$B=$B10)* (INPUTS_MASTER!$C:$C=$C10), INPUTS_MASTER!$E:$E),0)} -> 0 | F10: =AVERAGEIFS(MARKET_DATA!H:H, MARKET_DATA!$A:$A,$A10-1, MARKET_DATA!$C:$C,$C10) -> 0 | G10: =IFERROR(+F10/E10,0) -> 0 | H10: =+IF(D10="High", $B$2, $B$1) -> 1 | I10: =100 * (G10^H10) -> 0 | J10: =+MIN($B$4,MAX($B$3, I10)) -> 50
A11: 7 | B11: C1 | C11: South | D11: High | E11: {=IFERROR(_xlfn.XLOOKUP(1, (INPUTS_MASTER!$A:$A=$A11-1)* (INPUTS_MASTER!$B:$B=$B11)* (INPUTS_MASTER!$C:$C=$C11), INPUTS_MASTER!$E:$E),0)} -> 0 | F11: =AVERAGEIFS(MARKET_DATA!H:H, MARKET_DATA!$A:$A,$A11-1, MARKET_DATA!$C:$C,$C11) -> 0 | G11: =IFERROR(+F11/E11,0) -> 0 | H11: =+IF(D11="High", $B$2, $B$1) -> 1 | I11: =100 * (G11^H11) -> 0 | J11: =+MIN($B$4,MAX($B$3, I11)) -> 50
A12: 7 | B12: C1 | C12: Center | D12: Low | E12: {=IFERROR(_xlfn.XLOOKUP(1, (INPUTS_MASTER!$A:$A=$A12-1)* (INPUTS_MASTER!$B:$B=$B12)* (INPUTS_MASTER!$C:$C=$C12), INPUTS_MASTER!$E:$E),0)} -> 68 | F12: =AVERAGEIFS(MARKET_DATA!H:H, MARKET_DATA!$A:$A,$A12-1, MARKET_DATA!$C:$C,$C12) -> 68 | G12: =IFERROR(+F12/E12,0) -> 1 | H12: =+IF(D12="High", $B$2, $B$1) -> 2 | I12: =100 * (G12^H12) -> 100 | J12: =+MIN($B$4,MAX($B$3, I12)) -> 100
A13: 7 | B13: C1 | C13: West | D13: Low | E13: {=IFERROR(_xlfn.XLOOKUP(1, (INPUTS_MASTER!$A:$A=$A13-1)* (INPUTS_MASTER!$B:$B=$B13)* (INPUTS_MASTER!$C:$C=$C13), INPUTS_MASTER!$E:$E),0)} -> 68 | F13: =AVERAGEIFS(MARKET_DATA!H:H, MARKET_DATA!$A:$A,$A13-1, MARKET_DATA!$C:$C,$C13) -> 68 | G13: =IFERROR(+F13/E13,0) -> 1 | H13: =+IF(D13="High", $B$2, $B$1) -> 2 | I13: =100 * (G13^H13) -> 100 | J13: =+MIN($B$4,MAX($B$3, I13)) -> 100
A14: 7 | B14: C1 | C14: North | D14: Low | E14: {=IFERROR(_xlfn.XLOOKUP(1, (INPUTS_MASTER!$A:$A=$A14-1)* (INPUTS_MASTER!$B:$B=$B14)* (INPUTS_MASTER!$C:$C=$C14), INPUTS_MASTER!$E:$E),0)} -> 91 | F14: =AVERAGEIFS(MARKET_DATA!H:H, MARKET_DATA!$A:$A,$A14-1, MARKET_DATA!$C:$C,$C14) -> 91 | G14: =IFERROR(+F14/E14,0) -> 1 | H14: =+IF(D14="High", $B$2, $B$1) -> 2 | I14: =100 * (G14^H14) -> 100 | J14: =+MIN($B$4,MAX($B$3, I14)) -> 100
A15: 7 | B15: C1 | C15: East | D15: Low | E15: {=IFERROR(_xlfn.XLOOKUP(1, (INPUTS_MASTER!$A:$A=$A15-1)* (INPUTS_MASTER!$B:$B=$B15)* (INPUTS_MASTER!$C:$C=$C15), INPUTS_MASTER!$E:$E),0)} -> 0 | F15: =AVERAGEIFS(MARKET_DATA!H:H, MARKET_DATA!$A:$A,$A15-1, MARKET_DATA!$C:$C,$C15) -> 0 | G15: =IFERROR(+F15/E15,0) -> 0 | H15: =+IF(D15="High", $B$2, $B$1) -> 2 | I15: =100 * (G15^H15) -> 0 | J15: =+MIN($B$4,MAX($B$3, I15)) -> 50
A16: 7 | B16: C1 | C16: South | D16: Low | E16: {=IFERROR(_xlfn.XLOOKUP(1, (INPUTS_MASTER!$A:$A=$A16-1)* (INPUTS_MASTER!$B:$B=$B16)* (INPUTS_MASTER!$C:$C=$C16), INPUTS_MASTER!$E:$E),0)} -> 0 | F16: =AVERAGEIFS(MARKET_DATA!H:H, MARKET_DATA!$A:$A,$A16-1, MARKET_DATA!$C:$C,$C16) -> 0 | G16: =IFERROR(+F16/E16,0) -> 0 | H16: =+IF(D16="High", $B$2, $B$1) -> 2 | I16: =100 * (G16^H16) -> 0 | J16: =+MIN($B$4,MAX($B$3, I16)) -> 50
A17: 8 | B17: C1 | C17: Center | D17: High | E17: {=IFERROR(_xlfn.XLOOKUP(1, (INPUTS_MASTER!$A:$A=$A17-1)* (INPUTS_MASTER!$B:$B=$B17)* (INPUTS_MASTER!$C:$C=$C17), INPUTS_MASTER!$E:$E),0)} -> 69 | F17: =AVERAGEIFS(MARKET_DATA!H:H, MARKET_DATA!$A:$A,$A17-1, MARKET_DATA!$C:$C,$C17) -> #DIV/0! | G17: =IFERROR(+F17/E17,0) -> 0
A18: 8 | B18: C1 | C18: West | D18: High | E18: {=IFERROR(_xlfn.XLOOKUP(1, (INPUTS_MASTER!$A:$A=$A18-1)* (INPUTS_MASTER!$B:$B=$B18)* (INPUTS_MASTER!$C:$C=$C18), INPUTS_MASTER!$E:$E),0)} -> 69 | F18: =AVERAGEIFS(MARKET_DATA!H:H, MARKET_DATA!$A:$A,$A18-1, MARKET_DATA!$C:$C,$C18) -> #DIV/0! | G18: =IFERROR(+F18/E18,0) -> 0
A19: 8 | B19: C1 | C19: North | D19: High | E19: {=IFERROR(_xlfn.XLOOKUP(1, (INPUTS_MASTER!$A:$A=$A19-1)* (INPUTS_MASTER!$B:$B=$B19)* (INPUTS_MASTER!$C:$C=$C19), INPUTS_MASTER!$E:$E),0)} -> 92 | F19: =AVERAGEIFS(MARKET_DATA!H:H, MARKET_DATA!$A:$A,$A19-1, MARKET_DATA!$C:$C,$C19) -> #DIV/0! | G19: =IFERROR(+F19/E19,0) -> 0
A20: 8 | B20: C1 | C20: East | D20: High | E20: {=IFERROR(_xlfn.XLOOKUP(1, (INPUTS_MASTER!$A:$A=$A20-1)* (INPUTS_MASTER!$B:$B=$B20)* (INPUTS_MASTER!$C:$C=$C20), INPUTS_MASTER!$E:$E),0)} -> 65 | F20: =AVERAGEIFS(MARKET_DATA!H:H, MARKET_DATA!$A:$A,$A20-1, MARKET_DATA!$C:$C,$C20) -> #DIV/0! | G20: =IFERROR(+F20/E20,0) -> 0
A21: 8 | B21: C1 | C21: South | D21: High | E21: {=IFERROR(_xlfn.XLOOKUP(1, (INPUTS_MASTER!$A:$A=$A21-1)* (INPUTS_MASTER!$B:$B=$B21)* (INPUTS_MASTER!$C:$C=$C21), INPUTS_MASTER!$E:$E),0)} -> 65 | F21: =AVERAGEIFS(MARKET_DATA!H:H, MARKET_DATA!$A:$A,$A21-1, MARKET_DATA!$C:$C,$C21) -> #DIV/0! | G21: =IFERROR(+F21/E21,0) -> 0
A22: 9 | B22: C1 | C22: Center | D22: High | E22: {=IFERROR(_xlfn.XLOOKUP(1, (INPUTS_MASTER!$A:$A=$A22-1)* (INPUTS_MASTER!$B:$B=$B22)* (INPUTS_MASTER!$C:$C=$C22), INPUTS_MASTER!$E:$E),0)} -> 0 | F22: =AVERAGEIFS(MARKET_DATA!H:H, MARKET_DATA!$A:$A,$A22-1, MARKET_DATA!$C:$C,$C22) -> #DIV/0! | G22: =IFERROR(+F22/E22,0) -> 0
A23: 9 | B23: C1 | C23: West | D23: High | E23: {=IFERROR(_xlfn.XLOOKUP(1, (INPUTS_MASTER!$A:$A=$A23-1)* (INPUTS_MASTER!$B:$B=$B23)* (INPUTS_MASTER!$C:$C=$C23), INPUTS_MASTER!$E:$E),0)} -> 0 | F23: =AVERAGEIFS(MARKET_DATA!H:H, MARKET_DATA!$A:$A,$A23-1, MARKET_DATA!$C:$C,$C23) -> #DIV/0! | G23: =IFERROR(+F23/E23,0) -> 0
A24: 9 | B24: C1 | C24: North | D24: High | E24: {=IFERROR(_xlfn.XLOOKUP(1, (INPUTS_MASTER!$A:$A=$A24-1)* (INPUTS_MASTER!$B:$B=$B24)* (INPUTS_MASTER!$C:$C=$C24), INPUTS_MASTER!$E:$E),0)} -> 0 | F24: =AVERAGEIFS(MARKET_DATA!H:H, MARKET_DATA!$A:$A,$A24-1, MARKET_DATA!$C:$C,$C24) -> #DIV/0! | G24: =IFERROR(+F24/E24,0) -> 0
A25: 9 | B25: C1 | C25: East | D25: High | E25: {=IFERROR(_xlfn.XLOOKUP(1, (INPUTS_MASTER!$A:$A=$A25-1)* (INPUTS_MASTER!$B:$B=$B25)* (INPUTS_MASTER!$C:$C=$C25), INPUTS_MASTER!$E:$E),0)} -> 0 | F25: =AVERAGEIFS(MARKET_DATA!H:H, MARKET_DATA!$A:$A,$A25-1, MARKET_DATA!$C:$C,$C25) -> #DIV/0! | G25: =IFERROR(+F25/E25,0) -> 0
A26: 9 | B26: C1 | C26: South | D26: High | E26: {=IFERROR(_xlfn.XLOOKUP(1, (INPUTS_MASTER!$A:$A=$A26-1)* (INPUTS_MASTER!$B:$B=$B26)* (INPUTS_MASTER!$C:$C=$C26), INPUTS_MASTER!$E:$E),0)} -> 0 | F26: =AVERAGEIFS(MARKET_DATA!H:H, MARKET_DATA!$A:$A,$A26-1, MARKET_DATA!$C:$C,$C26) -> #DIV/0! | G26: =IFERROR(+F26/E26,0) -> 0
A27: 10 | B27: C1 | C27: Center | D27: High | E27: {=IFERROR(_xlfn.XLOOKUP(1, (INPUTS_MASTER!$A:$A=$A27-1)* (INPUTS_MASTER!$B:$B=$B27)* (INPUTS_MASTER!$C:$C=$C27), INPUTS_MASTER!$E:$E),0)} -> 0 | F27: =AVERAGEIFS(MARKET_DATA!H:H, MARKET_DATA!$A:$A,$A27-1, MARKET_DATA!$C:$C,$C27) -> #DIV/0! | G27: =IFERROR(+F27/E27,0) -> 0
A28: 10 | B28: C1 | C28: West | D28: High | E28: {=IFERROR(_xlfn.XLOOKUP(1, (INPUTS_MASTER!$A:$A=$A28-1)* (INPUTS_MASTER!$B:$B=$B28)* (INPUTS_MASTER!$C:$C=$C28), INPUTS_MASTER!$E:$E),0)} -> 0 | F28: =AVERAGEIFS(MARKET_DATA!H:H, MARKET_DATA!$A:$A,$A28-1, MARKET_DATA!$C:$C,$C28) -> #DIV/0! | G28: =IFERROR(+F28/E28,0) -> 0
... A41: 12 | B41: C1 | C41: South | D41: High | E41: {=IFERROR(_xlfn.XLOOKUP(1, (INPUTS_MASTER!$A:$A=$A41-1)* (INPUTS_MASTER!$B:$B=$B41)* (INPUTS_MASTER!$C:$C=$C41), INPUTS_MASTER!$E:$E),0)} -> 0 | F41: =AVERAGEIFS(MARKET_DATA!H:H, MARKET_DATA!$A:$A,$A41-1, MARKET_DATA!$C:$C,$C41) -> #DIV/0! | G41: =IFERROR(+F41/E41,0) -> 0
A42: 8 | B42: C1 | C42: Center | D42: Low
A43: 8 | B43: C1 | C43: West | D43: Low
A44: 8 | B44: C1 | C44: North | D44: Low
A45: 8 | B45: C1 | C45: East | D45: Low
A46: 8 | B46: C1 | C46: South | D46: Low
A47: 9 | B47: C1 | C47: Center | D47: Low
A48: 9 | B48: C1 | C48: West | D48: Low
A49: 9 | B49: C1 | C49: North | D49: Low
A50: 9 | B50: C1 | C50: East | D50: Low
A51: 9 | B51: C1 | C51: South | D51: Low
A52: 10 | B52: C1 | C52: Center | D52: Low
A53: 10 | B53: C1 | C53: West | D53: Low
... A66: 12 | B66: C1 | C66: South | D66: Low

Sheet MS_ALLOCATION
A1: Awar W | B1: 0.26
A2: Attr W | B2: 0.19
A3: Avai W | B3: 0.26
A4: Pri W | B4: 0.3
A5: Inertia W | B5: 0.556
A6: competitors | B6: 3
A7: λ_initial | B7: 0.25
A8: λ_mature | B8: 0.6
A9: periods to maturity | B9: 8
A11: Period | B11: Company | C11: Region | D11: Segment | E11: Awareness % (t) | F11: Attractiveness % (t) | G11: Availability % (t) | H11: Price Score (t) | I11: Avg Market Awareness | J11: Avg Market Attractiveness | K11: Avg Market Availability | L11: Avg Market Price Score | M11: Utility | N11: Avg Competitor Utility | O11: Achievable Market Share | P11: Market Share (t-1) | Q11: Final Market Share (t)
A12: 7 | B12: C1 | C12: Center | D12: High | E12: {=+_xlfn.XLOOKUP(1, (AWARENESS!A:A=A12)* (AWARENESS!B:B=B12)* (AWARENESS!C:C=C12)* (AWARENESS!D:D=D12), AWARENESS!Q:Q)} -> 15.720097 | F12: {=+_xlfn.XLOOKUP(1, (ATTRACTIVENESS!A:A=A12)* (ATTRACTIVENESS!B:B=B12)* (ATTRACTIVENESS!C:C=C12)* (ATTRACTIVENESS!D:D=D12), ATTRACTIVENESS!R:R)} -> 30 | G12: {=+_xlfn.XLOOKUP(1, (AVAILABILITY!A:A=A12)* (AVAILABILITY!B:B=B12)* (AVAILABILITY!C:C=C12), AVAILABILITY!J:J)} -> 66.382001 | H12: {=+_xlfn.XLOOKUP(1, (PRICE_P!A:A=A12)* (PRICE_P!B:B=B12)* (PRICE_P!C:C=C12)* (PRICE_P!D:D=D12), PRICE_P!J:J)} -> 100 | I12: {=IFERROR( _xlfn.XLOOKUP(1, (MARKET_DATA!$A:$A=$A12-1)* (MARKET_DATA!$B:$B=$B12)* (MARKET_DATA!$C:$C=$C12)* (MARKET_DATA!$D:$D=$D12), MARKET_DATA!$I:$I), 0)} -> 0 | J12: {=IFERROR( _xlfn.XLOOKUP(1, (MARKET_DATA!$A:$A=$A12-1)* (MARKET_DATA!$B:$B=$B12)* (MARKET_DATA!$C:$C=$C12)* (MARKET_DATA!$D:$D=$D12), MARKET_DATA!$J:$J), 0)} -> 0 | K12: {=IFERROR( _xlfn.XLOOKUP(1, (MARKET_DATA!$A:$A=$A12-1)* (MARKET_DATA!$B:$B=$B12)* (MARKET_DATA!$C:$C=$C12)* (MARKET_DATA!$D:$D=$D12), MARKET_DATA!$K:$K), 0)} -> 0 | L12: {=IFERROR( _xlfn.XLOOKUP(1, (MARKET_DATA!$A:$A=$A12-1)* (MARKET_DATA!$B:$B=$B12)* (MARKET_DATA!$C:$C=$C12)* (MARKET_DATA!$D:$D=$D12), MARKET_DATA!$H:$H), 0)} -> 0 | M12: =+$B$1*E12 + $B$2*F12 + $B$3*G12 + $B$4*H12 -> 57.046545 | N12: =+$B$1*I12 + $B$2*J12 + $B$3*K12 + $B$4*L12 -> 0 | O12: =M12 / (M12 + $B$6*N12)*100 -> 100 | P12: {=IFERROR( _xlfn.XLOOKUP(1, (MARKET_DATA!$A:$A=$A12-1)* (MARKET_DATA!$B:$B=$B12)* (MARKET_DATA!$C:$C=$C12)* (MARKET_DATA!$D:$D=$D12), MARKET_DATA!$G:$G), 0)} -> 0 | Q12: =+$B$5*P12 + (1-$B$5)*O12 -> 44.4
A13: 7 | B13: C1 | C13: West | D13: High | E13: {=+_xlfn.XLOOKUP(1, (AWARENESS!A:A=A13)* (AWARENESS!B:B=B13)* (AWARENESS!C:C=C13)* (AWARENESS!D:D=D13), AWARENESS!Q:Q)} -> 11.071795 | F13: {=+_xlfn.XLOOKUP(1, (ATTRACTIVENESS!A:A=A13)* (ATTRACTIVENESS!B:B=B13)* (ATTRACTIVENESS!C:C=C13)* (ATTRACTIVENESS!D:D=D13), ATTRACTIVENESS!R:R)} -> 30 | G13: {=+_xlfn.XLOOKUP(1, (AVAILABILITY!A:A=A13)* (AVAILABILITY!B:B=B13)* (AVAILABILITY!C:C=C13), AVAILABILITY!J:J)} -> 58.049376 | H13: {=+_xlfn.XLOOKUP(1, (PRICE_P!A:A=A13)* (PRICE_P!B:B=B13)* (PRICE_P!C:C=C13)* (PRICE_P!D:D=D13), PRICE_P!J:J)} -> 100 | I13: {=IFERROR( _xlfn.XLOOKUP(1, (MARKET_DATA!$A:$A=$A13-1)* (MARKET_DATA!$B:$B=$B13)* (MARKET_DATA!$C:$C=$C13)* (MARKET_DATA!$D:$D=$D13), MARKET_DATA!$I:$I), 0)} -> 0 | J13: {=IFERROR( _xlfn.XLOOKUP(1, (MARKET_DATA!$A:$A=$A13-1)* (MARKET_DATA!$B:$B=$B13)* (MARKET_DATA!$C:$C=$C13)* (MARKET_DATA!$D:$D=$D13), MARKET_DATA!$J:$J), 0)} -> 0 | K13: {=IFERROR( _xlfn.XLOOKUP(1, (MARKET_DATA!$A:$A=$A13-1)* (MARKET_DATA!$B:$B=$B13)* (MARKET_DATA!$C:$C=$C13)* (MARKET_DATA!$D:$D=$D13), MARKET_DATA!$K:$K), 0)} -> 0 | L13: {=IFERROR( _xlfn.XLOOKUP(1, (MARKET_DATA!$A:$A=$A13-1)* (MARKET_DATA!$B:$B=$B13)* (MARKET_DATA!$C:$C=$C13)* (MARKET_DATA!$D:$D=$D13), MARKET_DATA!$H:$H), 0)} -> 0 | M13: =+$B$1*E13 + $B$2*F13 + $B$3*G13 + $B$4*H13 -> 53.671504 | N13: =+$B$1*I13 + $B$2*J13 + $B$3*K13 + $B$4*L13 -> 0 | O13: =M13 / (M13 + $B$6*N13)*100 -> 100 | P13: {=IFERROR( _xlfn.XLOOKUP(1, (MARKET_DATA!$A:$A=$A13-1)* (MARKET_DATA!$B:$B=$B13)* (MARKET_DATA!$C:$C=$C13)* (MARKET_DATA!$D:$D=$D13), MARKET_DATA!$G:$G), 0)} -> 0 | Q13: =+$B$5*P13 + (1-$B$5)*O13 -> 44.4
A14: 7 | B14: C1 | C14: North | D14: High | E14: {=+_xlfn.XLOOKUP(1, (AWARENESS!A:A=A14)* (AWARENESS!B:B=B14)* (AWARENESS!C:C=C14)* (AWARENESS!D:D=D14), AWARENESS!Q:Q)} -> 10.519273 | F14: {=+_xlfn.XLOOKUP(1, (ATTRACTIVENESS!A:A=A14)* (ATTRACTIVENESS!B:B=B14)* (ATTRACTIVENESS!C:C=C14)* (ATTRACTIVENESS!D:D=D14), ATTRACTIVENESS!R:R)} -> 30 | G14: {=+_xlfn.XLOOKUP(1, (AVAILABILITY!A:A=A14)* (AVAILABILITY!B:B=B14)* (AVAILABILITY!C:C=C14), AVAILABILITY!J:J)} -> 60.240684 | H14: {=+_xlfn.XLOOKUP(1, (PRICE_P!A:A=A14)* (PRICE_P!B:B=B14)* (PRICE_P!C:C=C14)* (PRICE_P!D:D=D14), PRICE_P!J:J)} -> 100 | I14: {=IFERROR( _xlfn.XLOOKUP(1, (MARKET_DATA!$A:$A=$A14-1)* (MARKET_DATA!$B:$B=$B14)* (MARKET_DATA!$C:$C=$C14)* (MARKET_DATA!$D:$D=$D14), MARKET_DATA!$I:$I), 0)} -> 0 | J14: {=IFERROR( _xlfn.XLOOKUP(1, (MARKET_DATA!$A:$A=$A14-1)* (MARKET_DATA!$B:$B=$B14)* (MARKET_DATA!$C:$C=$C14)* (MARKET_DATA!$D:$D=$D14), MARKET_DATA!$J:$J), 0)} -> 0 | K14: {=IFERROR( _xlfn.XLOOKUP(1, (MARKET_DATA!$A:$A=$A14-1)* (MARKET_DATA!$B:$B=$B14)* (MARKET_DATA!$C:$C=$C14)* (MARKET_DATA!$D:$D=$D14), MARKET_DATA!$K:$K), 0)} -> 0 | L14: {=IFERROR( _xlfn.XLOOKUP(1, (MARKET_DATA!$A:$A=$A14-1)* (MARKET_DATA!$B:$B=$B14)* (MARKET_DATA!$C:$C=$C14)* (MARKET_DATA!$D:$D=$D14), MARKET_DATA!$H:$H), 0)} -> 0 | M14: =+$B$1*E14 + $B$2*F14 + $B$3*G14 + $B$4*H14 -> 54.097589 | N14: =+$B$1*I14 + $B$2*J14 + $B$3*K14 + $B$4*L14 -> 0 | O14: =M14 / (M14 + $B$6*N14)*100 -> 100 | P14: {=IFERROR( _xlfn.XLOOKUP(1, (MARKET_DATA!$A:$A=$A14-1)* (MARKET_DATA!$B:$B=$B14)* (MARKET_DATA!$C:$C=$C14)* (MARKET_DATA!$D:$D=$D14), MARKET_DATA!$G:$G), 0)} -> 0 | Q14: =+$B$5*P14 + (1-$B$5)*O14 -> 44.4
A15: 7 | B15: C1 | C15: East | D15: High | E15: {=+_xlfn.XLOOKUP(1, (AWARENESS!A:A=A15)* (AWARENESS!B:B=B15)* (AWARENESS!C:C=C15)* (AWARENESS!D:D=D15), AWARENESS!Q:Q)} -> 9.4 | F15: {=+_xlfn.XLOOKUP(1, (ATTRACTIVENESS!A:A=A15)* (ATTRACTIVENESS!B:B=B15)* (ATTRACTIVENESS!C:C=C15)* (ATTRACTIVENESS!D:D=D15), ATTRACTIVENESS!R:R)} -> 30 | G15: {=+_xlfn.XLOOKUP(1, (AVAILABILITY!A:A=A15)* (AVAILABILITY!B:B=B15)* (AVAILABILITY!C:C=C15), AVAILABILITY!J:J)} -> 42.596596 | H15: {=+_xlfn.XLOOKUP(1, (PRICE_P!A:A=A15)* (PRICE_P!B:B=B15)* (PRICE_P!C:C=C15)* (PRICE_P!D:D=D15), PRICE_P!J:J)} -> 50 | I15: {=IFERROR( _xlfn.XLOOKUP(1, (MARKET_DATA!$A:$A=$A15-1)* (MARKET_DATA!$B:$B=$B15)* (MARKET_DATA!$C:$C=$C15)* (MARKET_DATA!$D:$D=$D15), MARKET_DATA!$I:$I), 0)} -> 0 | J15: {=IFERROR( _xlfn.XLOOKUP(1, (MARKET_DATA!$A:$A=$A15-1)* (MARKET_DATA!$B:$B=$B15)* (MARKET_DATA!$C:$C=$C15)* (MARKET_DATA!$D:$D=$D15), MARKET_DATA!$J:$J), 0)} -> 0 | K15: {=IFERROR( _xlfn.XLOOKUP(1, (MARKET_DATA!$A:$A=$A15-1)* (MARKET_DATA!$B:$B=$B15)* (MARKET_DATA!$C:$C=$C15)* (MARKET_DATA!$D:$D=$D15), MARKET_DATA!$K:$K), 0)} -> 0 | L15: {=IFERROR( _xlfn.XLOOKUP(1, (MARKET_DATA!$A:$A=$A15-1)* (MARKET_DATA!$B:$B=$B15)* (MARKET_DATA!$C:$C=$C15)* (MARKET_DATA!$D:$D=$D15), MARKET_DATA!$H:$H), 0)} -> 0 | M15: =+$B$1*E15 + $B$2*F15 + $B$3*G15 + $B$4*H15 -> 34.219115 | N15: =+$B$1*I15 + $B$2*J15 + $B$3*K15 + $B$4*L15 -> 0 | O15: =M15 / (M15 + $B$6*N15)*100 -> 100 | P15: {=IFERROR( _xlfn.XLOOKUP(1, (MARKET_DATA!$A:$A=$A15-1)* (MARKET_DATA!$B:$B=$B15)* (MARKET_DATA!$C:$C=$C15)* (MARKET_DATA!$D:$D=$D15), MARKET_DATA!$G:$G), 0)} -> 0 | Q15: =+$B$5*P15 + (1-$B$5)*O15 -> 44.4
A16: 7 | B16: C1 | C16: South | D16: High | E16: {=+_xlfn.XLOOKUP(1, (AWARENESS!A:A=A16)* (AWARENESS!B:B=B16)* (AWARENESS!C:C=C16)* (AWARENESS!D:D=D16), AWARENESS!Q:Q)} -> 9.4 | F16: {=+_xlfn.XLOOKUP(1, (ATTRACTIVENESS!A:A=A16)* (ATTRACTIVENESS!B:B=B16)* (ATTRACTIVENESS!C:C=C16)* (ATTRACTIVENESS!D:D=D16), ATTRACTIVENESS!R:R)} -> 30 | G16: {=+_xlfn.XLOOKUP(1, (AVAILABILITY!A:A=A16)* (AVAILABILITY!B:B=B16)* (AVAILABILITY!C:C=C16), AVAILABILITY!J:J)} -> 42.596596 | H16: {=+_xlfn.XLOOKUP(1, (PRICE_P!A:A=A16)* (PRICE_P!B:B=B16)* (PRICE_P!C:C=C16)* (PRICE_P!D:D=D16), PRICE_P!J:J)} -> 50 | I16: {=IFERROR( _xlfn.XLOOKUP(1, (MARKET_DATA!$A:$A=$A16-1)* (MARKET_DATA!$B:$B=$B16)* (MARKET_DATA!$C:$C=$C16)* (MARKET_DATA!$D:$D=$D16), MARKET_DATA!$I:$I), 0)} -> 0 | J16: {=IFERROR( _xlfn.XLOOKUP(1, (MARKET_DATA!$A:$A=$A16-1)* (MARKET_DATA!$B:$B=$B16)* (MARKET_DATA!$C:$C=$C16)* (MARKET_DATA!$D:$D=$D16), MARKET_DATA!$J:$J), 0)} -> 0 | K16: {=IFERROR( _xlfn.XLOOKUP(1, (MARKET_DATA!$A:$A=$A16-1)* (MARKET_DATA!$B:$B=$B16)* (MARKET_DATA!$C:$C=$C16)* (MARKET_DATA!$D:$D=$D16), MARKET_DATA!$K:$K), 0)} -> 0 | L16: {=IFERROR( _xlfn.XLOOKUP(1, (MARKET_DATA!$A:$A=$A16-1)* (MARKET_DATA!$B:$B=$B16)* (MARKET_DATA!$C:$C=$C16)* (MARKET_DATA!$D:$D=$D16), MARKET_DATA!$H:$H), 0)} -> 0 | M16: =+$B$1*E16 + $B$2*F16 + $B$3*G16 + $B$4*H16 -> 34.219115 | N16: =+$B$1*I16 + $B$2*J16 + $B$3*K16 + $B$4*L16 -> 0 | O16: =M16 / (M16 + $B$6*N16)*100 -> 100 | P16: {=IFERROR( _xlfn.XLOOKUP(1, (MARKET_DATA!$A:$A=$A16-1)* (MARKET_DATA!$B:$B=$B16)* (MARKET_DATA!$C:$C=$C16)* (MARKET_DATA!$D:$D=$D16), MARKET_DATA!$G:$G), 0)} -> 0 | Q16: =+$B$5*P16 + (1-$B$5)*O16 -> 44.4
A17: 7 | B17: C1 | C17: Center | D17: Low | E17: {=+_xlfn.XLOOKUP(1, (AWARENESS!A:A=A17)* (AWARENESS!B:B=B17)* (AWARENESS!C:C=C17)* (AWARENESS!D:D=D17), AWARENESS!Q:Q)} -> 38.514624 | F17: {=+_xlfn.XLOOKUP(1, (ATTRACTIVENESS!A:A=A17)* (ATTRACTIVENESS!B:B=B17)* (ATTRACTIVENESS!C:C=C17)* (ATTRACTIVENESS!D:D=D17), ATTRACTIVENESS!R:R)} -> 23 | G17: {=+_xlfn.XLOOKUP(1, (AVAILABILITY!A:A=A17)* (AVAILABILITY!B:B=B17)* (AVAILABILITY!C:C=C17), AVAILABILITY!J:J)} -> 66.382001 | H17: {=+_xlfn.XLOOKUP(1, (PRICE_P!A:A=A17)* (PRICE_P!B:B=B17)* (PRICE_P!C:C=C17)* (PRICE_P!D:D=D17), PRICE_P!J:J)} -> 100 | I17: {=IFERROR( _xlfn.XLOOKUP(1, (MARKET_DATA!$A:$A=$A17-1)* (MARKET_DATA!$B:$B=$B17)* (MARKET_DATA!$C:$C=$C17)* (MARKET_DATA!$D:$D=$D17), MARKET_DATA!$I:$I), 0)} -> 0 | J17: {=IFERROR( _xlfn.XLOOKUP(1, (MARKET_DATA!$A:$A=$A17-1)* (MARKET_DATA!$B:$B=$B17)* (MARKET_DATA!$C:$C=$C17)* (MARKET_DATA!$D:$D=$D17), MARKET_DATA!$J:$J), 0)} -> 0 | K17: {=IFERROR( _xlfn.XLOOKUP(1, (MARKET_DATA!$A:$A=$A17-1)* (MARKET_DATA!$B:$B=$B17)* (MARKET_DATA!$C:$C=$C17)* (MARKET_DATA!$D:$D=$D17), MARKET_DATA!$K:$K), 0)} -> 0 | L17: {=IFERROR( _xlfn.XLOOKUP(1, (MARKET_DATA!$A:$A=$A17-1)* (MARKET_DATA!$B:$B=$B17)* (MARKET_DATA!$C:$C=$C17)* (MARKET_DATA!$D:$D=$D17), MARKET_DATA!$H:$H), 0)} -> 0 | M17: =+$B$1*E17 + $B$2*F17 + $B$3*G17 + $B$4*H17 -> 61.643122 | N17: =+$B$1*I17 + $B$2*J17 + $B$3*K17 + $B$4*L17 -> 0 | O17: =M17 / (M17 + $B$6*N17)*100 -> 100 | P17: {=IFERROR( _xlfn.XLOOKUP(1, (MARKET_DATA!$A:$A=$A17-1)* (MARKET_DATA!$B:$B=$B17)* (MARKET_DATA!$C:$C=$C17)* (MARKET_DATA!$D:$D=$D17), MARKET_DATA!$G:$G), 0)} -> 0 | Q17: =+$B$5*P17 + (1-$B$5)*O17 -> 44.4
A18: 7 | B18: C1 | C18: West | D18: Low | E18: {=+_xlfn.XLOOKUP(1, (AWARENESS!A:A=A18)* (AWARENESS!B:B=B18)* (AWARENESS!C:C=C18)* (AWARENESS!D:D=D18), AWARENESS!Q:Q)} -> 20.35465 | F18: {=+_xlfn.XLOOKUP(1, (ATTRACTIVENESS!A:A=A18)* (ATTRACTIVENESS!B:B=B18)* (ATTRACTIVENESS!C:C=C18)* (ATTRACTIVENESS!D:D=D18), ATTRACTIVENESS!R:R)} -> 23 | G18: {=+_xlfn.XLOOKUP(1, (AVAILABILITY!A:A=A18)* (AVAILABILITY!B:B=B18)* (AVAILABILITY!C:C=C18), AVAILABILITY!J:J)} -> 58.049376 | H18: {=+_xlfn.XLOOKUP(1, (PRICE_P!A:A=A18)* (PRICE_P!B:B=B18)* (PRICE_P!C:C=C18)* (PRICE_P!D:D=D18), PRICE_P!J:J)} -> 100 | I18: {=IFERROR( _xlfn.XLOOKUP(1, (MARKET_DATA!$A:$A=$A18-1)* (MARKET_DATA!$B:$B=$B18)* (MARKET_DATA!$C:$C=$C18)* (MARKET_DATA!$D:$D=$D18), MARKET_DATA!$I:$I), 0)} -> 0 | J18: {=IFERROR( _xlfn.XLOOKUP(1, (MARKET_DATA!$A:$A=$A18-1)* (MARKET_DATA!$B:$B=$B18)* (MARKET_DATA!$C:$C=$C18)* (MARKET_DATA!$D:$D=$D18), MARKET_DATA!$J:$J), 0)} -> 0 | K18: {=IFERROR( _xlfn.XLOOKUP(1, (MARKET_DATA!$A:$A=$A18-1)* (MARKET_DATA!$B:$B=$B18)* (MARKET_DATA!$C:$C=$C18)* (MARKET_DATA!$D:$D=$D18), MARKET_DATA!$K:$K), 0)} -> 0 | L18: {=IFERROR( _xlfn.XLOOKUP(1, (MARKET_DATA!$A:$A=$A18-1)* (MARKET_DATA!$B:$B=$B18)* (MARKET_DATA!$C:$C=$C18)* (MARKET_DATA!$D:$D=$D18), MARKET_DATA!$H:$H), 0)} -> 0 | M18: =+$B$1*E18 + $B$2*F18 + $B$3*G18 + $B$4*H18 -> 54.755047 | N18: =+$B$1*I18 + $B$2*J18 + $B$3*K18 + $B$4*L18 -> 0 | O18: =M18 / (M18 + $B$6*N18)*100 -> 100 | P18: {=IFERROR( _xlfn.XLOOKUP(1, (MARKET_DATA!$A:$A=$A18-1)* (MARKET_DATA!$B:$B=$B18)* (MARKET_DATA!$C:$C=$C18)* (MARKET_DATA!$D:$D=$D18), MARKET_DATA!$G:$G), 0)} -> 0 | Q18: =+$B$5*P18 + (1-$B$5)*O18 -> 44.4
A19: 7 | B19: C1 | C19: North | D19: Low | E19: {=+_xlfn.XLOOKUP(1, (AWARENESS!A:A=A19)* (AWARENESS!B:B=B19)* (AWARENESS!C:C=C19)* (AWARENESS!D:D=D19), AWARENESS!Q:Q)} -> 16.654909 | F19: {=+_xlfn.XLOOKUP(1, (ATTRACTIVENESS!A:A=A19)* (ATTRACTIVENESS!B:B=B19)* (ATTRACTIVENESS!C:C=C19)* (ATTRACTIVENESS!D:D=D19), ATTRACTIVENESS!R:R)} -> 23 | G19: {=+_xlfn.XLOOKUP(1, (AVAILABILITY!A:A=A19)* (AVAILABILITY!B:B=B19)* (AVAILABILITY!C:C=C19), AVAILABILITY!J:J)} -> 60.240684 | H19: {=+_xlfn.XLOOKUP(1, (PRICE_P!A:A=A19)* (PRICE_P!B:B=B19)* (PRICE_P!C:C=C19)* (PRICE_P!D:D=D19), PRICE_P!J:J)} -> 100 | I19: {=IFERROR( _xlfn.XLOOKUP(1, (MARKET_DATA!$A:$A=$A19-1)* (MARKET_DATA!$B:$B=$B19)* (MARKET_DATA!$C:$C=$C19)* (MARKET_DATA!$D:$D=$D19), MARKET_DATA!$I:$I), 0)} -> 0 | J19: {=IFERROR( _xlfn.XLOOKUP(1, (MARKET_DATA!$A:$A=$A19-1)* (MARKET_DATA!$B:$B=$B19)* (MARKET_DATA!$C:$C=$C19)* (MARKET_DATA!$D:$D=$D19), MARKET_DATA!$J:$J), 0)} -> 0 | K19: {=IFERROR( _xlfn.XLOOKUP(1, (MARKET_DATA!$A:$A=$A19-1)* (MARKET_DATA!$B:$B=$B19)* (MARKET_DATA!$C:$C=$C19)* (MARKET_DATA!$D:$D=$D19), MARKET_DATA!$K:$K), 0)} -> 0 | L19: {=IFERROR( _xlfn.XLOOKUP(1, (MARKET_DATA!$A:$A=$A19-1)* (MARKET_DATA!$B:$B=$B19)* (MARKET_DATA!$C:$C=$C19)* (MARKET_DATA!$D:$D=$D19), MARKET_DATA!$H:$H), 0)} -> 0 | M19: =+$B$1*E19 + $B$2*F19 + $B$3*G19 + $B$4*H19 -> 54.362854 | N19: =+$B$1*I19 + $B$2*J19 + $B$3*K19 + $B$4*L19 -> 0 | O19: =M19 / (M19 + $B$6*N19)*100 -> 100 | P19: {=IFERROR( _xlfn.XLOOKUP(1, (MARKET_DATA!$A:$A=$A19-1)* (MARKET_DATA!$B:$B=$B19)* (MARKET_DATA!$C:$C=$C19)* (MARKET_DATA!$D:$D=$D19), MARKET_DATA!$G:$G), 0)} -> 0 | Q19: =+$B$5*P19 + (1-$B$5)*O19 -> 44.4
A20: 7 | B20: C1 | C20: East | D20: Low | E20: {=+_xlfn.XLOOKUP(1, (AWARENESS!A:A=A20)* (AWARENESS!B:B=B20)* (AWARENESS!C:C=C20)* (AWARENESS!D:D=D20), AWARENESS!Q:Q)} -> 10.1 | F20: {=+_xlfn.XLOOKUP(1, (ATTRACTIVENESS!A:A=A20)* (ATTRACTIVENESS!B:B=B20)* (ATTRACTIVENESS!C:C=C20)* (ATTRACTIVENESS!D:D=D20), ATTRACTIVENESS!R:R)} -> 23 | G20: {=+_xlfn.XLOOKUP(1, (AVAILABILITY!A:A=A20)* (AVAILABILITY!B:B=B20)* (AVAILABILITY!C:C=C20), AVAILABILITY!J:J)} -> 42.596596 | H20: {=+_xlfn.XLOOKUP(1, (PRICE_P!A:A=A20)* (PRICE_P!B:B=B20)* (PRICE_P!C:C=C20)* (PRICE_P!D:D=D20), PRICE_P!J:J)} -> 50 | I20: {=IFERROR( _xlfn.XLOOKUP(1, (MARKET_DATA!$A:$A=$A20-1)* (MARKET_DATA!$B:$B=$B20)* (MARKET_DATA!$C:$C=$C20)* (MARKET_DATA!$D:$D=$D20), MARKET_DATA!$I:$I), 0)} -> 0 | J20: {=IFERROR( _xlfn.XLOOKUP(1, (MARKET_DATA!$A:$A=$A20-1)* (MARKET_DATA!$B:$B=$B20)* (MARKET_DATA!$C:$C=$C20)* (MARKET_DATA!$D:$D=$D20), MARKET_DATA!$J:$J), 0)} -> 0 | K20: {=IFERROR( _xlfn.XLOOKUP(1, (MARKET_DATA!$A:$A=$A20-1)* (MARKET_DATA!$B:$B=$B20)* (MARKET_DATA!$C:$C=$C20)* (MARKET_DATA!$D:$D=$D20), MARKET_DATA!$K:$K), 0)} -> 0 | L20: {=IFERROR( _xlfn.XLOOKUP(1, (MARKET_DATA!$A:$A=$A20-1)* (MARKET_DATA!$B:$B=$B20)* (MARKET_DATA!$C:$C=$C20)* (MARKET_DATA!$D:$D=$D20), MARKET_DATA!$H:$H), 0)} -> 0 | M20: =+$B$1*E20 + $B$2*F20 + $B$3*G20 + $B$4*H20 -> 33.071115 | N20: =+$B$1*I20 + $B$2*J20 + $B$3*K20 + $B$4*L20 -> 0 | O20: =M20 / (M20 + $B$6*N20)*100 -> 100 | P20: {=IFERROR( _xlfn.XLOOKUP(1, (MARKET_DATA!$A:$A=$A20-1)* (MARKET_DATA!$B:$B=$B20)* (MARKET_DATA!$C:$C=$C20)* (MARKET_DATA!$D:$D=$D20), MARKET_DATA!$G:$G), 0)} -> 0 | Q20: =+$B$5*P20 + (1-$B$5)*O20 -> 44.4
A21: 7 | B21: C1 | C21: South | D21: Low | E21: {=+_xlfn.XLOOKUP(1, (AWARENESS!A:A=A21)* (AWARENESS!B:B=B21)* (AWARENESS!C:C=C21)* (AWARENESS!D:D=D21), AWARENESS!Q:Q)} -> 10.1 | F21: {=+_xlfn.XLOOKUP(1, (ATTRACTIVENESS!A:A=A21)* (ATTRACTIVENESS!B:B=B21)* (ATTRACTIVENESS!C:C=C21)* (ATTRACTIVENESS!D:D=D21), ATTRACTIVENESS!R:R)} -> 23 | G21: {=+_xlfn.XLOOKUP(1, (AVAILABILITY!A:A=A21)* (AVAILABILITY!B:B=B21)* (AVAILABILITY!C:C=C21), AVAILABILITY!J:J)} -> 42.596596 | H21: {=+_xlfn.XLOOKUP(1, (PRICE_P!A:A=A21)* (PRICE_P!B:B=B21)* (PRICE_P!C:C=C21)* (PRICE_P!D:D=D21), PRICE_P!J:J)} -> 50 | I21: {=IFERROR( _xlfn.XLOOKUP(1, (MARKET_DATA!$A:$A=$A21-1)* (MARKET_DATA!$B:$B=$B21)* (MARKET_DATA!$C:$C=$C21)* (MARKET_DATA!$D:$D=$D21), MARKET_DATA!$I:$I), 0)} -> 0 | J21: {=IFERROR( _xlfn.XLOOKUP(1, (MARKET_DATA!$A:$A=$A21-1)* (MARKET_DATA!$B:$B=$B21)* (MARKET_DATA!$C:$C=$C21)* (MARKET_DATA!$D:$D=$D21), MARKET_DATA!$J:$J), 0)} -> 0 | K21: {=IFERROR( _xlfn.XLOOKUP(1, (MARKET_DATA!$A:$A=$A21-1)* (MARKET_DATA!$B:$B=$B21)* (MARKET_DATA!$C:$C=$C21)* (MARKET_DATA!$D:$D=$D21), MARKET_DATA!$K:$K), 0)} -> 0 | L21: {=IFERROR( _xlfn.XLOOKUP(1, (MARKET_DATA!$A:$A=$A21-1)* (MARKET_DATA!$B:$B=$B21)* (MARKET_DATA!$C:$C=$C21)* (MARKET_DATA!$D:$D=$D21), MARKET_DATA!$H:$H), 0)} -> 0 | M21: =+$B$1*E21 + $B$2*F21 + $B$3*G21 + $B$4*H21 -> 33.071115 | N21: =+$B$1*I21 + $B$2*J21 + $B$3*K21 + $B$4*L21 -> 0 | O21: =M21 / (M21 + $B$6*N21)*100 -> 100 | P21: {=IFERROR( _xlfn.XLOOKUP(1, (MARKET_DATA!$A:$A=$A21-1)* (MARKET_DATA!$B:$B=$B21)* (MARKET_DATA!$C:$C=$C21)* (MARKET_DATA!$D:$D=$D21), MARKET_DATA!$G:$G), 0)} -> 0 | Q21: =+$B$5*P21 + (1-$B$5)*O21 -> 44.4
