Workbook

Sheet LIQUIDITY_MONITOR
A1: LIQUIDITY MONITOR - Cash Flow Engine
A3: SECTION A: INITIALIZATION (Initial Cash Flow Bridge)
A5: Cash at End of Last Period | B5: 0
A6: Less: Tax Payments | B6: 0
A7: Less: Dividend Payments | B7: 0
A8: Less: Asset Purchases | B8: 0
A9: STARTING CASH FOR FN1 (HARD) | B9: =B5-B6-B7-B8 | C9: ← From initial_cash_flow.xlsx
A12: SECTION B: OPERATIONAL CASH FLOW
A14: Item | B14: FN1 | C14: FN2 | D14: FN3 | E14: FN4 | F14: FN5 | G14: FN6 | H14: FN7 | I14: FN8
A15: Opening Cash | B15: =$B$9 | C15: =B$33 | D15: =C$33 | E15: =D$33 | F15: =E$33 | G15: =F$33 | H15: =G$33 | I15: =H$33
A16: Sales Receipts (Est.) | B16: 100000 | C16: 100000 | D16: 100000 | E16: 100000 | F16: 100000 | G16: 100000 | H16: 100000 | I16: 100000
A17: Procurement Spend (Est.) | B17: 0 | C17: 0 | D17: 0 | E17: 0 | F17: 0 | G17: 0 | H17: 0 | I17: 0
A18: Fixed Overhead (S&A) | B18: 0 | C18: 0 | D18: 0 | E18: 0 | F18: 0 | G18: 0 | H18: 0 | I18: 0
A19: Receivables (HARD) | B19: 0 | C19: 0 | D19: 0 | E19: 0 | F19: 0 | G19: 0 | H19: 0 | I19: 0
A20: Payables (HARD) | B20: 0 | C20: 0 | D20: 0 | E20: 0 | F20: 0 | G20: 0 | H20: 0 | I20: 0
A24: SECTION C: FINANCING DECISIONS | C24: DEBT CAPACITY (Short Term) | D24: Limit: $500,000
A25: Change in Credit Line (+/-) | B25: 0 | C25: 0 | D25: 0 | E25: 0 | F25: 0 | G25: 0 | H25: 0 | I25: 0
A26: Proj. ST Debt Balance | B26: =0+B25 | C26: =B26+C25 | D26: =C26+D25 | E26: =D26+E25 | F26: =E26+F25 | G26: =F26+G25 | H26: =G26+H25 | I26: =H26+I25
A27: Change in Investments (+/-) | B27: 0 | C27: 0 | D27: 0 | E27: 0 | F27: 0 | G27: 0 | H27: 0 | I27: 0
A28: New Mortgage Inflow | B28: 0 | C28: 0 | D28: 0 | E28: 0 | F28: 0 | G28: 0 | H28: 0 | I28: 0
A29: Dividends Paid | B29: 0 | C29: 0 | D29: 0 | E29: 0 | F29: 0 | G29: 0 | H29: 0 | I29: 0
A31: SECTION D: CASH BALANCE
A32: Net Cash Flow | B32: =B16+B19+B25+B28-B17-B18-B20-B27-B29 | C32: =C16+C19+C25+C28-C17-C18-C20-C27-C29 | D32: =D16+D19+D25+D28-D17-D18-D20-D27-D29 | E32: =E16+E19+E25+E28-E17-E18-E20-E27-E29 | F32: =F16+F19+F25+F28-F17-F18-F20-F27-F29 | G32: =G16+G19+G25+G28-G17-G18-G20-G27-G29 | H32: =H16+H19+H25+H28-H17-H18-H20-H27-H29 | I32: =I16+I19+I25+I28-I17-I18-I20-I27-I29
A33: ENDING CASH BALANCE | B33: =B15+B32 | C33: =C15+C32 | D33: =D15+D32 | E33: =E15+E32 | F33: =F15+F32 | G33: =G15+G32 | H33: =H15+H32 | I33: =I15+I32
A34: Solvency Check | B34: =IF(B33<0,"INSOLVENT!",IF(B33>200000,"Excess Cash","OK")) | C34: =IF(C33<0,"INSOLVENT!",IF(C33>200000,"Excess Cash","OK")) | D34: =IF(D33<0,"INSOLVENT!",IF(D33>200000,"Excess Cash","OK")) | E34: =IF(E33<0,"INSOLVENT!",IF(E33>200000,"Excess Cash","OK")) | F34: =IF(F33<0,"INSOLVENT!",IF(F33>200000,"Excess Cash","OK")) | G34: =IF(G33<0,"INSOLVENT!",IF(G33>200000,"Excess Cash","OK")) | H34: =IF(H33<0,"INSOLVENT!",IF(H33>200000,"Excess Cash","OK")) | I34: =IF(I33<0,"INSOLVENT!",IF(I33>200000,"Excess Cash","OK"))

Sheet PROFIT_CONTROL
A1: PROFIT CONTROL - Income Statement Forecast vs Actuals
A3: HISTORICAL MARGINS (From results_and_balance_statements)
A5: Historical Gross Margin % | B5: 0
A6: Historical Net Margin % | B6: 0
A9: INCOME STATEMENT COMPARISON
A10: Line Item | B10: Last Round Actuals | C10: This Round Projected | D10: Variance %
A11: Net Sales / Revenue | B11: 0 | C11: 0 | D11: =IF(B11>0,(C11-B11)/B11,0)
A12: Cost of Goods Sold | B12: 0 | C12: =C11*(1-$B$5) | D12: =IF(B12>0,(C12-B12)/B12,0)
A13: Gross Margin | B13: 0 | C13: =C11-C12 | D13: =IF(B13>0,(C13-B13)/B13,0)
A14: S&A Expenses | B14: 0 | C14: 0 | D14: =IF(B14>0,(C14-B14)/B14,0)
A15: Depreciation (HARD) | B15: 0 | C15: 0 | D15: =IF(B15>0,(C15-B15)/B15,0) | E15: ← Auto-calc from machine_spaces.xlsx
A16: Interest Expense | B16: 0 | C16: 0
A17: EST. NET INCOME | B17: 0 | C17: =C13-C14-C15-C16 | D17: =IF(B17>0,(C17-B17)/B17,0)
A19: ACCURACY CHECK
A20: Projected Net Margin | B20: =IF(C11>0,C17/C11,0)
A21: Profit Realism Flag | B21: =IF(B20>$B$6+0.05,"WARNING: Unrealistic profit jump!","Projection OK")

Sheet BALANCE_SHEET_HEALTH
A1: BALANCE SHEET HEALTH - Solvency & Debt Control
A3: CURRENT POSITION (From results_and_balance_statements)
A5: Total Assets | B5: 0
A6: Total Liabilities | B6: 0
A7: Total Equity | B7: 0
A8: Retained Earnings | B8: 0
A11: DEBT ANALYSIS
H12: Metric | I12: Ratio | J12: Limit
A13: Current Debt Ratio | B13: =B6/B5 | H13: Current | I13: =B13 | J13: 0.6
H14: Post-Decision | I14: =B19 | J14: 0.6
A15: Projected New Credit Lines | B15: 0
A16: Projected New Mortgages | B16: 0
A17: Total New Debt | B17: =B15+B16
A19: Est. Post-Decision Debt Ratio | B19: =(B6+B17)/B5
A21: WARNING FLAGS
A22: Debt Level Check | B22: =IF(B19>0.6,"CRITICAL: Debt too high. Credit Rating Risk.","Health OK")
B23: =IF(B8<0,"CRITICAL: Equity Erosion. Retained earnings negative.","Equity OK")

Sheet DEBT_MANAGER
A1: DEBT MANAGER - Mortgage Calculator
A3: MORTGAGE BLOCK
A5: Loan # | B5: Amount | C5: Interest Rate | D5: Payment Period 1 | E5: Payment Period 2 | F5: Total Payments
A6: Loan 1 | B6: 0 | C6: 0 | D6: 0 | E6: 0 | F6: =D6+E6
A7: Loan 2 | B7: 0 | C7: 0 | D7: 0 | E7: 0 | F7: =D7+E7
A8: Loan 3 | B8: 0 | C8: 0 | D8: 0 | E8: 0 | F8: =D8+E8
A10: TOTAL | B10: =SUM(B6:B8) | F10: =SUM(F6:F8)
A13: DIVIDEND CONTROL
A14: Max Dividend Capacity (HARD) | B14: 0 | C14: ← Retained Earnings from balance sheet
A15: User Dividend Input | B15: 0
A16: Dividend Status | B16: =IF(B15>B14,"❌ ILLEGAL: Exceeds Retained Earnings","✓ LEGAL")

Sheet UPLOAD_READY_FINANCE
A1: FINANCE DECISIONS - ExSim Upload Format
A2: Copy these values to ExSim Finance upload
A4: Credit Lines
B5: FN1 | C5: FN2 | D5: FN3 | E5: FN4 | F5: FN5 | G5: FN6 | H5: FN7 | I5: FN8
A6: Amount | B6: =LIQUIDITY_MONITOR!B25 | C6: =LIQUIDITY_MONITOR!C25 | D6: =LIQUIDITY_MONITOR!D25 | E6: =LIQUIDITY_MONITOR!E25 | F6: =LIQUIDITY_MONITOR!F25 | G6: =LIQUIDITY_MONITOR!G25 | H6: =LIQUIDITY_MONITOR!H25 | I6: =LIQUIDITY_MONITOR!I25
A9: Investments
B10: FN1 | C10: FN2 | D10: FN3 | E10: FN4 | F10: FN5 | G10: FN6 | H10: FN7 | I10: FN8
A11: Amount | B11: =LIQUIDITY_MONITOR!B27 | C11: =LIQUIDITY_MONITOR!C27 | D11: =LIQUIDITY_MONITOR!D27 | E11: =LIQUIDITY_MONITOR!E27 | F11: =LIQUIDITY_MONITOR!F27 | G11: =LIQUIDITY_MONITOR!G27 | H11: =LIQUIDITY_MONITOR!H27 | I11: =LIQUIDITY_MONITOR!I27
A14: Mortgages
A15: Loan | B15: Amount | C15: Payment 1 | D15: Payment 2
A16: Loan 1 | B16: =DEBT_MANAGER!B6 | C16: =DEBT_MANAGER!D6 | D16: =DEBT_MANAGER!E6
A17: Loan 2 | B17: =DEBT_MANAGER!B7 | C17: =DEBT_MANAGER!D7 | D17: =DEBT_MANAGER!E7
A18: Loan 3 | B18: =DEBT_MANAGER!B8 | C18: =DEBT_MANAGER!D8 | D18: =DEBT_MANAGER!E8
A21: Dividends
B22: =LIQUIDITY_MONITOR!B29 | C22: =LIQUIDITY_MONITOR!C29 | D22: =LIQUIDITY_MONITOR!D29 | E22: =LIQUIDITY_MONITOR!E29 | F22: =LIQUIDITY_MONITOR!F29 | G22: =LIQUIDITY_MONITOR!G29 | H22: =LIQUIDITY_MONITOR!H29 | I22: =LIQUIDITY_MONITOR!I29

Sheet CROSS_REFERENCE
A1: CROSS-REFERENCE SUMMARY - Upstream Dashboard KPIs
A2: Key metrics from other dashboards affecting cash flow. Data from shared_outputs.json.
A4: CMO (Revenue & Marketing)
A5: Projected Revenue | B5: 0
A6: Marketing Spend | B6: 0
A7: Innovation Costs | B7: 0
A9: PRODUCTION (Output)
A10: Total Production | B10: 0
A11: Avg Unit Cost | B11: 0
A12: Utilization | B12: 0
A14: COST DRIVERS (Variable)
A15: Labor (CPO) | B15: 0
A16: Materials (Purchasing) | B16: 0
A17: Logistics (CLO) | B17: 0
A18: TOTAL VARIABLE EST. | B18: 0
A20: ESG (Sustainability)
A21: CO2 Emissions | B21: 0
A22: Tax Liability | B22: 0
