Workbook

Sheet IMPACT_CONFIG
A1: IMPACT CONFIGURATION - Initiative Specifications
A2: Define the unit costs and CO2 reduction rates from Case Guide.
A4: CO2 TAX RATE ($/Ton) | B4: 0 | C4: <-- Get from Case Guide!
A6: INITIATIVE SPECIFICATIONS
A7: Initiative | B7: Unit Cost ($) | C7: CO2 Reduction (Tons/Unit) | D7: Unit Type
A8: Solar PV Panels | B8: 0 | C8: 0 | D8: panels
A9: Trees Planted | B9: 0 | C9: 0 | D9: trees
A10: Green Electricity | B10: 0 | C10: 0 | D10: % of consumption
A11: CO2 Credits | B11: 0 | C11: 0 | D11: credits
A14: NOTES:
A15: - Solar: CAPEX investment, long-term savings
A16: - Trees: Low cost, slow reduction, good for PR
A17: - Green Electricity: Operating cost, immediate impact
A18: - CO2 Credits: Quick fix, no long-term benefit

Sheet STRATEGY_SELECTOR
A1: STRATEGY SELECTOR - CO2 Abatement Calculator
A2: Compare ROI of green initiatives vs. paying CO2 taxes.
A4: SECTION A: CURRENT BASELINE
A6: Current CO2 Emissions (Tons/Year) | B6: 0
A7: Current CO2 Tax Bill ($) | B7: =B6*IMPACT_CONFIG!$B$4
A8: Energy Consumption (kWh/Year) | B8: 0
A10: SECTION B: INVESTMENT SIMULATOR
A11: Enter quantities in yellow cells to see impact.
A12: Initiative | B12: Quantity | C12: Investment/Cost | D12: CO2 Reduced (Tons) | E12: Tax Savings ($) | F12: Net Annual Benefit | G12: Payback (Years) | H12: Cost per Ton
A13: Solar PV Panels | B13: 0 | C13: =B13*IMPACT_CONFIG!B8 | D13: =B13*IMPACT_CONFIG!C8 | E13: =D13*IMPACT_CONFIG!$B$4 | F13: =E13 | G13: =IF(E13>0,C13/E13,"N/A") | H13: =IF(D13>0,C13/D13,0) | I13: =IMPACT_CONFIG!$B$4
A14: Trees Planted | B14: 0 | C14: =B14*IMPACT_CONFIG!B9 | D14: =B14*IMPACT_CONFIG!C9 | E14: =D14*IMPACT_CONFIG!$B$4 | F14: =E14 | G14: =IF(E14>0,C14/E14,"N/A") | H14: =IF(D14>0,C14/D14,0) | I14: =IMPACT_CONFIG!$B$4
A15: Green Electricity | B15: 0 | C15: =$B$8*B15*IMPACT_CONFIG!B10 | D15: =$B$8*B15*IMPACT_CONFIG!C10 | E15: =D15*IMPACT_CONFIG!$B$4 | F15: =E15-C15 | G15: N/A (OpEx) | H15: =IF(D15>0,C15/D15,0) | I15: =IMPACT_CONFIG!$B$4
A16: CO2 Credits | B16: 0 | C16: =B16*IMPACT_CONFIG!B11 | D16: =B16*IMPACT_CONFIG!C11 | E16: =D16*IMPACT_CONFIG!$B$4 | F16: =E16-C16 | G16: N/A (OpEx) | H16: =IF(D16>0,C16/D16,0) | I16: =IMPACT_CONFIG!$B$4
A18: SECTION C: THE VERDICT
A20: Total CO2 Reduced | B20: =SUM(D13:D16) | C20: tons/year
A21: Total Investment Required | B21: =SUM(C13:C16)
A22: New Tax Bill | B22: =MAX(0,(B6-B20)*IMPACT_CONFIG!B4)
A23: Annual Savings | B23: =B7-B22
A25: SECTION D: STRATEGY ALIGNMENT
A26: Target | B26: Goal | C26: Current | D26: Status
A27: Carbon Neutral Year | B27: 2030 | C27: TBD | D27: =IF(C27="TBD", "PENDING", IF(C27<=B27, "ON TRACK", "BEHIND"))
A28: Product Recyclability % | B28: 1 | C28: 0 | D28: =IF(C28>=B28, "COMPLIANT", "GAP: "&TEXT(B28-C28,"0%"))
A29: Fair Wage (vs Market) | B29: 1.1 | C29: 1 | D29: =IF(C29>=B29, "COMPLIANT", "RAISE WAGES")

Sheet UPLOAD_READY_ESG
A1: UPLOAD READY DATA - DO NOT EDIT
A5: Initiative | B5: Quantity | C5: Investment | D5: CO2 Reduction | E5: Tax Savings
A6: Solar PV Panels | B6: =STRATEGY_SELECTOR!B13 | C6: =STRATEGY_SELECTOR!C13 | D6: =STRATEGY_SELECTOR!D13 | E6: =STRATEGY_SELECTOR!E13
A7: Trees Planted | B7: =STRATEGY_SELECTOR!B14 | C7: =STRATEGY_SELECTOR!C14 | D7: =STRATEGY_SELECTOR!D14 | E7: =STRATEGY_SELECTOR!E14
A8: Green Electricity | B8: =STRATEGY_SELECTOR!B15 | C8: =STRATEGY_SELECTOR!C15 | D8: =STRATEGY_SELECTOR!D15 | E8: =STRATEGY_SELECTOR!E15
A9: CO2 Credits | B9: =STRATEGY_SELECTOR!B16 | C9: =STRATEGY_SELECTOR!C16 | D9: =STRATEGY_SELECTOR!D16 | E9: =STRATEGY_SELECTOR!E16

Sheet CROSS_REFERENCE
A1: CROSS-REFERENCE SUMMARY - Upstream Support
A2: Key metrics from Production and Logistics.
A4: Production (Output)
A5: Total Production | B5: N/A
A6: Avg Utilization | B6: N/A
A9: Logistics (Transport)
A10: Logistics Costs | B10: $0
A11: Shipping Volume | B11: See CLO Dashboard
