Workbook

Sheet SEGMENT_PULSE
A1: SEGMENT PULSE - Market Allocation Drivers | H1: COMPETITIVE POSITIONING
A3: HIGH SEGMENT ANALYSIS | H3: Entity | I3: Price | J3: Attractiveness
A4: Zone | B4: My Market Share | C4: Awareness Gap | D4: Price Gap | E4: Attractiveness | F4: Allocation Flag | H4: My Product | I4: 50.286 | J4: 14.96
A5: Center | B5: 31.7 | C5: -21.133333 | D5: 0.11140592 | E5: 30.21 | F5: CRITICAL: Boost TV for Allocation | H5: Competitors | I5: 50.622 | J5: 0
A6: West | B6: 21.8 | C6: -14.023333 | D6: -0.088167341 | E6: 19.24 | F6: CRITICAL: Boost TV for Allocation
A7: North | B7: 26 | C7: 2.0433333 | D7: -0.080115113 | E7: 25.35 | F7: OK
A8: East | B8: 0 | C8: 0 | D8: 0 | E8: 0 | F8: CRITICAL: Boost TV for Allocation
A9: South | B9: 0 | C9: 0 | D9: 0 | E9: 0 | F9: CRITICAL: Boost TV for Allocation
A12: LOW SEGMENT ANALYSIS
A13: Zone | B13: My Market Share | C13: Awareness Gap | D13: Price Gap | E13: Attractiveness | F13: Allocation Flag
A14: Center | B14: 33.7 | C14: -7.6066667 | D14: 0.11140592 | E14: 30.21 | F14: RISK: Losing Volume to Price
A15: West | B15: 18.8 | C15: -0.50333333 | D15: -0.088167341 | E15: 19.24 | F15: OK
A16: North | B16: 20.7 | C16: 2.53 | D16: -0.080115113 | E16: 25.35 | F16: OK
A17: East | B17: 0 | C17: 0 | D17: 0 | E17: 0 | F17: OK
A18: South | B18: 0 | C18: 0 | D18: 0 | E18: 0 | F18: OK
H24: HIGH vs LOW SEGMENT GAP
H26: Metric | I26: High Segment | J26: Low Segment
H27: Awareness | I27: 24.584 | J27: 24.584
H28: Price Competitiveness | I28: 98.862469 | J28: 98.862469
H29: Attractiveness | I29: 14.96 | J29: 14.96

Sheet INNOVATION_LAB
A1: INNOVATION LAB - Feature Selection
A2: Note: Innovations increase Attractiveness. Required for High Segment Allocation.
A4: Feature Name | B4: Decision (1=Yes) | C4: Est. Cost ($)
A5: STAINLESS MATERIAL | B5: 0 | C5: 10000
A6: RECYCLABLE MATERIALS | B6: 0 | C6: 10000
A7: ENERGY EFFICIENCY | B7: 0 | C7: 10000
A8: LIGHTER AND MORE COMPACT | B8: 0 | C8: 10000
A9: IMPACT RESISTANCE | B9: 0 | C9: 10000
A10: NOISE REDUCTION | B10: 0 | C10: 10000
A11: IMPROVED BATTERY CAPACITY | B11: 0 | C11: 10000
A12: SELF-CLEANING | B12: 0 | C12: 10000
A13: SPEED SETTINGS | B13: 0 | C13: 10000
A14: DIGITAL CONTROLS | B14: 0 | C14: 10000
A15: VOICE ASSISTANCE INTEGRATION | B15: 0 | C15: 10000
A16: AUTOMATION AND PROGRAMMABILITY | B16: 0 | C16: 10000
... A18: MAPPING TECHNOLOGY | B18: 0 | C18: 10000
A20: TOTAL INNOVATION COST | C20: =SUMPRODUCT(B5:B18,C5:C18)

Sheet STRATEGY_COCKPIT
A1: HOW TO USE: Adjust Yellow cells. Check Profit Projection. Go to UPLOAD_READY tabs to copy decisions.
A3: SECTION A: GLOBAL ALLOCATIONS
A5: TV Budget ($) | B5: 0 | C5: Primary Driver: High Segment Awareness
A6: Brand Focus (0-100) | B6: 0 | C6: 0=Awareness focus, 100=Attributes focus
A9: SECTION B: ZONAL ALLOCATIONS
A11: Zone | B11: Last Sales | C11: Stockout? | D11: Target Demand | E11: Radio Budget | F11: Salespeople | G11: Price | H11: Payment | I11: Est. Revenue | J11: Mkt Cost | K11: Contribution
A12: Center | B12: 6770 | C12: TRUE DEMAND HIGHER | D12: 7447 | E12: 0 | F12: 0 | G12: 0 | I12: =D12*G12 | J12: =($B$5/5)+E12+(F12*0)+(INNOVATION_LAB!C20/5) | K12: =I12-J12-(D12*0)
A13: West | B13: 5864 | C13: TRUE DEMAND HIGHER | D13: 6450 | E13: 0 | F13: 0 | G13: 0 | I13: =D13*G13 | J13: =($B$5/5)+E13+(F13*0)+(INNOVATION_LAB!C20/5) | K13: =I13-J13-(D13*0)
A14: North | B14: 5500 | C14: TRUE DEMAND HIGHER | D14: 6050 | E14: 0 | F14: 0 | G14: 0 | I14: =D14*G14 | J14: =($B$5/5)+E14+(F14*0)+(INNOVATION_LAB!C20/5) | K14: =I14-J14-(D14*0)
A15: East | B15: 0 | C15: TRUE DEMAND HIGHER | D15: 0 | E15: 0 | F15: 0 | G15: 0 | I15: =D15*G15 | J15: =($B$5/5)+E15+(F15*0)+(INNOVATION_LAB!C20/5) | K15: =I15-J15-(D15*0)
A16: South | B16: 0 | C16: TRUE DEMAND HIGHER | D16: 0 | E16: 0 | F16: 0 | G16: 0 | I16: =D16*G16 | J16: =($B$5/5)+E16+(F16*0)+(INNOVATION_LAB!C20/5) | K16: =I16-J16-(D16*0)
A17: TOTAL | D17: =SUM(D12:D16) | I17: =SUM(I12:I16) | J17: =SUM(J12:J16) | K17: =SUM(K12:K16)

Sheet UPLOAD_READY_MARKETING
A1: MARKETING DECISIONS - ExSim Upload Format
A2: Copy these values to ExSim Marketing upload
A4: Marketing Campaigns | G4: Demand | J4: Pricing Strategy | N4: Channels
A5: Brand | B5: Zone | C5: Channel | D5: Amount | E5: Brand Focus | G5: Zone | H5: Demand | J5: Zone | K5: Brand | L5: Price | N5: Zone | O5: Payment | P5: Salespeople
A6: A | B6: All | C6: TV | D6: =STRATEGY_COCKPIT!B5 | E6: =STRATEGY_COCKPIT!B6 | G6: Center | H6: =STRATEGY_COCKPIT!D12 | J6: Center | K6: A | L6: =STRATEGY_COCKPIT!G12 | N6: Center | O6: =STRATEGY_COCKPIT!H12 | P6: =STRATEGY_COCKPIT!F12
A7: A | B7: Center | C7: Radio | D7: =STRATEGY_COCKPIT!E12 | E7: =STRATEGY_COCKPIT!B6 | G7: West | H7: =STRATEGY_COCKPIT!D13 | J7: West | K7: A | L7: =STRATEGY_COCKPIT!G13 | N7: West | O7: =STRATEGY_COCKPIT!H13 | P7: =STRATEGY_COCKPIT!F13
A8: A | B8: West | C8: Radio | D8: =STRATEGY_COCKPIT!E13 | E8: =STRATEGY_COCKPIT!B6 | G8: North | H8: =STRATEGY_COCKPIT!D14 | J8: North | K8: A | L8: =STRATEGY_COCKPIT!G14 | N8: North | O8: =STRATEGY_COCKPIT!H14 | P8: =STRATEGY_COCKPIT!F14
A9: A | B9: North | C9: Radio | D9: =STRATEGY_COCKPIT!E14 | E9: =STRATEGY_COCKPIT!B6 | G9: East | H9: =STRATEGY_COCKPIT!D15 | J9: East | K9: A | L9: =STRATEGY_COCKPIT!G15 | N9: East | O9: =STRATEGY_COCKPIT!H15 | P9: =STRATEGY_COCKPIT!F15
A10: A | B10: East | C10: Radio | D10: =STRATEGY_COCKPIT!E15 | E10: =STRATEGY_COCKPIT!B6 | G10: South | H10: =STRATEGY_COCKPIT!D16 | J10: South | K10: A | L10: =STRATEGY_COCKPIT!G16 | N10: South | O10: =STRATEGY_COCKPIT!H16 | P10: =STRATEGY_COCKPIT!F16
A11: A | B11: South | C11: Radio | D11: =STRATEGY_COCKPIT!E16 | E11: =STRATEGY_COCKPIT!B6

Sheet UPLOAD_READY_INNOVATION
A1: INNOVATION DECISIONS - ExSim Upload Format
A2: Copy these values to ExSim Innovation upload
A4: Brand | B4: Improvement | C4: Value
A5: A | B5: STAINLESS MATERIAL | C5: =INNOVATION_LAB!B5
A6: A | B6: RECYCLABLE MATERIALS | C6: =INNOVATION_LAB!B6
A7: A | B7: ENERGY EFFICIENCY | C7: =INNOVATION_LAB!B7
A8: A | B8: LIGHTER AND MORE COMPACT | C8: =INNOVATION_LAB!B8
A9: A | B9: IMPACT RESISTANCE | C9: =INNOVATION_LAB!B9
A10: A | B10: NOISE REDUCTION | C10: =INNOVATION_LAB!B10
A11: A | B11: IMPROVED BATTERY CAPACITY | C11: =INNOVATION_LAB!B11
A12: A | B12: SELF-CLEANING | C12: =INNOVATION_LAB!B12
A13: A | B13: SPEED SETTINGS | C13: =INNOVATION_LAB!B13
A14: A | B14: DIGITAL CONTROLS | C14: =INNOVATION_LAB!B14
A15: A | B15: VOICE ASSISTANCE INTEGRATION | C15: =INNOVATION_LAB!B15
A16: A | B16: AUTOMATION AND PROGRAMMABILITY | C16: =INNOVATION_LAB!B16
... A18: A | B18: MAPPING TECHNOLOGY | C18: =INNOVATION_LAB!B18
