Workbook

Sheet WORKFORCE PLANNING
A1: WORKFORCE PLANNING - Headcount Management
A2: Yellow cells = User inputs. Green = Outputs for Finance.
A4: COST PARAMETERS
A5: Est. Hiring Fee (per worker) | B5: 240 | C5: Benchmark (Sales Hire): $1,100
A6: Est. Severance (per worker) | B6: 2000
A8: HEADCOUNT ANALYSIS BY ZONE
A9: Zone | B9: Current Staff | C9: Required Workers | D9: Est. Turnover % | E9: Projected Loss | F9: Net Staff | G9: Hiring Needed | H9: Firing Needed | I9: Hiring Cost | J9: Firing Cost | K9: Net Change Cost
A10: Center | B10: 219 | C10: 219 | D10: 0 | E10: =B10*D10 | F10: =B10-E10 | G10: =MAX(0,C10-F10) | H10: =MAX(0,F10-C10) | I10: =G10*$B$5 | J10: =H10*$B$6 | K10: =I10+J10
A11: West | B11: 71 | C11: 71 | D11: 0 | E11: =B11*D11 | F11: =B11-E11 | G11: =MAX(0,C11-F11) | H11: =MAX(0,F11-C11) | I11: =G11*$B$5 | J11: =H11*$B$6 | K11: =I11+J11
A12: North | B12: 0 | C12: 0 | D12: 0 | E12: =B12*D12 | F12: =B12-E12 | G12: =MAX(0,C12-F12) | H12: =MAX(0,F12-C12) | I12: =G12*$B$5 | J12: =H12*$B$6 | K12: =I12+J12
A13: East | B13: 0 | C13: 0 | D13: 0 | E13: =B13*D13 | F13: =B13-E13 | G13: =MAX(0,C13-F13) | H13: =MAX(0,F13-C13) | I13: =G13*$B$5 | J13: =H13*$B$6 | K13: =I13+J13
A14: South | B14: 0 | C14: 0 | D14: 0 | E14: =B14*D14 | F14: =B14-E14 | G14: =MAX(0,C14-F14) | H14: =MAX(0,F14-C14) | I14: =G14*$B$5 | J14: =H14*$B$6 | K14: =I14+J14
A15: TOTAL | B15: =SUM(B10:B14) | C15: =SUM(C10:C14) | D15: =SUM(D10:D14) | E15: =SUM(E10:E14) | F15: =SUM(F10:F14) | G15: =SUM(G10:G14) | H15: =SUM(H10:H14) | I15: =SUM(I10:I14) | ... K15: =SUM(K10:K14)
A18: COST OPTIMIZER: HIRE vs OVERTIME
A19: Global Workforce Deficit (Workers) | B19: =MAX(0, C15 - F15)
A20: Strategy A: HIRE NEW STAFF
A21: Total Cost (Upfront + Salary) | B21: =B19*($B$5 + 650)
A22: Strategy B: OVERTIME
A23: Max Overtime Capacity (Workers eq.) | B23: =F15*0.2
A24: Cost (Salary x 1.4) | B24: =MIN(B19, B23) * 650 * 1.4
A25: RECOMMENDATION: | B25: =IF(B19>B23, "MUST HIRE (Capacity Exceeded)", IF(B24<B21, "USE OVERTIME (Cheaper)", "HIRE (Cheaper)"))

Sheet COMPENSATION STRATEGY
A1: COMPENSATION STRATEGY - Salaries & Benefits
A2: CRITICAL: Set Inflation Rate from Case Guide to avoid STRIKES!
A4: SECTION A: GLOBAL PARAMETERS
A5: HIGH ABSENTEEISM DETECTED. RISK OF STRIKE OR LOW CAPACITY. INCREASE HEALTH & SAFETY BUDGET.
A6: Inflation Rate % | B6: 0.03 | C6: <-- CRITICAL: Get from Case Guide!
A7: Target Purchasing Power Increase % | B7: 0
A9: SECTION B: SALARY DECISIONS (Per Zone)
A10: Zone | B10: Previous Salary | C10: Inflation Floor | D10: Proposed New Salary | E10: Strike Risk | F10: Real PPP Change
A11: Center | B11: 650 | C11: =B11*(1+$B$6) | D11: 676 | E11: =IF(OR(D11<C11, D11<650),"STRIKE RISK!","OK") | F11: =IF(B11>0,(D11/B11)-1-$B$6,0)
A12: West | B12: 650 | C12: =B12*(1+$B$6) | D12: 676 | E12: =IF(OR(D12<C12, D12<650),"STRIKE RISK!","OK") | F12: =IF(B12>0,(D12/B12)-1-$B$6,0)
A13: North | B13: 650 | C13: =B13*(1+$B$6) | D13: 676 | E13: =IF(OR(D13<C13, D13<650),"STRIKE RISK!","OK") | F13: =IF(B13>0,(D13/B13)-1-$B$6,0)
A14: East | B14: 650 | C14: =B14*(1+$B$6) | D14: 676 | E14: =IF(OR(D14<C14, D14<650),"STRIKE RISK!","OK") | F14: =IF(B14>0,(D14/B14)-1-$B$6,0)
A15: South | B15: 650 | C15: =B15*(1+$B$6) | D15: 676 | E15: =IF(OR(D15<C15, D15<650),"STRIKE RISK!","OK") | F15: =IF(B15>0,(D15/B15)-1-$B$6,0)
A17: MOTIVATION ALERT:
A18: Low Training Budget increases Defective Products!
A19: High Absenteeism may indicate low morale - consider benefits.
A21: SECTION C: BENEFITS DECISIONS
A22: Benefit Type | B22: Decision Value | C22: Notes
A23: Training Budget (% of Payroll) | B23: 0 | C23: Low = More defects
A24: Health Insurance (% of Payroll) | B24: 0 | C24: Reduces absenteeism
A25: Profit Sharing (% of Net Profit) | B25: 0 | C25: Paid on net profit
A26: Personal Days (per Worker) | B26: 0 | C26: Labor requirement
A27: Union Representatives | B27: 0 | C27: Labor requirement
A28: Reduction in Working Hours (%) | B28: 0 | C28: Reduces capacity
A29: Off-Days for Workers | B29: 0 | C29: Extra days off

Sheet LABOR COST ANALYSIS
A1: LABOR COST ANALYSIS - Total People Expense for Finance
A2: Output for CFO to include in cash flow projections.
A4: INPUT: Estimated Net Profit (for Profit Sharing) | B4: 0
A5: Previous Period Labor Cost | B5: 236412
A7: COST BREAKDOWN
A8: Cost Category | B8: Calculation | C8: Amount
A9: Total Planned Factory Headcount | B9: =WORKFORCE_PLANNING!C15 | C9: =B9
A10: Factory Base Salaries | B10: =B9*AVERAGE(COMPENSATION_STRATEGY!D11:D15)*8 | C10: =B10
A11: Overtime & Bonuses | B11: 0 | C11: =B11
A12: Training & Benefits | B12: =COMPENSATION_STRATEGY!B23*C10 + COMPENSATION_STRATEGY!B24*C10 | C12: =B12
A13: Profit Sharing | B13: =$B$4*COMPENSATION_STRATEGY!B25 | C13: =B13
A14: Hiring & Firing | B14: =WORKFORCE_PLANNING!K15 | C14: =B14
A15: SALESFORCE PAYROLL (Fixed) | B15: 0 | C15: =B15 | D15: Based on 0 salespeople @ $750/person (Admin Report)
A16: TOTAL PEOPLE EXPENSE | C16: =SUM(C10:C14)
A18: Variance vs Previous Period | C18: =C16-B5

Sheet UPLOAD READY PEOPLE
A1: PEOPLE DECISIONS - ExSim Upload Format
A2: Copy these values to ExSim People upload.
A4: Salaries | D4: Benefits & Policies
A5: Zone | B5: Salary | D5: Benefit | E5: Value
A6: Center | B6: =COMPENSATION_STRATEGY!D11 | D6: Training Budget (% of Payroll) | E6: =COMPENSATION_STRATEGY!B23
A7: West | B7: =COMPENSATION_STRATEGY!D12 | D7: Health Insurance (% of Payroll) | E7: =COMPENSATION_STRATEGY!B24
A8: North | B8: =COMPENSATION_STRATEGY!D13 | D8: Profit Sharing (% of Net Profit) | E8: =COMPENSATION_STRATEGY!B25
A9: East | B9: =COMPENSATION_STRATEGY!D14 | D9: Personal Days (per Worker) | E9: =COMPENSATION_STRATEGY!B26
A10: South | B10: =COMPENSATION_STRATEGY!D15 | D10: Union Representatives | E10: =COMPENSATION_STRATEGY!B27
D11: Reduction in Working Hours (%) | E11: =COMPENSATION_STRATEGY!B28
D12: Off-Days for Workers | E12: =COMPENSATION_STRATEGY!B29

Sheet CROSS REFERENCE
A1: CROSS-REFERENCE SUMMARY - Upstream Support
A2: Key metrics from Production and Finance.
A4: Production (Targets)
A5: Total Production Target | B5: 12252
A6: Overtime Hours | B6: 0
A9: Finance (Payroll Budget)
A10: Cash Availability | B10: Check Finance Dashboard
A11: Liquidity Status | B11: 🟡 Excess Cash
