Workbook

Sheet ZONE CALCULATORS
A1: ZONE-SPECIFIC PRODUCTION CALCULATORS
A2: Each zone has its own resources. Resources in Center do NOT count towards West capacity.
A4: ═══ CENTER ZONE ═══
A5: Machines in Zone | B5: 759578
A6: Material Stock (Part A) | B6: 3496
A7: Workers in Zone | B7: 219
A8: Nominal Rate/Machine | B8: 200
A10: Fortnight | B10: Target | C10: Overtime | D10: Local Capacity | E10: Max OT Pot. | F10: Material Cap | G10: REAL OUTPUT | H10: Est. Unit Cost | I10: Shipment?
A11: FN1 | B11: 500 | C11: N | D11: =$B$5*$B$8 | E11: =D11*0.2 | F11: =$B$6 | G11: =MIN(B11, IF(C11="Y", D11+E11, D11), F11) | H11: =IF(C11="Y", 55.439, 35.439) | I11: =IF(B11>F11, "SHIPMENT NEEDED!", "OK")
A12: FN2 | B12: 500 | C12: N | D12: =$B$5*$B$8 | E12: =D12*0.2 | F12: =$B$6 | G12: =MIN(B12, IF(C12="Y", D12+E12, D12), F12) | H12: =IF(C12="Y", 55.439, 35.439) | I12: =IF(B12>F12, "SHIPMENT NEEDED!", "OK")
A13: FN3 | B13: 500 | C13: N | D13: =$B$5*$B$8 | E13: =D13*0.2 | F13: =$B$6 | G13: =MIN(B13, IF(C13="Y", D13+E13, D13), F13) | H13: =IF(C13="Y", 55.439, 35.439) | I13: =IF(B13>F13, "SHIPMENT NEEDED!", "OK")
A14: FN4 | B14: 500 | C14: N | D14: =$B$5*$B$8 | E14: =D14*0.2 | F14: =$B$6 | G14: =MIN(B14, IF(C14="Y", D14+E14, D14), F14) | H14: =IF(C14="Y", 55.439, 35.439) | I14: =IF(B14>F14, "SHIPMENT NEEDED!", "OK")
A15: FN5 | B15: 500 | C15: N | D15: =$B$5*$B$8 | E15: =D15*0.2 | F15: =$B$6 | G15: =MIN(B15, IF(C15="Y", D15+E15, D15), F15) | H15: =IF(C15="Y", 55.439, 35.439) | I15: =IF(B15>F15, "SHIPMENT NEEDED!", "OK")
A16: FN6 | B16: 500 | C16: N | D16: =$B$5*$B$8 | E16: =D16*0.2 | F16: =$B$6 | G16: =MIN(B16, IF(C16="Y", D16+E16, D16), F16) | H16: =IF(C16="Y", 55.439, 35.439) | I16: =IF(B16>F16, "SHIPMENT NEEDED!", "OK")
A17: FN7 | B17: 500 | C17: N | D17: =$B$5*$B$8 | E17: =D17*0.2 | F17: =$B$6 | G17: =MIN(B17, IF(C17="Y", D17+E17, D17), F17) | H17: =IF(C17="Y", 55.439, 35.439) | I17: =IF(B17>F17, "SHIPMENT NEEDED!", "OK")
A18: FN8 | B18: 500 | C18: N | D18: =$B$5*$B$8 | E18: =D18*0.2 | F18: =$B$6 | G18: =MIN(B18, IF(C18="Y", D18+E18, D18), F18) | H18: =IF(C18="Y", 55.439, 35.439) | I18: =IF(B18>F18, "SHIPMENT NEEDED!", "OK")
A19: TOTAL | B19: =SUM(B11:B18) | G19: =SUM(G11:G18)
A39: ═══ WEST ZONE ═══
A40: Machines in Zone | B40: 86
A41: Material Stock (Part A) | B41: 1016
A42: Workers in Zone | B42: 71
A43: Nominal Rate/Machine | B43: 200
A45: Fortnight | B45: Target | C45: Overtime | D45: Local Capacity | E45: Max OT Pot. | F45: Material Cap | G45: REAL OUTPUT | H45: Est. Unit Cost | I45: Shipment?
A46: FN1 | B46: 500 | C46: N | D46: =$B$40*$B$43 | E46: =D46*0.2 | F46: =$B$41 | G46: =MIN(B46, IF(C46="Y", D46+E46, D46), F46) | H46: =IF(C46="Y", 55.439, 35.439) | I46: =IF(B46>F46, "SHIPMENT NEEDED!", "OK")
A47: FN2 | B47: 500 | C47: N | D47: =$B$40*$B$43 | E47: =D47*0.2 | F47: =$B$41 | G47: =MIN(B47, IF(C47="Y", D47+E47, D47), F47) | H47: =IF(C47="Y", 55.439, 35.439) | I47: =IF(B47>F47, "SHIPMENT NEEDED!", "OK")
A48: FN3 | B48: 500 | C48: N | D48: =$B$40*$B$43 | E48: =D48*0.2 | F48: =$B$41 | G48: =MIN(B48, IF(C48="Y", D48+E48, D48), F48) | H48: =IF(C48="Y", 55.439, 35.439) | I48: =IF(B48>F48, "SHIPMENT NEEDED!", "OK")
A49: FN4 | B49: 500 | C49: N | D49: =$B$40*$B$43 | E49: =D49*0.2 | F49: =$B$41 | G49: =MIN(B49, IF(C49="Y", D49+E49, D49), F49) | H49: =IF(C49="Y", 55.439, 35.439) | I49: =IF(B49>F49, "SHIPMENT NEEDED!", "OK")
A50: FN5 | B50: 500 | C50: N | D50: =$B$40*$B$43 | E50: =D50*0.2 | F50: =$B$41 | G50: =MIN(B50, IF(C50="Y", D50+E50, D50), F50) | H50: =IF(C50="Y", 55.439, 35.439) | I50: =IF(B50>F50, "SHIPMENT NEEDED!", "OK")
A51: FN6 | B51: 500 | C51: N | D51: =$B$40*$B$43 | E51: =D51*0.2 | F51: =$B$41 | G51: =MIN(B51, IF(C51="Y", D51+E51, D51), F51) | H51: =IF(C51="Y", 55.439, 35.439) | I51: =IF(B51>F51, "SHIPMENT NEEDED!", "OK")
A52: FN7 | B52: 500 | C52: N | D52: =$B$40*$B$43 | E52: =D52*0.2 | F52: =$B$41 | G52: =MIN(B52, IF(C52="Y", D52+E52, D52), F52) | H52: =IF(C52="Y", 55.439, 35.439) | I52: =IF(B52>F52, "SHIPMENT NEEDED!", "OK")
A53: FN8 | B53: 500 | C53: N | D53: =$B$40*$B$43 | E53: =D53*0.2 | F53: =$B$41 | G53: =MIN(B53, IF(C53="Y", D53+E53, D53), F53) | H53: =IF(C53="Y", 55.439, 35.439) | I53: =IF(B53>F53, "SHIPMENT NEEDED!", "OK")
A54: TOTAL | B54: =SUM(B46:B53) | G54: =SUM(G46:G53)
A74: ═══ NORTH ZONE ═══
A75: Machines in Zone | B75: 78
A76: Material Stock (Part A) | B76: 0
A77: Workers in Zone | B77: 0
A78: Nominal Rate/Machine | B78: 200
A80: Fortnight | B80: Target | C80: Overtime | D80: Local Capacity | E80: Max OT Pot. | F80: Material Cap | G80: REAL OUTPUT | H80: Est. Unit Cost | I80: Shipment?
A81: FN1 | B81: 500 | C81: N | D81: =$B$75*$B$78 | E81: =D81*0.2 | F81: =$B$76 | G81: =MIN(B81, IF(C81="Y", D81+E81, D81), F81) | H81: =IF(C81="Y", 55.439, 35.439) | I81: =IF(B81>F81, "SHIPMENT NEEDED!", "OK")
A82: FN2 | B82: 500 | C82: N | D82: =$B$75*$B$78 | E82: =D82*0.2 | F82: =$B$76 | G82: =MIN(B82, IF(C82="Y", D82+E82, D82), F82) | H82: =IF(C82="Y", 55.439, 35.439) | I82: =IF(B82>F82, "SHIPMENT NEEDED!", "OK")
A83: FN3 | B83: 500 | C83: N | D83: =$B$75*$B$78 | E83: =D83*0.2 | F83: =$B$76 | G83: =MIN(B83, IF(C83="Y", D83+E83, D83), F83) | H83: =IF(C83="Y", 55.439, 35.439) | I83: =IF(B83>F83, "SHIPMENT NEEDED!", "OK")
A84: FN4 | B84: 500 | C84: N | D84: =$B$75*$B$78 | E84: =D84*0.2 | F84: =$B$76 | G84: =MIN(B84, IF(C84="Y", D84+E84, D84), F84) | H84: =IF(C84="Y", 55.439, 35.439) | I84: =IF(B84>F84, "SHIPMENT NEEDED!", "OK")
A85: FN5 | B85: 500 | C85: N | D85: =$B$75*$B$78 | E85: =D85*0.2 | F85: =$B$76 | G85: =MIN(B85, IF(C85="Y", D85+E85, D85), F85) | H85: =IF(C85="Y", 55.439, 35.439) | I85: =IF(B85>F85, "SHIPMENT NEEDED!", "OK")
A86: FN6 | B86: 500 | C86: N | D86: =$B$75*$B$78 | E86: =D86*0.2 | F86: =$B$76 | G86: =MIN(B86, IF(C86="Y", D86+E86, D86), F86) | H86: =IF(C86="Y", 55.439, 35.439) | I86: =IF(B86>F86, "SHIPMENT NEEDED!", "OK")
A87: FN7 | B87: 500 | C87: N | D87: =$B$75*$B$78 | E87: =D87*0.2 | F87: =$B$76 | G87: =MIN(B87, IF(C87="Y", D87+E87, D87), F87) | H87: =IF(C87="Y", 55.439, 35.439) | I87: =IF(B87>F87, "SHIPMENT NEEDED!", "OK")
A88: FN8 | B88: 500 | C88: N | D88: =$B$75*$B$78 | E88: =D88*0.2 | F88: =$B$76 | G88: =MIN(B88, IF(C88="Y", D88+E88, D88), F88) | H88: =IF(C88="Y", 55.439, 35.439) | I88: =IF(B88>F88, "SHIPMENT NEEDED!", "OK")
A89: TOTAL | B89: =SUM(B81:B88) | G89: =SUM(G81:G88)
A109: ═══ EAST ZONE ═══
A110: Machines in Zone | B110: 78
A111: Material Stock (Part A) | B111: 0
A112: Workers in Zone | B112: 0
A113: Nominal Rate/Machine | B113: 200
A115: Fortnight | B115: Target | C115: Overtime | D115: Local Capacity | E115: Max OT Pot. | F115: Material Cap | G115: REAL OUTPUT | H115: Est. Unit Cost | I115: Shipment?
A116: FN1 | B116: 500 | C116: N | D116: =$B$110*$B$113 | E116: =D116*0.2 | F116: =$B$111 | G116: =MIN(B116, IF(C116="Y", D116+E116, D116), F116) | H116: =IF(C116="Y", 55.439, 35.439) | I116: =IF(B116>F116, "SHIPMENT NEEDED!", "OK")
A117: FN2 | B117: 500 | C117: N | D117: =$B$110*$B$113 | E117: =D117*0.2 | F117: =$B$111 | G117: =MIN(B117, IF(C117="Y", D117+E117, D117), F117) | H117: =IF(C117="Y", 55.439, 35.439) | I117: =IF(B117>F117, "SHIPMENT NEEDED!", "OK")
A118: FN3 | B118: 500 | C118: N | D118: =$B$110*$B$113 | E118: =D118*0.2 | F118: =$B$111 | G118: =MIN(B118, IF(C118="Y", D118+E118, D118), F118) | H118: =IF(C118="Y", 55.439, 35.439) | I118: =IF(B118>F118, "SHIPMENT NEEDED!", "OK")
A119: FN4 | B119: 500 | C119: N | D119: =$B$110*$B$113 | E119: =D119*0.2 | F119: =$B$111 | G119: =MIN(B119, IF(C119="Y", D119+E119, D119), F119) | H119: =IF(C119="Y", 55.439, 35.439) | I119: =IF(B119>F119, "SHIPMENT NEEDED!", "OK")
A120: FN5 | B120: 500 | C120: N | D120: =$B$110*$B$113 | E120: =D120*0.2 | F120: =$B$111 | G120: =MIN(B120, IF(C120="Y", D120+E120, D120), F120) | H120: =IF(C120="Y", 55.439, 35.439) | I120: =IF(B120>F120, "SHIPMENT NEEDED!", "OK")
A121: FN6 | B121: 500 | C121: N | D121: =$B$110*$B$113 | E121: =D121*0.2 | F121: =$B$111 | G121: =MIN(B121, IF(C121="Y", D121+E121, D121), F121) | H121: =IF(C121="Y", 55.439, 35.439) | I121: =IF(B121>F121, "SHIPMENT NEEDED!", "OK")
A122: FN7 | B122: 500 | C122: N | D122: =$B$110*$B$113 | E122: =D122*0.2 | F122: =$B$111 | G122: =MIN(B122, IF(C122="Y", D122+E122, D122), F122) | H122: =IF(C122="Y", 55.439, 35.439) | I122: =IF(B122>F122, "SHIPMENT NEEDED!", "OK")
A123: FN8 | B123: 500 | C123: N | D123: =$B$110*$B$113 | E123: =D123*0.2 | F123: =$B$111 | G123: =MIN(B123, IF(C123="Y", D123+E123, D123), F123) | H123: =IF(C123="Y", 55.439, 35.439) | I123: =IF(B123>F123, "SHIPMENT NEEDED!", "OK")
A124: TOTAL | B124: =SUM(B116:B123) | G124: =SUM(G116:G123)
A144: ═══ SOUTH ZONE ═══
A145: Machines in Zone | B145: 60390
A146: Material Stock (Part A) | B146: 0
A147: Workers in Zone | B147: 0
A148: Nominal Rate/Machine | B148: 200
A150: Fortnight | B150: Target | C150: Overtime | D150: Local Capacity | E150: Max OT Pot. | F150: Material Cap | G150: REAL OUTPUT | H150: Est. Unit Cost | I150: Shipment?
A151: FN1 | B151: 500 | C151: N | D151: =$B$145*$B$148 | E151: =D151*0.2 | F151: =$B$146 | G151: =MIN(B151, IF(C151="Y", D151+E151, D151), F151) | H151: =IF(C151="Y", 55.439, 35.439) | I151: =IF(B151>F151, "SHIPMENT NEEDED!", "OK")
A152: FN2 | B152: 500 | C152: N | D152: =$B$145*$B$148 | E152: =D152*0.2 | F152: =$B$146 | G152: =MIN(B152, IF(C152="Y", D152+E152, D152), F152) | H152: =IF(C152="Y", 55.439, 35.439) | I152: =IF(B152>F152, "SHIPMENT NEEDED!", "OK")
A153: FN3 | B153: 500 | C153: N | D153: =$B$145*$B$148 | E153: =D153*0.2 | F153: =$B$146 | G153: =MIN(B153, IF(C153="Y", D153+E153, D153), F153) | H153: =IF(C153="Y", 55.439, 35.439) | I153: =IF(B153>F153, "SHIPMENT NEEDED!", "OK")
A154: FN4 | B154: 500 | C154: N | D154: =$B$145*$B$148 | E154: =D154*0.2 | F154: =$B$146 | G154: =MIN(B154, IF(C154="Y", D154+E154, D154), F154) | H154: =IF(C154="Y", 55.439, 35.439) | I154: =IF(B154>F154, "SHIPMENT NEEDED!", "OK")
A155: FN5 | B155: 500 | C155: N | D155: =$B$145*$B$148 | E155: =D155*0.2 | F155: =$B$146 | G155: =MIN(B155, IF(C155="Y", D155+E155, D155), F155) | H155: =IF(C155="Y", 55.439, 35.439) | I155: =IF(B155>F155, "SHIPMENT NEEDED!", "OK")
A156: FN6 | B156: 500 | C156: N | D156: =$B$145*$B$148 | E156: =D156*0.2 | F156: =$B$146 | G156: =MIN(B156, IF(C156="Y", D156+E156, D156), F156) | H156: =IF(C156="Y", 55.439, 35.439) | I156: =IF(B156>F156, "SHIPMENT NEEDED!", "OK")
A157: FN7 | B157: 500 | C157: N | D157: =$B$145*$B$148 | E157: =D157*0.2 | F157: =$B$146 | G157: =MIN(B157, IF(C157="Y", D157+E157, D157), F157) | H157: =IF(C157="Y", 55.439, 35.439) | I157: =IF(B157>F157, "SHIPMENT NEEDED!", "OK")
A158: FN8 | B158: 500 | C158: N | D158: =$B$145*$B$148 | E158: =D158*0.2 | F158: =$B$146 | G158: =MIN(B158, IF(C158="Y", D158+E158, D158), F158) | H158: =IF(C158="Y", 55.439, 35.439) | I158: =IF(B158>F158, "SHIPMENT NEEDED!", "OK")
A159: TOTAL | B159: =SUM(B151:B158) | G159: =SUM(G151:G158)

Sheet RESOURCE MGR
A1: RESOURCE MANAGER - Zone-by-Zone Asset Allocation
A3: SECTION A: MACHINE ASSIGNMENTS BY ZONE
A5: Zone | B5: Section | C5: Machines Assigned | D5: Workers Needed | E5: Status
A6: Center | B6: Section 1 | C6: 20 | D6: =C6*5 | E6: OK
A7: Center | B7: Section 2 | C7: 20 | D7: =C7*5 | E7: OK
A8: Center | B8: Section 3 | C8: 17 | D8: =C8*5 | E8: OK
A9: Center | B9: Section 4 | C9: 10 | D9: =C9*5 | E9: OK
A10: Center | B10: Section 5 | C10: 10 | D10: =C10*5 | E10: OK
A11: West | B11: Section 1 | C11: 0 | D11: =C11*5 | E11: OK
A12: West | B12: Section 2 | C12: 0 | D12: =C12*5 | E12: OK
A13: West | B13: Section 3 | C13: 0 | D13: =C13*5 | E13: OK
A14: West | B14: Section 4 | C14: 0 | D14: =C14*5 | E14: OK
A15: West | B15: Section 5 | C15: 0 | D15: =C15*5 | E15: OK
A16: North | B16: Section 1 | C16: 0 | D16: =C16*5 | E16: OK
A17: North | B17: Section 2 | C17: 0 | D17: =C17*5 | E17: OK
... A30: South | B30: Section 5 | C30: 0 | D30: =C30*5 | E30: OK
A34: SECTION B: EXPANSION RECOMMENDATIONS BY ZONE
A36: Zone | B36: Target Capacity | C36: Current Machines | D36: Capacity Gap | E36: Recommendation
A37: Center | B37: ='ZONE CALCULATORS'!B19 | C37: 759578 | D37: =B37-(C37*200) | E37: =IF(D37>0, "M1 Opt: "&ROUNDUP(D37/200,0)&" @ $10.6k ea | " &"M3 Opt: "&ROUNDUP(D37/1000,0)&" @ $155.4k ea", "OK")
A38: West | B38: ='ZONE CALCULATORS'!B54 | C38: 86 | D38: =B38-(C38*200) | E38: =IF(D38>0, "M1 Opt: "&ROUNDUP(D38/200,0)&" @ $10.6k ea | " &"M3 Opt: "&ROUNDUP(D38/1000,0)&" @ $155.4k ea", "OK")
A39: North | B39: ='ZONE CALCULATORS'!B89 | C39: 78 | D39: =B39-(C39*200) | E39: =IF(D39>0, "M1 Opt: "&ROUNDUP(D39/200,0)&" @ $10.6k ea | " &"M3 Opt: "&ROUNDUP(D39/1000,0)&" @ $155.4k ea", "OK")
A40: East | B40: ='ZONE CALCULATORS'!B124 | C40: 78 | D40: =B40-(C40*200) | E40: =IF(D40>0, "M1 Opt: "&ROUNDUP(D40/200,0)&" @ $10.6k ea | " &"M3 Opt: "&ROUNDUP(D40/1000,0)&" @ $155.4k ea", "OK")
A41: South | B41: ='ZONE CALCULATORS'!B159 | C41: 60390 | D41: =B41-(C41*200) | E41: =IF(D41>0, "M1 Opt: "&ROUNDUP(D41/200,0)&" @ $10.6k ea | " &"M3 Opt: "&ROUNDUP(D41/1000,0)&" @ $155.4k ea", "OK")
A45: SECTION C: REAL ESTATE (MODULES) BY ZONE
A47: Zone | B47: Machines | C47: Module Slots | D47: Free Slots | E47: Recommendation
A48: Center | B48: 759578 | C48: 0 | D48: =C48-B48 | E48: =IF(D48<5, "Buy module in Center", "OK")
A49: West | B49: 86 | C49: 0 | D49: =C49-B49 | E49: =IF(D49<5, "Buy module in West", "OK")
A50: North | B50: 78 | C50: 0 | D50: =C50-B50 | E50: =IF(D50<5, "Buy module in North", "OK")
A51: East | B51: 78 | C51: 0 | D51: =C51-B51 | E51: =IF(D51<5, "Buy module in East", "OK")
A52: South | B52: 60390 | C52: 0 | D52: =C52-B52 | E52: =IF(D52<5, "Buy module in South", "OK")

Sheet UPLOAD READY PRODUCTION
A1: PRODUCTION DECISIONS - ExSim Upload (Zone-Mapped)
A2: Values linked from Zone Calculators
A4: Production Targets
A5: Zone | B5: Product | C5: Target | D5: Overtime
A6: Center | B6: A | C6: ='ZONE CALCULATORS'!G19 | D6: ='ZONE CALCULATORS'!C11
A7: West | B7: A | C7: ='ZONE CALCULATORS'!G54 | D7: ='ZONE CALCULATORS'!C46
A8: North | B8: A | C8: ='ZONE CALCULATORS'!G89 | D8: ='ZONE CALCULATORS'!C81
A9: East | B9: A | C9: ='ZONE CALCULATORS'!G124 | D9: ='ZONE CALCULATORS'!C116
A10: South | B10: A | C10: ='ZONE CALCULATORS'!G159 | D10: ='ZONE CALCULATORS'!C151
A13: Machine Purchases
A14: Zone | B14: Machine Type | C14: Quantity
A15: Center | B15: M1 | C15: 0
A16: Center | B16: M2 | C16: 0
A17: West | B17: M1 | C17: 0
A18: West | B18: M2 | C18: 0
A19: North | B19: M1 | C19: 0
A20: North | B20: M2 | C20: 0
A21: East | B21: M1 | C21: 0
A22: East | B22: M2 | C22: 0
A23: South | B23: M1 | C23: 0
A24: South | B24: M2 | C24: 0
A27: Section Assignments
A28: Zone | B28: Section | C28: Machines | D28: Workers
A29: Center | B29: Section 1 | C29: ='RESOURCE MGR'!C6 | D29: ='RESOURCE MGR'!D6
A30: Center | B30: Section 2 | C30: ='RESOURCE MGR'!C7 | D30: ='RESOURCE MGR'!D7
A31: Center | B31: Section 3 | C31: ='RESOURCE MGR'!C8 | D31: ='RESOURCE MGR'!D8
A32: Center | B32: Section 4 | C32: ='RESOURCE MGR'!C9 | D32: ='RESOURCE MGR'!D9
A33: Center | B33: Section 5 | C33: ='RESOURCE MGR'!C10 | D33: ='RESOURCE MGR'!D10
A34: West | B34: Section 1 | C34: ='RESOURCE MGR'!C11 | D34: ='RESOURCE MGR'!D11
A35: West | B35: Section 2 | C35: ='RESOURCE MGR'!C12 | D35: ='RESOURCE MGR'!D12
A36: West | B36: Section 3 | C36: ='RESOURCE MGR'!C13 | D36: ='RESOURCE MGR'!D13
A37: West | B37: Section 4 | C37: ='RESOURCE MGR'!C14 | D37: ='RESOURCE MGR'!D14
A38: West | B38: Section 5 | C38: ='RESOURCE MGR'!C15 | D38: ='RESOURCE MGR'!D15
A39: North | B39: Section 1 | C39: ='RESOURCE MGR'!C16 | D39: ='RESOURCE MGR'!D16
A40: North | B40: Section 2 | C40: ='RESOURCE MGR'!C17 | D40: ='RESOURCE MGR'!D17
... A53: South | B53: Section 5 | C53: ='RESOURCE MGR'!C30 | D53: ='RESOURCE MGR'!D30

Sheet CROSS REFERENCE
A1: CROSS-REFERENCE SUMMARY - Upstream Dashboard KPIs
A2: Key metrics from CMO (demand) and CPO (workforce) affecting production planning.
A4: CMO (Marketing) - Demand Forecast
A5: Zone | B5: Demand | C5: Price
A6: Center | B6: 0 | C6: 68
A7: West | B7: 0 | C7: 68
A8: North | B8: 0 | C8: 91
A9: East | B9: 0 | C9: 0
A10: South | B10: 0 | C10: 0
A12: Marketing Spend | B12: 0
A14: CPO (People) - Workforce Available
A15: Zone | B15: Workers | C15: Capacity*
A16: Center | B16: 0 | C16: 0
A17: West | B17: 0 | C17: 0
A18: North | B18: 0 | C18: 0
A19: East | B19: 0 | C19: 0
A20: South | B20: 0 | C20: 0
A22: Total Payroll Forecast | B22: 0
A23: Hiring Costs | B23: 0
A25: * Capacity assumes 50 units/worker/fortnight
