Workbook

Sheet SUPPLIER_CONFIG
A1: SUPPLIER CONFIGURATION
A2: Enter your case study supplier data here. Pre-filled with defaults.
A4: TABLE 1: PARTS SUPPLIERS
A5: Part | B5: Supplier | C5: Lead Time (FN) | D5: Cost/Unit | E5: Payment Terms (FN) | F5: Batch Size
A6: Part A | B6: Supplier A | C6: 0 | D6: 15 | E6: 0 | F6: 0
A7: Part A | B7: Supplier B | C7: 0 | D7: 15 | E7: 0 | F7: 0
A8: Part A | B8: Supplier C | C8: 0 | D8: 15 | E8: 0 | F8: 0
A9: Part B | B9: Supplier A | C9: 0 | D9: 25 | E9: 0 | F9: 0
A10: Part B | B10: Supplier B | C10: 0 | D10: 25 | E10: 0 | F10: 0
A11: Part B | B11: Supplier C | C11: 0 | D11: 25 | E11: 0 | F11: 0
A14: TABLE 2: PIECES CONFIGURATION
A15: Piece Name | B15: Cost/Unit | C15: Batch Size
A16: Piece 1 | B16: 2 | C16: 0
A17: Piece 2 | B17: 2 | C17: 0
A18: Piece 3 | B18: 2 | C18: 0
A19: Piece 4 | B19: 2 | C19: 0
A20: Piece 5 | B20: 2 | C20: 0
A21: Piece 6 | B21: 2 | C21: 0

Sheet COST_ANALYSIS
A1: COST ANALYSIS - Batch Size Efficiency
A3: PREVIOUS PERIOD COSTS
A5: Ordering Cost (Total) | B5: 24244
A6: Holding Cost (Total) | B6: 3572
A7: Total Cost | B7: =B5+B6
A9: EFFICIENCY ANALYSIS
A11: Ordering Cost Ratio | B11: =IF(B7>0, B5/B7, 0)
A13: Efficiency Flag | B13: =IF(B11>0.7,"CRITICAL: Ordering too often. INCREASE BATCH SIZE.",IF(B11<0.3,"CRITICAL: Holding too much. DECREASE BATCH SIZE/JIT.","OK: Balanced"))
A16: STRATEGIC ADVICE
A17: Based on your Ordering Cost Ratio: • > 70%: You're placing too many small orders. Consolidate orders into larger batches. • < 30%: You're holding too much inventory. Consider Just-In-Time ordering or smaller batches. • 30-70%: Good balance between ordering frequency and inventory holding.
A22: MATERIAL COST ANALYZER
A23: Item | B23: Avg Supplier Cost | C23: BOM Target | D23: Variance % | E23: Status
A24: Part A | B24: =AVERAGE(SUPPLIER_CONFIG!D6:D8) | C24: 15 | D24: =IF(C24>0, (B24-C24)/C24, 0) | E24: =IF(B24>C24, "OVER BUDGET", "OK")
A25: Part B | B25: =AVERAGE(SUPPLIER_CONFIG!D9:D11) | C25: 25 | D25: =IF(C25>0, (B25-C25)/C25, 0) | E25: =IF(B25>C25, "OVER BUDGET", "OK")

Sheet MRP_ENGINE
A1: MRP ENGINE - Material Requirements Planning
A3: SECTION A: PRODUCTION DEMAND (Input from Production Manager)
A5: Metric | B5: FN1 | C5: FN2 | D5: FN3 | E5: FN4 | F5: FN5 | G5: FN6 | H5: FN7 | I5: FN8
A6: Target Production | B6: 0 | C6: 0 | D6: 0 | E6: 0 | F6: 0 | G6: 0 | H6: 0 | I6: 0
A9: SECTION B: NET REQUIREMENTS CALCULATION
A11: PART A
A12: Gross Requirement | B12: =$B$6 | C12: =$B$6 | D12: =$B$6 | E12: =$B$6 | F12: =$B$6 | G12: =$B$6 | H12: =$B$6 | I12: =$B$6
A13: Scheduled Arrivals | B13: 0 | C13: 0 | D13: 0 | E13: 0 | F13: 0 | G13: 0 | H13: 0 | I13: 0
A14: Projected Inventory | B14: =0.0+B13-B12 | C14: =B14+C13-C12 | D14: =C14+D13-D12 | E14: =D14+E13-E12 | F14: =E14+F13-F12 | G14: =F14+G13-G12 | H14: =G14+H13-H12 | I14: =H14+I13-I12
A15: Net Deficit (if negative) | B15: =IF(B14<0, -B14, 0) | C15: =IF(C14<0, -C14, 0) | D15: =IF(D14<0, -D14, 0) | E15: =IF(E14<0, -E14, 0) | F15: =IF(F14<0, -F14, 0) | G15: =IF(G14<0, -G14, 0) | H15: =IF(H14<0, -H14, 0) | I15: =IF(I14<0, -I14, 0)
A17: ORDERS FOR PART A
A18: Order Supplier A (Lead:0, Batch:0) | B18: 0 | C18: 0 | D18: 0 | E18: 0 | F18: 0 | G18: 0 | H18: 0 | I18: 0
A19: Order Supplier B (Lead:0, Batch:0) | B19: 0 | C19: 0 | D19: 0 | E19: 0 | F19: 0 | G19: 0 | H19: 0 | I19: 0
A20: Order Supplier C (Lead:0, Batch:0) | B20: 0 | C20: 0 | D20: 0 | E20: 0 | F20: 0 | G20: 0 | H20: 0 | I20: 0
A23: PART B
A24: Gross Requirement | B24: =$B$6 | C24: =$B$6 | D24: =$B$6 | E24: =$B$6 | F24: =$B$6 | G24: =$B$6 | H24: =$B$6 | I24: =$B$6
A25: Scheduled Arrivals | B25: 0 | C25: 0 | D25: 0 | E25: 0 | F25: 0 | G25: 0 | H25: 0 | I25: 0
A26: Projected Inventory | B26: =0.0+B25-B24 | C26: =B26+C25-C24 | D26: =C26+D25-D24 | E26: =D26+E25-E24 | F26: =E26+F25-F24 | G26: =F26+G25-G24 | H26: =G26+H25-H24 | I26: =H26+I25-I24
A27: Net Deficit (if negative) | B27: =IF(B26<0, -B26, 0) | C27: =IF(C26<0, -C26, 0) | D27: =IF(D26<0, -D26, 0) | E27: =IF(E26<0, -E26, 0) | F27: =IF(F26<0, -F26, 0) | G27: =IF(G26<0, -G26, 0) | H27: =IF(H26<0, -H26, 0) | I27: =IF(I26<0, -I26, 0)
A29: ORDERS FOR PART B
A30: Order Supplier A (Lead:0, Batch:0) | B30: 0 | C30: 0 | D30: 0 | E30: 0 | F30: 0 | G30: 0 | H30: 0 | I30: 0
A31: Order Supplier B (Lead:0, Batch:0) | B31: 0 | C31: 0 | D31: 0 | E31: 0 | F31: 0 | G31: 0 | H31: 0 | I31: 0
A32: Order Supplier C (Lead:0, Batch:0) | B32: 0 | C32: 0 | D32: 0 | E32: 0 | F32: 0 | G32: 0 | H32: 0 | I32: 0
A40: Stockout Limit | B40: 0 | C40: 0 | D40: 0 | E40: 0 | F40: 0 | G40: 0 | H40: 0 | I40: 0

Sheet CASH_FLOW_PREVIEW
A1: CASH FLOW PREVIEW - Procurement Spending
A3: ESTIMATED OUTFLOW BY SUPPLIER
A5: Supplier | B5: FN1 | C5: FN2 | D5: FN3 | E5: FN4 | F5: FN5 | G5: FN6 | H5: FN7 | I5: FN8 | J5: Total
A6: Supplier A | B6: =MRP_ENGINE!B18+MRP_ENGINE!B30 | C6: =MRP_ENGINE!C18+MRP_ENGINE!C30 | D6: =MRP_ENGINE!D18+MRP_ENGINE!D30 | E6: =MRP_ENGINE!E18+MRP_ENGINE!E30 | F6: =MRP_ENGINE!F18+MRP_ENGINE!F30 | G6: =MRP_ENGINE!G18+MRP_ENGINE!G30 | H6: =MRP_ENGINE!H18+MRP_ENGINE!H30 | I6: =MRP_ENGINE!I18+MRP_ENGINE!I30 | J6: =SUM(B6:I6)
A7: Supplier B | B7: =MRP_ENGINE!B19+MRP_ENGINE!B31 | C7: =MRP_ENGINE!C19+MRP_ENGINE!C31 | D7: =MRP_ENGINE!D19+MRP_ENGINE!D31 | E7: =MRP_ENGINE!E19+MRP_ENGINE!E31 | F7: =MRP_ENGINE!F19+MRP_ENGINE!F31 | G7: =MRP_ENGINE!G19+MRP_ENGINE!G31 | H7: =MRP_ENGINE!H19+MRP_ENGINE!H31 | I7: =MRP_ENGINE!I19+MRP_ENGINE!I31 | J7: =SUM(B7:I7)
A8: Supplier C | B8: =MRP_ENGINE!B20+MRP_ENGINE!B32 | C8: =MRP_ENGINE!C20+MRP_ENGINE!C32 | D8: =MRP_ENGINE!D20+MRP_ENGINE!D32 | E8: =MRP_ENGINE!E20+MRP_ENGINE!E32 | F8: =MRP_ENGINE!F20+MRP_ENGINE!F32 | G8: =MRP_ENGINE!G20+MRP_ENGINE!G32 | H8: =MRP_ENGINE!H20+MRP_ENGINE!H32 | I8: =MRP_ENGINE!I20+MRP_ENGINE!I32 | J8: =SUM(B8:I8)
A9: TOTAL SPEND | B9: =SUM(B6:B8) | C9: =SUM(C6:C8) | D9: =SUM(D6:D8) | E9: =SUM(E6:E8) | F9: =SUM(F6:F8) | G9: =SUM(G6:G8) | H9: =SUM(H6:H8) | I9: =SUM(I6:I8) | J9: =SUM(B9:I9)
A29: BUDGET TRACKING
A30: Total Budget | B30: 100000
A31: Total Projected Spend | B31: =J9
A32: Remaining Budget | B32: =B30-B31

Sheet UPLOAD_READY_PROCUREMENT
A1: PROCUREMENT DECISIONS - ExSim Upload Format (Side-by-Side)
A2: This matches the exact ExSim Procurement upload layout
A4: Parts | R4: Pieces
A5: Zone | B5: Supplier | C5: Component | D5: 1 | E5: 2 | F5: 3 | G5: 4 | H5: 5 | I5: 6 | J5: 7 | K5: 8 | R5: Zone | S5: Supplier | T5: Component | U5: Order
A6: Center | B6: Supplier A | C6: Part A | D6: =MRP_ENGINE!B18 | E6: =MRP_ENGINE!C18 | F6: =MRP_ENGINE!D18 | G6: =MRP_ENGINE!E18 | H6: =MRP_ENGINE!F18 | I6: =MRP_ENGINE!G18 | J6: =MRP_ENGINE!H18 | K6: =MRP_ENGINE!I18 | R6: Center | S6: Pieces | T6: Piece 1 | U6: 0
A7: Center | B7: Supplier A | C7: Part B | D7: =MRP_ENGINE!B30 | E7: =MRP_ENGINE!C30 | F7: =MRP_ENGINE!D30 | G7: =MRP_ENGINE!E30 | H7: =MRP_ENGINE!F30 | I7: =MRP_ENGINE!G30 | J7: =MRP_ENGINE!H30 | K7: =MRP_ENGINE!I30 | R7: Center | S7: Pieces | T7: Piece 2 | U7: 0
A8: Center | B8: Supplier B | C8: Part A | D8: =MRP_ENGINE!B19 | E8: =MRP_ENGINE!C19 | F8: =MRP_ENGINE!D19 | G8: =MRP_ENGINE!E19 | H8: =MRP_ENGINE!F19 | I8: =MRP_ENGINE!G19 | J8: =MRP_ENGINE!H19 | K8: =MRP_ENGINE!I19 | R8: Center | S8: Pieces | T8: Piece 3 | U8: 0
A9: Center | B9: Supplier B | C9: Part B | D9: =MRP_ENGINE!B31 | E9: =MRP_ENGINE!C31 | F9: =MRP_ENGINE!D31 | G9: =MRP_ENGINE!E31 | H9: =MRP_ENGINE!F31 | I9: =MRP_ENGINE!G31 | J9: =MRP_ENGINE!H31 | K9: =MRP_ENGINE!I31 | R9: Center | S9: Pieces | T9: Piece 4 | U9: 0
A10: Center | B10: Supplier C | C10: Part A | D10: =MRP_ENGINE!B20 | E10: =MRP_ENGINE!C20 | F10: =MRP_ENGINE!D20 | G10: =MRP_ENGINE!E20 | H10: =MRP_ENGINE!F20 | I10: =MRP_ENGINE!G20 | J10: =MRP_ENGINE!H20 | K10: =MRP_ENGINE!I20 | R10: Center | S10: Pieces | T10: Piece 5 | U10: 0
A11: Center | B11: Supplier C | C11: Part B | D11: =MRP_ENGINE!B32 | E11: =MRP_ENGINE!C32 | F11: =MRP_ENGINE!D32 | G11: =MRP_ENGINE!E32 | H11: =MRP_ENGINE!F32 | I11: =MRP_ENGINE!G32 | J11: =MRP_ENGINE!H32 | K11: =MRP_ENGINE!I32 | R11: Center | S11: Pieces | T11: Piece 6 | U11: 0
A12: West | B12: Supplier A | C12: Part A | D12: 0 | E12: 0 | F12: 0 | G12: 0 | H12: 0 | I12: 0 | J12: 0 | K12: 0 | R12: West | S12: Pieces | T12: Piece 1 | U12: 0
A13: West | B13: Supplier A | C13: Part B | D13: 0 | E13: 0 | F13: 0 | G13: 0 | H13: 0 | I13: 0 | J13: 0 | K13: 0 | R13: West | S13: Pieces | T13: Piece 2 | U13: 0
A14: West | B14: Supplier B | C14: Part A | D14: 0 | E14: 0 | F14: 0 | G14: 0 | H14: 0 | I14: 0 | J14: 0 | K14: 0 | R14: West | S14: Pieces | T14: Piece 3 | U14: 0
A15: West | B15: Supplier B | C15: Part B | D15: 0 | E15: 0 | F15: 0 | G15: 0 | H15: 0 | I15: 0 | J15: 0 | K15: 0 | R15: West | S15: Pieces | T15: Piece 4 | U15: 0
A16: West | B16: Supplier C | C16: Part A | D16: 0 | E16: 0 | F16: 0 | G16: 0 | H16: 0 | I16: 0 | J16: 0 | K16: 0 | R16: West | S16: Pieces | T16: Piece 5 | U16: 0
A17: West | B17: Supplier C | C17: Part B | D17: 0 | E17: 0 | F17: 0 | G17: 0 | H17: 0 | I17: 0 | J17: 0 | K17: 0 | R17: West | S17: Pieces | T17: Piece 6 | U17: 0
A18: North | B18: Supplier A | C18: Part A | D18: 0 | E18: 0 | F18: 0 | G18: 0 | H18: 0 | I18: 0 | J18: 0 | K18: 0 | R18: North | S18: Pieces | T18: Piece 1 | U18: 0
A19: North | B19: Supplier A | C19: Part B | D19: 0 | E19: 0 | F19: 0 | G19: 0 | H19: 0 | I19: 0 | J19: 0 | K19: 0 | R19: North | S19: Pieces | T19: Piece 2 | U19: 0
A20: North | B20: Supplier B | C20: Part A | D20: 0 | E20: 0 | F20: 0 | G20: 0 | H20: 0 | I20: 0 | J20: 0 | K20: 0 | R20: North | S20: Pieces | T20: Piece 3 | U20: 0
A21: North | B21: Supplier B | C21: Part B | D21: 0 | E21: 0 | F21: 0 | G21: 0 | H21: 0 | I21: 0 | J21: 0 | K21: 0 | R21: North | S21: Pieces | T21: Piece 4 | U21: 0
A22: North | B22: Supplier C | C22: Part A | D22: 0 | E22: 0 | F22: 0 | G22: 0 | H22: 0 | I22: 0 | J22: 0 | K22: 0 | R22: North | S22: Pieces | T22: Piece 5 | U22: 0
A23: North | B23: Supplier C | C23: Part B | D23: 0 | E23: 0 | F23: 0 | G23: 0 | H23: 0 | I23: 0 | J23: 0 | K23: 0 | R23: North | S23: Pieces | T23: Piece 6 | U23: 0
... A35: South | B35: Supplier C | C35: Part B | D35: 0 | E35: 0 | F35: 0 | G35: 0 | H35: 0 | I35: 0 | J35: 0 | K35: 0 | R35: South | S35: Pieces | T35: Piece 6 | U35: 0
